Workbook

Sheet Packages Working
A1: S.NO. | B1: MODEL | C1: DESCRIPTION | D1: QTY. | E1: DISTRIBUTOR UNIT PRICE (POUND) | F1: DISTRIBUTOR AMOUNT (POUND) | G1: DISC. OFFERED | H1: NET BUYING (AFTER DISC.) | I1: HT COST (x147) | J1: CP (42%) | K1: Hi-Tech Margin | L1: LP (CP x 2) | M1: MRP (LP + 18%)
I2: 147 | J2: 1.42 | L2: 2
A3: 1 | B3: Quantum 112 surface Only | C3: X-Q112-WS | D3: 1 | E3: ='Q1'!F41 -> 9600 | F3: =D3*E3 -> 9600 | G3: 0.15 | H3: =F4-F4*G3 -> 8160 | I3: =H3*$I$2 -> 1199520 | J3: =ROUND(I3*$J$2,-2) -> 1703300 | K3: =(J3-I3)/J3 -> 0.29576704 | L3: =J3*$L$2 -> 3406600 | M3: =L3+L3*18% -> 4019788
F4: =SUM(F3) -> 9600
A6: 2 | B6: Quantum 112 Optic Kit | C6: MOD-Q1-OP-HMA | D6: 1 | E6: ='Q1'!F52 -> 4050 | F6: =D6*E6 -> 4050 | G6: 0.15 | H6: =F7-F7*G6 -> 3442.5 | I6: =H6*$I$2 -> 506047.5 | J6: =ROUND(I6*$J$2,-2) -> 718600 | K6: =(J6-I6)/J6 -> 0.29578695 | L6: =J6*$L$2 -> 1437200 | M6: =L6+L6*18% -> 1695896
F7: =SUM(F6) -> 4050
A9: 3 | B9: Quantum 112 System - MADI (with 1 # Nos of MQ Rack) | C9: X-Q112-WS | D9: 1 | E9: ='Q1'!F41 -> 9600 | F9: =D9*E9 -> 9600 | G9: 0.15 | H9: =F13-F13*G9 -> 13254.202 | I9: =H9*$I$2 -> 1948367.7 | J9: =ROUND(I9*$J$2,-2) -> 2766700 | K9: =(J9-I9)/J9 -> 0.29577921 | L9: =J9*$L$2 -> 5533400 | M9: =L9+L9*18% -> 6529412
C10: FC-Q112 | D10: 1 | E10: ='Q1'!F61 -> 875 | F10: =D10*E10 -> 875
C11: LEADS0049 - 100m BNC cable | D11: 2 | E11: =Racks!F211 -> 61.589257 | F11: =D11*E11 -> 123.17851
C12: X-MQ-RACK | D12: 1 | E12: =Racks!F124 -> 4995 | F12: =D12*E12 -> 4995
F13: =SUM(F9:F12) -> 15593.179
A15: 4 | B15: Quantum 112 System - Optics (with 1 # Nos of SD Rack) | C15: X-Q112-WS | D15: 1 | E15: ='Q1'!F41 -> 9600 | F15: =D15*E15 -> 9600 | G15: 0.15 | H15: =F22-F22*G15 -> 26924.281 | I15: =H15*$I$2 -> 3957869.3 | J15: =ROUND(I15*$J$2,-2) -> 5620200 | K15: =(J15-I15)/J15 -> 0.29577785 | L15: =J15*$L$2 -> 11240400 | M15: =L15*1.18 -> 13263672
C16: FC-Q112 | D16: 1 | E16: ='Q1'!F61 -> 875 | F16: =D16*E16 -> 875
C17: MOD-Q1-OP-HMA | D17: 1 | E17: ='Q1'!F52 -> 4050 | F17: =D17*E17 -> 4050
C18: X-SD-RACK-O | D18: 1 | E18: =Racks!F25 -> 5194.125 | F18: =D18*E18 -> 5194.125
C19: MOD-SDR-ADC32B | D19: 7 | E19: =Racks!F83 -> 895.5 | F19: =D19*E19 -> 6268.5
C20: MOD-SDR-DAC32B | D20: 7 | E20: =Racks!F89 -> 607.5 | F20: =D20*E20 -> 4252.5
C21: OPTIC-DRUM-150 | D21: 1 | E21: =Racks!F227 -> 1435.5 | F21: =D21*E21 -> 1435.5
F22: =SUM(F15:F21) -> 31675.625
A24: 5 | B24: Quantum 225 Single Screen System - MADI (with 1 # Nos of MQ Rack) | C24: X-Q225-WS | D24: 1 | E24: ='Q225'!F55 -> 14470 | F24: =D24*E24 -> 14470 | G24: 0.15 | H24: =F28-F28*G24 -> 18393.15 | I24: =H24*$I$2 -> 2703793.1 | J24: =ROUND(I24*$J$2,-2) -> 3839400 | K24: =(J24-I24)/J24 -> 0.29577719 | L24: =J24*$L$2 -> 7678800 | M24: =L24+L24*18% -> 9060984
C25: FC-Q225 | D25: 1 | E25: ='Q225'!F100 -> 1149 | F25: =D25*E25 -> 1149
C26: MOD-WAVES-Q2 | D26: 1 | E26: ='Q225'!F90 -> 1025 | F26: =D26*E26 -> 1025
C27: X-MQ-RACK | D27: 1 | E27: =Racks!F124 -> 4995 | F27: =D27*E27 -> 4995
F28: =SUM(F24:F27) -> 21639
A30: 6 | B30: Quantum 225 Single Screen System - MADI (with 2 # Nos of MQ Rack) | C30: X-Q225-WS | D30: 1 | E30: ='Q225'!F55 -> 14470 | F30: =D30*E30 -> 14470 | G30: 0.15 | H30: =F34-F34*G30 -> 22638.9 | I30: =H30*$I$2 -> 3327918.3 | J30: =ROUND(I30*$J$2,-2) -> 4725600 | K30: =(J30-I30)/J30 -> 0.29576809 | L30: =J30*$L$2 -> 9451200 | M30: =L30+L30*18% -> 11152416
C31: FC-Q225 | D31: 1 | E31: ='Q225'!F100 -> 1149 | F31: =D31*E31 -> 1149
C32: MOD-WAVES-Q2 | D32: 1 | E32: ='Q225'!F90 -> 1025 | F32: =D32*E32 -> 1025
C33: X-MQ-RACK | D33: 2 | E33: =Racks!F124 -> 4995 | F33: =D33*E33 -> 9990
F34: =SUM(F30:F33) -> 26634
A36: 7 | B36: Quantum 225 Single Screen System - Optics (with 1 # Nos of SD Rack) | C36: X-Q225-WS | D36: 1 | E36: ='Q225'!F55 -> 14470 | F36: =D36*E36 -> 14470 | G36: 0.15 | H36: =F44-F44*G36 -> 32167.931 | I36: =H36*$I$2 -> 4728685.9 | J36: =ROUND(I36*$J$2,-2) -> 6714700 | K36: =(J36-I36)/J36 -> 0.29577109 | L36: =J36*$L$2 -> 13429400 | M36: =L36*1.18 -> 15846692
C37: FC-Q225 | D37: 1 | E37: ='Q225'!F100 -> 1149 | F37: =D37*E37 -> 1149
C38: MOD-WAVES-Q2 | D38: 1 | E38: ='Q225'!F90 -> 1025 | F38: =D38*E38 -> 1025
C39: MOD-Q2-OP-HMA | D39: 1 | E39: ='Q225'!F66 -> 4050 | F39: =D39*E39 -> 4050
C40: X-SD-RACK-O | D40: 1 | E40: =Racks!F25 -> 5194.125 | F40: =D40*E40 -> 5194.125
C41: MOD-SDR-ADC32B | D41: 7 | E41: =Racks!F83 -> 895.5 | F41: =D41*E41 -> 6268.5
C42: MOD-SDR-DAC32B | D42: 7 | E42: =Racks!F89 -> 607.5 | F42: =D42*E42 -> 4252.5
C43: OPTIC-DRUM-150 | D43: 1 | E43: =Racks!F227 -> 1435.5 | F43: =D43*E43 -> 1435.5
F44: =SUM(F36:F43) -> 37844.625
A46: 8 | B46: Quantum 225 Dual Screen System - MADI (with 1 # Nos of MQ Rack) | C46: X-Q225-WS-DS | D46: 1 | E46: ='Q225'!G46 -> 14700 | F46: =D46*E46 -> 14700 | G46: Discount already applied 25% on Surface & 15% on rest | I46: =F50*$I$2 -> 3056666.6 | J46: =ROUND(I46*$J$2,-2) -> 4340500 | K46: =(J46-I46)/J46 -> 0.29578008 | L46: =J46*$L$2 -> 8681000 | M46: =L46+L46*18% -> 10243580
C47: FC-Q225 | D47: 1 | E47: ='Q225'!G100 -> 976.65 | F47: =D47*E47 -> 976.65
C48: MOD-WAVES-Q2 | D48: 1 | E48: ='Q225'!G90 -> 871.25 | F48: =D48*E48 -> 871.25
C49: X-MQ-RACK | D49: 1 | E49: =Racks!G124 -> 4245.75 | F49: =D49*E49 -> 4245.75
F50: =SUM(F46:F49) -> 20793.65
A52: 9 | B52: Quantum 225 Dual Screen System - MADI (with 2 # Nos of MQ Rack) | C52: X-Q225-WS-DS | D52: 1 | E52: ='Q225'!G46 -> 14700 | F52: =D52*E52 -> 14700 | G52: Discount already applied 25% on Surface & 15% on rest | I52: =F56*$I$2 -> 3680791.8 | J52: =ROUND(I52*$J$2,-2) -> 5226700 | K52: =(J52-I52)/J52 -> 0.29577137 | L52: =J52*$L$2 -> 10453400 | M52: =L52+L52*18% -> 12335012
C53: FC-Q225 | D53: 1 | E53: ='Q225'!G100 -> 976.65 | F53: =D53*E53 -> 976.65
C54: MOD-WAVES-Q2 | D54: 1 | E54: ='Q225'!G90 -> 871.25 | F54: =D54*E54 -> 871.25
C55: X-MQ-RACK | D55: 2 | E55: =Racks!G124 -> 4245.75 | F55: =D55*E55 -> 8491.5
F56: =SUM(F52:F55) -> 25039.4
A59: 10 | B59: Quantum 225 Dual Screen System - Optics (with 1 # Nos of SD Rack) | C59: X-Q225-WS-DS | D59: 1 | E59: ='Q225'!G46 -> 14700 | F59: =D59*E59 -> 14700 | G59: Discount already applied 25% on Surface, 15% on Q225 elements and SD rack cards & 20% on SD Rack and drum | I59: =F67*$I$2 -> 5032831.7 | J59: =ROUND(I59*$J$2,-2) -> 7146600 | K59: =(J59-I59)/J59 -> 0.29577258 | L59: =J59*$L$2 -> 14293200 | M59: =L59*1.18 -> 16865976
C60: FC-Q225 | D60: 1 | E60: ='Q225'!G100 -> 976.65 | F60: =D60*E60 -> 976.65
C61: MOD-WAVES-Q2 | D61: 1 | E61: ='Q225'!G90 -> 871.25 | F61: =D61*E61 -> 871.25
C62: MOD-Q2-OP-HMA | D62: 1 | E62: ='Q225'!G66 -> 3442.5 | F62: =D62*E62 -> 3442.5
C63: X-SD-RACK-O | D63: 1 | E63: =Racks!G25 -> 4155.3 | F63: =D63*E63 -> 4155.3
C64: MOD-SDR-ADC32B | D64: 7 | E64: =Racks!G83 -> 761.175 | F64: =D64*E64 -> 5328.225
C65: MOD-SDR-DAC32B | D65: 7 | E65: =Racks!G89 -> 516.375 | F65: =D65*E65 -> 3614.625
C66: OPTIC-DRUM-150 | D66: 1 | E66: =Racks!G227 -> 1148.4 | F66: =D66*E66 -> 1148.4
F67: =SUM(F59:F66) -> 34236.95
A69: 11 | B69: Quantum 326 surface - HMA optics with #1 SD Rack | C69: X-Q326-WS-OP | D69: 1 | E69: ='Q 3'!F76 -> 31196 | F69: =D69*E69 -> 31196 | G69: 0.2 | H69: =F76-F76*G69 -> 40457.3 | I69: =H69*$I$2 -> 5947223.1 | J69: =ROUND(I69*$J$2,-2) -> 8445100 | K69: =(J69-I69)/J69 -> 0.29577825 | L69: =J69*$L$2 -> 16890200 | M69: =L69+L69*18% -> 19930436
C70: FC-Q326 | D70: 1 | E70: ='Q 3'!F135 -> 1200 | F70: =D70*E70 -> 1200
C71: MOD-WAVES-Q3 | D71: 1 | E71: ='Q 3'!F126 -> 1025 | F71: =D71*E71 -> 1025
C72: OPTIC-DRUM-150 | D72: 1 | E72: =Racks!F227 -> 1435.5 | F72: =D72*E72 -> 1435.5
C73: X-SD-RACK-O | D73: 1 | E73: =Racks!F25 -> 5194.125 | F73: =D73*E73 -> 5194.125
C74: MOD-SDR-ADC32B | D74: 7 | E74: =Racks!F83 -> 895.5 | F74: =D74*E74 -> 6268.5
C75: MOD-SDR-DAC32B | D75: 7 | E75: =Racks!F89 -> 607.5 | F75: =D75*E75 -> 4252.5
F76: =SUM(F69:F75) -> 50571.625
A78: 12 | B78: Quantum 338 surface - HMA optics with #1 SD Rack | C78: X-Q338-WS-OP | D78: 1 | E78: ='Q 3'!F40 -> 35634.375 | F78: =D78*E78 -> 35634.375 | G78: 0.2 | H78: =F85-F85*G78 -> 44247.2 | I78: =H78*$I$2 -> 6504338.4 | J78: =ROUND(I78*$J$2,-2) -> 9236200 | K78: =(J78-I78)/J78 -> 0.29577766 | L78: =J78*$L$2 -> 18472400 | M78: =L78+L78*18% -> 21797432
C79: FC-Q338 | D79: 1 | E79: ='Q 3'!F132 -> 1499 | F79: =D79*E79 -> 1499
C80: MOD-WAVES-Q3 | D80: 1 | E80: ='Q 3'!F123 -> 1025 | F80: =D80*E80 -> 1025
C81: OPTIC-DRUM-150 | D81: 1 | E81: =Racks!F227 -> 1435.5 | F81: =D81*E81 -> 1435.5
C82: X-SD-RACK-O | D82: 1 | E82: =Racks!F25 -> 5194.125 | F82: =D82*E82 -> 5194.125
C83: MOD-SDR-ADC32B | D83: 7 | E83: =Racks!F83 -> 895.5 | F83: =D83*E83 -> 6268.5
C84: MOD-SDR-DAC32B | D84: 7 | E84: =Racks!F89 -> 607.5 | F84: =D84*E84 -> 4252.5
F85: =SUM(F78:F84) -> 55309
A87: 13 | B87: DiGiCo Quantum 852 surface - MADI / HMA optics | C87: X-Q852-WS-OP | D87: 1 | E87: ='Q 852'!F31 -> 97950 | F87: =D87*E87 -> 97950 | G87: 0.2 | H87: =F88-F88*G87 -> 78360 | I87: =H87*$I$2 -> 11518920 | J87: =ROUND(I87*$J$2,-2) -> 16356900 | K87: =(J87-I87)/J87 -> 0.29577609 | L87: =J87*$L$2 -> 32713800 | M87: =L87+L87*18% -> 38602284
F88: =SUM(F87) -> 97950
A90: 14 | B90: Quantum 852 surface - HMA optics with #1 SD Rack | C90: X-Q852-WS-OP | D90: 1 | E90: ='Q 852'!F31 -> 97950 | F90: =D90*E90 -> 97950 | G90: 0.2 | H90: =F97-F97*G90 -> 95200.5 | I90: =H90*$I$2 -> 13994474 | J90: =ROUND(I90*$J$2,-2) -> 19872200 | K90: =(J90-I90)/J90 -> 0.29577634 | L90: =J90*$L$2 -> 39744400 | M90: =L90+L90*18% -> 46898392
C91: FC-Q852 | D91: 1 | E91: ='Q 852'!F79 -> 1850 | F91: =D91*E91 -> 1850
C92: MOD-WAVES-Q852 | D92: 2 | E92: ='Q 852'!F70 -> 1025 | F92: =D92*E92 -> 2050
C93: OPTIC-DRUM-150 | D93: 1 | E93: =Racks!F227 -> 1435.5 | F93: =D93*E93 -> 1435.5
C94: X-SD-RACK-O | D94: 1 | E94: =Racks!F25 -> 5194.125 | F94: =D94*E94 -> 5194.125
C95: MOD-SDR-ADC32B | D95: 7 | E95: =Racks!F83 -> 895.5 | F95: =D95*E95 -> 6268.5
C96: MOD-SDR-DAC32B | D96: 7 | E96: =Racks!F89 -> 607.5 | F96: =D96*E96 -> 4252.5
F97: =SUM(F90:F96) -> 119000.62
A99: 15 | B99: SD10 with 2# D2 Rack | C99: X-SD10-WS | D99: 1 | E99: ='SD 10'!F31 -> 22248 | F99: =D99*E99 -> 22248 | G99: 10800 | H99: =F104-G99 -> 22103.214 | I99: =H99*$I$2 -> 3249172.5 | J99: =ROUND(I99*$J$2,-2) -> 4613800 | K99: =(J99-I99)/J99 -> 0.29577085 | L99: =J99*$L$2 -> 9227600 | M99: =L99*1.18 -> 10888568
C100: MOD-WAVES-SD10 | D100: 1 | E100: ='SD 10'!F117 -> 1025 | F100: =D100*E100 -> 1025
C101: FC-SD10 | D101: 1 | E101: ='SD 10'!F135 -> 1249 | F101: =D101*E101 -> 1249
C102: X-D2-DI-M | D102: 2 | E102: =Racks!F146 -> 3944.25 | F102: =D102*E102 -> 7888.5
C103: LEADS0049 - 100m BNC cable | D103: 8 | E103: =Racks!F211 -> 61.589257 | F103: =D103*E103 -> 492.71406
F104: =SUM(F99:F103) -> 32903.214
A106: 16 | B106: SD10 with 2# MQ Rack | C106: X-SD10-WS | D106: 1 | E106: ='SD 10'!F31 -> 22248 | F106: =D106*E106 -> 22248 | G106: 10800 | H106: =F111-G106 -> 24204.714 | I106: =H106*$I$2 -> 3558093 | J106: =ROUND(I106*$J$2,-2) -> 5052500 | K106: =(J106-I106)/J106 -> 0.29577576 | L106: =J106*$L$2 -> 10105000 | M106: =L106*1.18 -> 11923900
C107: MOD-WAVES-SD10 | D107: 1 | E107: ='SD 10'!F117 -> 1025 | F107: =D107*E107 -> 1025
C108: FC-SD10 | D108: 1 | E108: ='SD 10'!F135 -> 1249 | F108: =D108*E108 -> 1249
C109: X-MQ-RACK | D109: 2 | E109: =Racks!F124 -> 4995 | F109: =D109*E109 -> 9990
C110: LEADS0049 - 100m BNC cable | D110: 8 | E110: =Racks!F211 -> 61.589257 | F110: =D110*E110 -> 492.71406
F111: =SUM(F106:F110) -> 35004.714
A113: 17 | B113: SD10 with 1# SD Rack | C113: X-SD10-WS | D113: 1 | E113: ='SD 10'!F31 -> 22248 | F113: =D113*E113 -> 22248 | G113: 10800 | H113: =F121-G113 -> 34922.625 | I113: =H113*$I$2 -> 5133625.9 | J113: =ROUND(I113*$J$2,-2) -> 7289700 | K113: =(J113-I113)/J113 -> 0.29576994 | L113: =J113*$L$2 -> 14579400 | M113: =L113*1.18 -> 17203692
C114: MOD-WAVES-SD10 | D114: 1 | E114: ='SD 10'!F117 -> 1025 | F114: =D114*E114 -> 1025
C115: FC-SD10 | D115: 1 | E115: ='SD 10'!F135 -> 1249 | F115: =D115*E115 -> 1249
C116: MOD-SD10-OPTO | D116: 1 | E116: ='SD 10'!F105 -> 4050 | F116: =D116*E116 -> 4050
C117: OPTIC-DRUM-150 | D117: 1 | E117: =Racks!F227 -> 1435.5 | F117: =D117*E117 -> 1435.5
...

Sheet Q225
B2: DiGiCo Quantum 2 Distributor Price List
B4: Apr 2026
B6: Unit 10 Silverglade Business Park, Leatherhead Road
B7: Chessington, Surrey, KT9 2QL
B8: Tel; +44 1372 845600
B9: Fax; +44 1372 845656
B10: email; sales@digiconsoles.com
B11: web; www.digiconsoles.com
B13: FCA Glenrothes KY7 4NX. E&OE. Prices, Products and Specification are subject to change without notice.
B14: This price list supercedes all previous price lists.
A16: Product Code | B16: Description | E16: List (£) | F16: Distributor (£) | G16: Disc. (15%) | H16: HT Buy (INR) | I16: Customer Price | J16: Hi-Tech
G17: 0.15 | H17: 147 | I17: 1.42 | J17: Margin
A18: DiGiCo Quantum 225 Systems
B20: DiGiCo Quantum 225 system - MADI | E20: =ROUND(F20/0.55,0) -> 31935 | F20: 17564 | G20: =IF(F20-F20*$G$17=0,"",F20-F20*$G$17) -> 14929.4 | H20: =IFERROR(G20*$H$17,"") -> 2194621.8 | I20: =IFERROR(ROUND(H20*$I$17,0),"") -> 3116363 | J20: =IFERROR((I20-H20)/I20,"") -> 0.29577466
B21: 1 x Quantum 225 surface - 24+1 faders, 2 DMI slots, USB Audio I/O, 4 BNC MADI, 2 PSU, 2 GPIO | G21: =IF(F21-F21*$G$17=0,"",F21-F21*$G$17) | H21: =IFERROR(G21*$H$17,"") | I21: =IFERROR(ROUND(H21*$I$17,0),"") | J21: =IFERROR((I21-H21)/I21,"")
B22: 72 mono input channels, 36 mono output busses, | G22: =IF(F22-F22*$G$17=0,"",F22-F22*$G$17) | H22: =IFERROR(G22*$H$17,"") | I22: =IFERROR(ROUND(H22*$I$17,0),"") | J22: =IFERROR((I22-H22)/I22,"")
B23: 2 mono or stereo solo busses. LR or LCR master buss | G23: =IF(F23-F23*$G$17=0,"",F23-F23*$G$17) | H23: =IFERROR(G23*$H$17,"") | I23: =IFERROR(ROUND(H23*$I$17,0),"") | J23: =IFERROR((I23-H23)/I23,"")
B24: 12 x 12 matrix, 12 CG/VCA, 12 FX, 16 x 32 band graphic eq’s | G24: =IF(F24-F24*$G$17=0,"",F24-F24*$G$17) | H24: =IFERROR(G24*$H$17,"") | I24: =IFERROR(ROUND(H24*$I$17,0),"") | J24: =IFERROR((I24-H24)/I24,"")
B25: 32 Nodal Processors, 24 Mustard Processors, 6 Spice FX | G25: =IF(F25-F25*$G$17=0,"",F25-F25*$G$17) | H25: =IFERROR(G25*$H$17,"") | I25: =IFERROR(ROUND(H25*$I$17,0),"") | J25: =IFERROR((I25-H25)/I25,"")
B26: Local I/O 8 x Mic/Line inputs, 8 x Line outputs, 8 x AES I/O mono stream, mounting bracket, dust cover, carton | G26: =IF(F26-F26*$G$17=0,"",F26-F26*$G$17) | H26: =IFERROR(G26*$H$17,"") | I26: =IFERROR(ROUND(H26*$I$17,0),"") | J26: =IFERROR((I26-H26)/I26,"")
B27: 1 x Quantum MADI Rack, 2 BNC MADI, dual PSU - 48 mic/line in / up to 24 line out / up to 8 AES output (mono), carton | G27: =IF(F27-F27*$G$17=0,"",F27-F27*$G$17) | H27: =IFERROR(G27*$H$17,"") | I27: =IFERROR(ROUND(H27*$I$17,0),"") | J27: =IFERROR((I27-H27)/I27,"")
B28: 2 x 100m BNC Cables | G28: =IF(F28-F28*$G$17=0,"",F28-F28*$G$17) | H28: =IFERROR(G28*$H$17,"") | I28: =IFERROR(ROUND(H28*$I$17,0),"") | J28: =IFERROR((I28-H28)/I28,"")
G29: =IF(F29-F29*$G$17=0,"",F29-F29*$G$17) | H29: =IFERROR(G29*$H$17,"") | I29: =IFERROR(ROUND(H29*$I$17,0),"") | J29: =IFERROR((I29-H29)/I29,"")
B30: DiGiCo Quantum 225 system - DANTE | E30: =ROUND(F30/0.55,0) -> 33751 | F30: 18563 | G30: =IF(F30-F30*$G$17=0,"",F30-F30*$G$17) -> 15778.55 | H30: =IFERROR(G30*$H$17,"") -> 2319446.9 | I30: =IFERROR(ROUND(H30*$I$17,0),"") -> 3293615 | J30: =IFERROR((I30-H30)/I30,"") -> 0.29577475
B31: 1 x Quantum 225 surface - 24+1 faders, 2 DMI slots, USB Audio I/O, 4 BNC MADI, 2 PSU, 2 GPIO | G31: =IF(F31-F31*$G$17=0,"",F31-F31*$G$17) | H31: =IFERROR(G31*$H$17,"") | I31: =IFERROR(ROUND(H31*$I$17,0),"") | J31: =IFERROR((I31-H31)/I31,"")
B32: 72 mono input channels, 36 mono output busses, | G32: =IF(F32-F32*$G$17=0,"",F32-F32*$G$17) | H32: =IFERROR(G32*$H$17,"") | I32: =IFERROR(ROUND(H32*$I$17,0),"") | J32: =IFERROR((I32-H32)/I32,"")
B33: 2 mono or stereo solo busses. LR or LCR master buss | G33: =IF(F33-F33*$G$17=0,"",F33-F33*$G$17) | H33: =IFERROR(G33*$H$17,"") | I33: =IFERROR(ROUND(H33*$I$17,0),"") | J33: =IFERROR((I33-H33)/I33,"")
B34: 12 x 12 matrix, 12 CG/VCA, 12 FX, 16 x 32 band graphic eq’s | G34: =IF(F34-F34*$G$17=0,"",F34-F34*$G$17) | H34: =IFERROR(G34*$H$17,"") | I34: =IFERROR(ROUND(H34*$I$17,0),"") | J34: =IFERROR((I34-H34)/I34,"")
B35: 32 Nodal Processors, 24 Mustard Processors, 6 Spice FX | G35: =IF(F35-F35*$G$17=0,"",F35-F35*$G$17) | H35: =IFERROR(G35*$H$17,"") | I35: =IFERROR(ROUND(H35*$I$17,0),"") | J35: =IFERROR((I35-H35)/I35,"")
B36: Local I/O 8 x Mic/Line inputs, 8 x Line outputs, 8 x AES I/O mono stream, mounting bracket, dust cover, carton | G36: =IF(F36-F36*$G$17=0,"",F36-F36*$G$17) | H36: =IFERROR(G36*$H$17,"") | I36: =IFERROR(ROUND(H36*$I$17,0),"") | J36: =IFERROR((I36-H36)/I36,"")
B37: 1 x DMI Dante 64@96 SRC I/O card, 2 etherCON, 1 RJ45 | G37: =IF(F37-F37*$G$17=0,"",F37-F37*$G$17) | H37: =IFERROR(G37*$H$17,"") | I37: =IFERROR(ROUND(H37*$I$17,0),"") | J37: =IFERROR((I37-H37)/I37,"") | M37: 3
B38: 1 x Quantum Dante Rack, 2 etherCON, dual PSU - 48 mic/line in / up to 24 line out / up to 8 AES output (mono), carton | G38: =IF(F38-F38*$G$17=0,"",F38-F38*$G$17) | H38: =IFERROR(G38*$H$17,"") | I38: =IFERROR(ROUND(H38*$I$17,0),"") | J38: =IFERROR((I38-H38)/I38,"") | M38: 8.25
B39: 1 x 75m CAT6 Cable | G39: =IF(F39-F39*$G$17=0,"",F39-F39*$G$17) | H39: =IFERROR(G39*$H$17,"") | I39: =IFERROR(ROUND(H39*$I$17,0),"") | J39: =IFERROR((I39-H39)/I39,"") | M39: 1
G40: =IF(F40-F40*$G$17=0,"",F40-F40*$G$17) | H40: =IFERROR(G40*$H$17,"") | I40: =IFERROR(ROUND(H40*$I$17,0),"") | J40: =IFERROR((I40-H40)/I40,"")
B41: The product codes for Q225 systems no longer exist. Please order as seperates: X-Q225-WS and X-MQ or X-DQ. | G41: =IF(F41-F41*$G$17=0,"",F41-F41*$G$17) | H41: =IFERROR(G41*$H$17,"") | I41: =IFERROR(ROUND(H41*$I$17,0),"") | J41: =IFERROR((I41-H41)/I41,"")
B42: A system discount will be applied to the Rack to ensure the System price remains the same. | G42: =IF(F42-F42*$G$17=0,"",F42-F42*$G$17) | H42: =IFERROR(G42*$H$17,"") | I42: =IFERROR(ROUND(H42*$I$17,0),"") | J42: =IFERROR((I42-H42)/I42,"")
G43: =IF(F43-F43*$G$17=0,"",F43-F43*$G$17) | H43: =IFERROR(G43*$H$17,"") | I43: =IFERROR(ROUND(H43*$I$17,0),"") | J43: =IFERROR((I43-H43)/I43,"")
A44: DiGiCo Quantum 225 Surface | G44: =IF(F44-F44*$G$17=0,"",F44-F44*$G$17) | H44: =IFERROR(G44*$H$17,"") | I44: =IFERROR(ROUND(H44*$I$17,0),"") | J44: =IFERROR((I44-H44)/I44,"")
G45: =IF(F45-F45*$G$17=0,"",F45-F45*$G$17) | H45: =IFERROR(G45*$H$17,"") | I45: =IFERROR(ROUND(H45*$I$17,0),"") | J45: =IFERROR((I45-H45)/I45,"")
A46: X-Q225-WS-DS | B46: DiGiCo Quantum 225 dual screen surface | E46: =ROUND(F46/0.55,0) -> 35636 | F46: 19600 | G46: =IF(F46-F46*25%=0,"",F46-F46*25%) -> 14700 | H46: =IFERROR(G46*$H$17,"") -> 2160900 | I46: =IFERROR(ROUND(H46*$I$17,0),"") -> 3068478 | J46: =IFERROR((I46-H46)/I46,"") -> 0.29577465
B47: Quantum 225 dual screen surface - 24+1 faders, 2 DMI slots, USB Audio I/O, 4 BNC MADI, 2 PSU, 2 GPIO | H47: =IFERROR(G47*$H$17,"") -> 0 | I47: =IFERROR(ROUND(H47*$I$17,0),"") -> 0 | J47: =IFERROR((I47-H47)/I47,"")
B48: 72 mono input channels, 36 mono output busses, | G48: =IF(F48-F48*$G$17=0,"",F48-F48*$G$17) | H48: =IFERROR(G48*$H$17,"") | I48: =IFERROR(ROUND(H48*$I$17,0),"") | J48: =IFERROR((I48-H48)/I48,"") | M48: DS Surface
B49: 2 mono or stereo solo busses. LR or LCR master buss | G49: =IF(F49-F49*$G$17=0,"",F49-F49*$G$17) | H49: =IFERROR(G49*$H$17,"") | I49: =IFERROR(ROUND(H49*$I$17,0),"") | J49: =IFERROR((I49-H49)/I49,"") | M49: 1 MQ rack
B50: 12 x 12 matrix, 12 CG/VCA, 12 FX, 16 x 32 band graphic eq’s | G50: =IF(F50-F50*$G$17=0,"",F50-F50*$G$17) | H50: =IFERROR(G50*$H$17,"") | I50: =IFERROR(ROUND(H50*$I$17,0),"") | J50: =IFERROR((I50-H50)/I50,"") | M50: FC
B51: 32 Nodal Processors, 24 Mustard Processors, 6 Spice FX | G51: =IF(F51-F51*$G$17=0,"",F51-F51*$G$17) | H51: =IFERROR(G51*$H$17,"") | I51: =IFERROR(ROUND(H51*$I$17,0),"") | J51: =IFERROR((I51-H51)/I51,"") | M51: Wave card
B52: Local I/O 8 x Mic/Line inputs, 8 x Line outputs, 8 x AES I/O mono stream, mounting bracket, dust cover, carton | G52: =IF(F52-F52*$G$17=0,"",F52-F52*$G$17) | H52: =IFERROR(G52*$H$17,"") | I52: =IFERROR(ROUND(H52*$I$17,0),"") | J52: =IFERROR((I52-H52)/I52,"")
B53: Dimensions; 1124(w) x 801(d) x 436(h) mm Weight; 44.64kg | G53: =IF(F53-F53*$G$17=0,"",F53-F53*$G$17) | H53: =IFERROR(G53*$H$17,"") | I53: =IFERROR(ROUND(H53*$I$17,0),"") | J53: =IFERROR((I53-H53)/I53,"")
G54: =IF(F54-F54*$G$17=0,"",F54-F54*$G$17) | H54: =IFERROR(G54*$H$17,"") | I54: =IFERROR(ROUND(H54*$I$17,0),"") | J54: =IFERROR((I54-H54)/I54,"")
A55: X-Q225-WS | B55: DiGiCo Quantum 225 surface | E55: =ROUND(F55/0.55,0) -> 26309 | F55: 14470 | G55: =IF(F55-F55*$G$17=0,"",F55-F55*$G$17) -> 12299.5 | H55: =IFERROR(G55*$H$17,"") -> 1808026.5 | I55: =IFERROR(ROUND(H55*$I$17,0),"") -> 2567398 | J55: =IFERROR((I55-H55)/I55,"") -> 0.29577475
B56: Quantum 225 single screen surface - 24+1 faders, 2 DMI slots, USB Audio I/O, 4 BNC MADI, 2 PSU, 2 GPIO | G56: =IF(F56-F56*$G$17=0,"",F56-F56*$G$17) | H56: =IFERROR(G56*$H$17,"") | I56: =IFERROR(ROUND(H56*$I$17,0),"") | J56: =IFERROR((I56-H56)/I56,"")
B57: 72 mono input channels, 36 mono output busses, | G57: =IF(F57-F57*$G$17=0,"",F57-F57*$G$17) | H57: =IFERROR(G57*$H$17,"") | I57: =IFERROR(ROUND(H57*$I$17,0),"") | J57: =IFERROR((I57-H57)/I57,"")
B58: 2 mono or stereo solo busses. LR or LCR master buss | G58: =IF(F58-F58*$G$17=0,"",F58-F58*$G$17) | H58: =IFERROR(G58*$H$17,"") | I58: =IFERROR(ROUND(H58*$I$17,0),"") | J58: =IFERROR((I58-H58)/I58,"")
B59: 12 x 12 matrix, 12 CG/VCA, 12 FX, 16 x 32 band graphic eq’s | G59: =IF(F59-F59*$G$17=0,"",F59-F59*$G$17) | H59: =IFERROR(G59*$H$17,"") | I59: =IFERROR(ROUND(H59*$I$17,0),"") | J59: =IFERROR((I59-H59)/I59,"")
B60: 32 Nodal Processors, 24 Mustard Processors, 6 Spice FX | G60: =IF(F60-F60*$G$17=0,"",F60-F60*$G$17) | H60: =IFERROR(G60*$H$17,"") | I60: =IFERROR(ROUND(H60*$I$17,0),"") | J60: =IFERROR((I60-H60)/I60,"")
B61: Local I/O 8 x Mic/Line inputs, 8 x Line outputs, 8 x AES I/O mono stream, mounting bracket, dust cover, carton | G61: =IF(F61-F61*$G$17=0,"",F61-F61*$G$17) | H61: =IFERROR(G61*$H$17,"") | I61: =IFERROR(ROUND(H61*$I$17,0),"") | J61: =IFERROR((I61-H61)/I61,"")
B62: Dimensions; 1124(w) x 801(d) x 436(h) mm Weight; 43.00kg | G62: =IF(F62-F62*$G$17=0,"",F62-F62*$G$17) | H62: =IFERROR(G62*$H$17,"") | I62: =IFERROR(ROUND(H62*$I$17,0),"") | J62: =IFERROR((I62-H62)/I62,"")
G63: =IF(F63-F63*$G$17=0,"",F63-F63*$G$17) | H63: =IFERROR(G63*$H$17,"") | I63: =IFERROR(ROUND(H63*$I$17,0),"") | J63: =IFERROR((I63-H63)/I63,"")
A64: DiGiCo Quantum 225 Surface Options | G64: =IF(F64-F64*$G$17=0,"",F64-F64*$G$17) | H64: =IFERROR(G64*$H$17,"") | I64: =IFERROR(ROUND(H64*$I$17,0),"") | J64: =IFERROR((I64-H64)/I64,"")
G65: =IF(F65-F65*$G$17=0,"",F65-F65*$G$17) | H65: =IFERROR(G65*$H$17,"") | I65: =IFERROR(ROUND(H65*$I$17,0),"") | J65: =IFERROR((I65-H65)/I65,"")
A66: MOD-Q2-OP-HMA | B66: DiGiCo Quantum 225 Optocore interface (HMA) | E66: =ROUND(F66/0.55,0) -> 7364 | F66: 4050 | G66: =IF(F66-F66*$G$17=0,"",F66-F66*$G$17) -> 3442.5 | H66: =IFERROR(G66*$H$17,"") -> 506047.5 | I66: =IFERROR(ROUND(H66*$I$17,0),"") -> 718587 | J66: =IFERROR((I66-H66)/I66,"") -> 0.29577421
B67: Factory fitted HMA expanded beam optics upgrade for surface | G67: =IF(F67-F67*$G$17=0,"",F67-F67*$G$17) | H67: =IFERROR(G67*$H$17,"") | I67: =IFERROR(ROUND(H67*$I$17,0),"") | J67: =IFERROR((I67-H67)/I67,"")
G68: =IF(F68-F68*$G$17=0,"",F68-F68*$G$17) | H68: =IFERROR(G68*$H$17,"") | I68: =IFERROR(ROUND(H68*$I$17,0),"") | J68: =IFERROR((I68-H68)/I68,"")
A69: MOD-Q2-OP-NC | B69: DiGiCo Quantum 225 Optocore interface (NC) | E69: =ROUND(F69/0.55,0) -> 6251 | F69: 3438 | G69: =IF(F69-F69*$G$17=0,"",F69-F69*$G$17) -> 2922.3 | H69: =IFERROR(G69*$H$17,"") -> 429578.1 | I69: =IFERROR(ROUND(H69*$I$17,0),"") -> 610001 | J69: =IFERROR((I69-H69)/I69,"") -> 0.29577476
B70: Factory fitted NC optics upgrade for surface | G70: =IF(F70-F70*$G$17=0,"",F70-F70*$G$17) | H70: =IFERROR(G70*$H$17,"") | I70: =IFERROR(ROUND(H70*$I$17,0),"") | J70: =IFERROR((I70-H70)/I70,"")
G71: =IF(F71-F71*$G$17=0,"",F71-F71*$G$17) | H71: =IFERROR(G71*$H$17,"") | I71: =IFERROR(ROUND(H71*$I$17,0),"") | J71: =IFERROR((I71-H71)/I71,"")
A72: MOD-Q2-OP-ST | B72: DiGiCo Quantum 225 Optocore intercace (ST) | E72: =ROUND(F72/0.55,0) -> 6038 | F72: 3321 | G72: =IF(F72-F72*$G$17=0,"",F72-F72*$G$17) -> 2822.85 | H72: =IFERROR(G72*$H$17,"") -> 414958.95 | I72: =IFERROR(ROUND(H72*$I$17,0),"") -> 589242 | J72: =IFERROR((I72-H72)/I72,"") -> 0.295775
B73: Factory fitted ST optics upgrade for surface | G73: =IF(F73-F73*$G$17=0,"",F73-F73*$G$17) | H73: =IFERROR(G73*$H$17,"") | I73: =IFERROR(ROUND(H73*$I$17,0),"") | J73: =IFERROR((I73-H73)/I73,"")
G74: =IF(F74-F74*$G$17=0,"",F74-F74*$G$17) | H74: =IFERROR(G74*$H$17,"") | I74: =IFERROR(ROUND(H74*$I$17,0),"") | J74: =IFERROR((I74-H74)/I74,"")
A75: MOD-Q2-OP-2 | B75: DiGiCo Quantum 225 second Optocore interface (HMA) | E75: =ROUND(F75/0.55,0) -> 7364 | F75: 4050 | G75: =IF(F75-F75*$G$17=0,"",F75-F75*$G$17) -> 3442.5 | H75: =IFERROR(G75*$H$17,"") -> 506047.5 | I75: =IFERROR(ROUND(H75*$I$17,0),"") -> 718587 | J75: =IFERROR((I75-H75)/I75,"") -> 0.29577421
B76: Factory fitted 2nd HMA expanded beam optics upgrade for surface | G76: =IF(F76-F76*$G$17=0,"",F76-F76*$G$17) | H76: =IFERROR(G76*$H$17,"") | I76: =IFERROR(ROUND(H76*$I$17,0),"") | J76: =IFERROR((I76-H76)/I76,"")
G77: =IF(F77-F77*$G$17=0,"",F77-F77*$G$17) | H77: =IFERROR(G77*$H$17,"") | I77: =IFERROR(ROUND(H77*$I$17,0),"") | J77: =IFERROR((I77-H77)/I77,"")
A78: MOD-Q2-NC-2 | B78: DiGiCo Quantum 225 second Optocore interface (NC) | E78: =ROUND(F78/0.55,0) -> 6251 | F78: 3438 | G78: =IF(F78-F78*$G$17=0,"",F78-F78*$G$17) -> 2922.3 | H78: =IFERROR(G78*$H$17,"") -> 429578.1 | I78: =IFERROR(ROUND(H78*$I$17,0),"") -> 610001 | J78: =IFERROR((I78-H78)/I78,"") -> 0.29577476
B79: Factory fitted 2nd NC Optocore Interface | G79: =IF(F79-F79*$G$17=0,"",F79-F79*$G$17) | H79: =IFERROR(G79*$H$17,"") | I79: =IFERROR(ROUND(H79*$I$17,0),"") | J79: =IFERROR((I79-H79)/I79,"")
G80: =IF(F80-F80*$G$17=0,"",F80-F80*$G$17) | H80: =IFERROR(G80*$H$17,"") | I80: =IFERROR(ROUND(H80*$I$17,0),"") | J80: =IFERROR((I80-H80)/I80,"")
A81: MOD-Q2-ST-2 | B81: DiGiCo Quantum 225 second Optocore intercace (ST) | E81: =ROUND(F81/0.55,0) -> 6038 | F81: 3321 | G81: =IF(F81-F81*$G$17=0,"",F81-F81*$G$17) -> 2822.85 | H81: =IFERROR(G81*$H$17,"") -> 414958.95 | I81: =IFERROR(ROUND(H81*$I$17,0),"") -> 589242 | J81: =IFERROR((I81-H81)/I81,"") -> 0.295775
B82: Factory fitted 2nd ST Optocore Interface | G82: =IF(F82-F82*$G$17=0,"",F82-F82*$G$17) | H82: =IFERROR(G82*$H$17,"") | I82: =IFERROR(ROUND(H82*$I$17,0),"") | J82: =IFERROR((I82-H82)/I82,"")
G83: =IF(F83-F83*$G$17=0,"",F83-F83*$G$17) | H83: =IFERROR(G83*$H$17,"") | I83: =IFERROR(ROUND(H83*$I$17,0),"") | J83: =IFERROR((I83-H83)/I83,"")
A84: MOD-Q2-DS-UP | B84: DiGiCo Quantum 225 dual screen upgrade | C84: 25% Disc.. | E84: =ROUND(F84/0.55,0) -> 10902 | F84: 5996 | G84: =IF(F84-F84*$G$17=0,"",F84-F84*$G$17) -> 5096.6 | H84: =IFERROR(G84*$H$17,"") -> 749200.2 | I84: =IFERROR(ROUND(H84*$I$17,0),"") -> 1063864 | J84: =IFERROR((I84-H84)/I84,"") -> 0.29577446
B85: Second screen upgrade for surface. Kit includes complete left panel, blanking panel for rear, new PC and instructions | G85: =IF(F85-F85*$G$17=0,"",F85-F85*$G$17) | H85: =IFERROR(G85*$H$17,"") | I85: =IFERROR(ROUND(H85*$I$17,0),"") | J85: =IFERROR((I85-H85)/I85,"")
G86: =IF(F86-F86*$G$17=0,"",F86-F86*$G$17) | H86: =IFERROR(G86*$H$17,"") | I86: =IFERROR(ROUND(H86*$I$17,0),"") | J86: =IFERROR((I86-H86)/I86,"")
A87: MOD-FOURIER-Q2 | B87: DiGiCo Quantum 225 Fourier Audio interface card | E87: =ROUND(F87/0.55,0) -> 1864 | F87: 1025 | G87: =IF(F87-F87*$G$17=0,"",F87-F87*$G$17) -> 871.25 | H87: =IFERROR(G87*$H$17,"") -> 128073.75 | I87: =IFERROR(ROUND(H87*$I$17,0),"") -> 181865 | J87: =IFERROR((I87-H87)/I87,"") -> 0.29577571
B88: Fourier Audio interface card. 64ch Dante I/O. 3 x RJ45 | G88: =IF(F88-F88*$G$17=0,"",F88-F88*$G$17) | H88: =IFERROR(G88*$H$17,"") | I88: =IFERROR(ROUND(H88*$I$17,0),"") | J88: =IFERROR((I88-H88)/I88,"")
G89: =IF(F89-F89*$G$17=0,"",F89-F89*$G$17) | H89: =IFERROR(G89*$H$17,"") | I89: =IFERROR(ROUND(H89*$I$17,0),"") | J89: =IFERROR((I89-H89)/I89,"")
A90: MOD-WAVES-Q2 | B90: DiGiCo Quantum 225 Waves interface card | E90: =ROUND(F90/0.55,0) -> 1864 | F90: 1025 | G90: =IF(F90-F90*$G$17=0,"",F90-F90*$G$17) -> 871.25 | H90: =IFERROR(G90*$H$17,"") -> 128073.75 | I90: =IFERROR(ROUND(H90*$I$17,0),"") -> 181865 | J90: =IFERROR((I90-H90)/I90,"") -> 0.29577571
B91: Waves interface card. 64ch Soundgrid I/O. RJ45 | G91: =IF(F91-F91*$G$17=0,"",F91-F91*$G$17) | H91: =IFERROR(G91*$H$17,"") | I91: =IFERROR(ROUND(H91*$I$17,0),"") | J91: =IFERROR((I91-H91)/I91,"")
G92: =IF(F92-F92*$G$17=0,"",F92-F92*$G$17) | H92: =IFERROR(G92*$H$17,"") | I92: =IFERROR(ROUND(H92*$I$17,0),"") | J92: =IFERROR((I92-H92)/I92,"")
A93: SOFT-Q225T | B93: DiGiCo Quantum 225 theatre-specific application software | E93: =ROUND(F93/0.55,0) -> 6545 | F93: 3600 | G93: =IF(F93-F93*$G$17=0,"",F93-F93*$G$17) -> 3060 | H93: =IFERROR(G93*$H$17,"") -> 449820 | I93: =IFERROR(ROUND(H93*$I$17,0),"") -> 638744 | J93: =IFERROR((I93-H93)/I93,"") -> 0.29577421
B94: Extensive Theatre specific software including - Auto Update, Cue Editor, Matrix nodal delay, Aliases, Players. | G94: =IF(F94-F94*$G$17=0,"",F94-F94*$G$17) | H94: =IFERROR(G94*$H$17,"") | I94: =IFERROR(ROUND(H94*$I$17,0),"") | J94: =IFERROR((I94-H94)/I94,"")
B95: Channels increased from 72 to 96. Busses increased from 36 to 48. Matrix increased from 12x12 to 24x24, | G95: =IF(F95-F95*$G$17=0,"",F95-F95*$G$17) | H95: =IFERROR(G95*$H$17,"") | I95: =IFERROR(ROUND(H95*$I$17,0),"") | J95: =IFERROR((I95-H95)/I95,"")
G96: =IF(F96-F96*$G$17=0,"",F96-F96*$G$17) | H96: =IFERROR(G96*$H$17,"") | I96: =IFERROR(ROUND(H96*$I$17,0),"") | J96: =IFERROR((I96-H96)/I96,"")
A97: MOD-Q225-TRAY | B97: DiGiCo Quantum 225 laptop/script tray option | E97: =ROUND(F97/0.55,0) -> 123 | F97: 67.5 | G97: =IF(F97-F97*$G$17=0,"",F97-F97*$G$17) -> 57.375 | H97: =IFERROR(G97*$H$17,"") -> 8434.125 | I97: =IFERROR(ROUND(H97*$I$17,0),"") -> 11976 | J97: =IFERROR((I97-H97)/I97,"") -> 0.29574775
B98: Laptop / script tray option for supplied Q225 mounting bracket | G98: =IF(F98-F98*$G$17=0,"",F98-F98*$G$17) | H98: =IFERROR(G98*$H$17,"") | I98: =IFERROR(ROUND(H98*$I$17,0),"") | J98: =IFERROR((I98-H98)/I98,"")
G99: =IF(F99-F99*$G$17=0,"",F99-F99*$G$17) | H99: =IFERROR(G99*$H$17,"") | I99: =IFERROR(ROUND(H99*$I$17,0),"") | J99: =IFERROR((I99-H99)/I99,"")
A100: FC-Q225 | B100: DiGiCo Quantum 225 3-piece surface touring flight case | E100: =ROUND(F100/0.55,0) -> 2089 | F100: 1149 | G100: =IF(F100-F100*$G$17=0,"",F100-F100*$G$17) -> 976.65 | H100: =IFERROR(G100*$H$17,"") -> 143567.55 | I100: =IFERROR(ROUND(H100*$I$17,0),"") -> 203866 | J100: =IFERROR((I100-H100)/I100,"") -> 0.29577492
B101: Dimensions; 1260(w) x 601(d) x 1141(h) mm Weight; 95Kg
B103: Please refer to the 'Racks, Cables and Options' and 'DiGiCo Solutions' Price Lists for additional options.
B104: All optics are Multimode as standard. Please call for prices on Singlemode.

Sheet Q 852
B1: DiGiCo Quantum 852 Distributor Price List
B3: Sept 2024
B5: Unit 10 Silverglade Business Park, Leatherhead Road
B6: Chessington, Surrey, KT9 2QL
B7: Tel; +44 1372 845600
B8: Fax; +44 1372 845656
B9: email; sales@digiconsoles.com
B10: web; www.digiconsoles.com
B12: FCA Glenrothes KY7 4NX. E&OE. Prices, Products and Specification are subject to change without notice.
B13: This price list supercedes all previous price lists
A15: Product Code | B15: Description | E15: List (£) | F15: Distributor (£) | G15: Disc. () | H15: HT Buy (INR) | I15: Customer Price | J15: Hi-Tech
G16: 0.2 | H16: 147 | I16: 1.42 | J16: Margin
A17: DiGiCo Quantum 852 32bit System
B19: DiGiCo Quantum 852 32bit touring system | E19: =ROUND(F19/0.55,0) -> 219804 | F19: 120892.38 | G19: =IF(F19-F19*$G$16=0,"",F19-F19*$G$16) -> 96713.904 | H19: =IFERROR(G19*$H$16,"") -> 14216944 | I19: =IFERROR(ROUND(H19*$I$16,0),"") -> 20188060 | J19: =IFERROR((I19-H19)/I19,"") -> 0.29577464
B20: 1 x Quantum 852 surface - 36+2+2 100mm faders, 12 60mm faders, 2 quantum engines, HMA optics, 2 DMI slots, 8 BNC MADI, 2 PSU, 32 GPI/O | G20: =IF(F20-F20*$G$16=0,"",F20-F20*$G$16) | H20: =IFERROR(G20*$H$16,"") | I20: =IFERROR(ROUND(H20*$I$16,0),"") | J20: =IFERROR((I20-H20)/I20,"")
B21: 384 input channels, 192 output busses, 2 mono or stereo solo busses. LR, LCR, LCRS or 5.1 master buss | G21: =IF(F21-F21*$G$16=0,"",F21-F21*$G$16) | H21: =IFERROR(G21*$H$16,"") | I21: =IFERROR(ROUND(H21*$I$16,0),"") | J21: =IFERROR((I21-H21)/I21,"")
B22: 64ch plugin I/O (Fourier or Waves), 64 x 64 matrix, 36 CG/VCA, 64 FX (Max 32 Reverbs), 48 x 32 band graphic eq’s, | G22: =IF(F22-F22*$G$16=0,"",F22-F22*$G$16) | H22: =IFERROR(G22*$H$16,"") | I22: =IFERROR(ROUND(H22*$I$16,0),"") | J22: =IFERROR((I22-H22)/I22,"")
B23: 384 Nodal Processors, 128 Mustard Processors, 32 Spice FX | G23: =IF(F23-F23*$G$16=0,"",F23-F23*$G$16) | H23: =IFERROR(G23*$H$16,"") | I23: =IFERROR(ROUND(H23*$I$16,0),"") | J23: =IFERROR((I23-H23)/I23,"")
B24: Local I/O 12 x 32bit Mic inputs, 12 x 32bit Line outputs, 12 x AES I/O mono stream, dust cover | G24: =IF(F24-F24*$G$16=0,"",F24-F24*$G$16) | H24: =IFERROR(G24*$H$16,"") | I24: =IFERROR(ROUND(H24*$I$16,0),"") | J24: =IFERROR((I24-H24)/I24,"")
B25: 1 x Stage SD-Rack, HMA optics, 2 BNC MADI, dual PSU - 56 32bit mic/line in / 40 32bit line out / 16 AES outputs | G25: =IF(F25-F25*$G$16=0,"",F25-F25*$G$16) | H25: =IFERROR(G25*$H$16,"") | I25: =IFERROR(ROUND(H25*$I$16,0),"") | J25: =IFERROR((I25-H25)/I25,"")
B26: 2 x 150m optical cable on drum | G26: =IF(F26-F26*$G$16=0,"",F26-F26*$G$16) | H26: =IFERROR(G26*$H$16,"") | I26: =IFERROR(ROUND(H26*$I$16,0),"") | J26: =IFERROR((I26-H26)/I26,"")
B27: 1 x Touring surface flight case | G27: =IF(F27-F27*$G$16=0,"",F27-F27*$G$16) | H27: =IFERROR(G27*$H$16,"") | I27: =IFERROR(ROUND(H27*$I$16,0),"") | J27: =IFERROR((I27-H27)/I27,"")
G28: =IF(F28-F28*$G$16=0,"",F28-F28*$G$16) | H28: =IFERROR(G28*$H$16,"") | I28: =IFERROR(ROUND(H28*$I$16,0),"") | J28: =IFERROR((I28-H28)/I28,"")
A29: DiGiCo Quantum 852 Surface | G29: =IF(F29-F29*$G$16=0,"",F29-F29*$G$16) | H29: =IFERROR(G29*$H$16,"") | I29: =IFERROR(ROUND(H29*$I$16,0),"") | J29: =IFERROR((I29-H29)/I29,"")
G30: =IF(F30-F30*$G$16=0,"",F30-F30*$G$16) | H30: =IFERROR(G30*$H$16,"") | I30: =IFERROR(ROUND(H30*$I$16,0),"") | J30: =IFERROR((I30-H30)/I30,"")
A31: X-Q852-WS-OP | B31: DiGiCo Quantum 852 surface - MADI / HMA optics | E31: =ROUND(F31/0.55,0) -> 178091 | F31: 97950 | G31: =IF(F31-F31*$G$16=0,"",F31-F31*$G$16) -> 78360 | H31: =IFERROR(G31*$H$16,"") -> 11518920 | I31: =IFERROR(ROUND(H31*$I$16,0),"") -> 16356866 | J31: =IFERROR((I31-H31)/I31,"") -> 0.29577463
B32: 1 x Quantum 852 surface - 36+2+2 100mm faders, 12 60mm faders, 2 quantum engines, HMA optics, 2 DMI slots, 8 BNC MADI, 2 PSU, 32 GPI/O | G32: =IF(F32-F32*$G$16=0,"",F32-F32*$G$16) | H32: =IFERROR(G32*$H$16,"") | I32: =IFERROR(ROUND(H32*$I$16,0),"") | J32: =IFERROR((I32-H32)/I32,"")
B33: 384 input channels, 192 output busses, 2 mono or stereo solo busses. LR, LCR, LCRS or 5.1 master buss | G33: =IF(F33-F33*$G$16=0,"",F33-F33*$G$16) | H33: =IFERROR(G33*$H$16,"") | I33: =IFERROR(ROUND(H33*$I$16,0),"") | J33: =IFERROR((I33-H33)/I33,"")
B34: 64 x 64 matrix, 36 CG/VCA, 64 FX (Max 32 Reverbs), 48 x 32 band graphic eq’s, | G34: =IF(F34-F34*$G$16=0,"",F34-F34*$G$16) | H34: =IFERROR(G34*$H$16,"") | I34: =IFERROR(ROUND(H34*$I$16,0),"") | J34: =IFERROR((I34-H34)/I34,"")
B35: 384 Nodal Processors, 128 Mustard Processors, 32 Spice FX | G35: =IF(F35-F35*$G$16=0,"",F35-F35*$G$16) | H35: =IFERROR(G35*$H$16,"") | I35: =IFERROR(ROUND(H35*$I$16,0),"") | J35: =IFERROR((I35-H35)/I35,"")
B36: Local I/O 12 x 32bit Mic inputs, 12 x 32bit Line outputs, 12 x AES I/O mono stream, dust cover | G36: =IF(F36-F36*$G$16=0,"",F36-F36*$G$16) | H36: =IFERROR(G36*$H$16,"") | I36: =IFERROR(ROUND(H36*$I$16,0),"") | J36: =IFERROR((I36-H36)/I36,"")
B37: Dimensions; 1767(w) x 1075(d) x 607(h) mm Weight; 120Kg | G37: =IF(F37-F37*$G$16=0,"",F37-F37*$G$16) | H37: =IFERROR(G37*$H$16,"") | I37: =IFERROR(ROUND(H37*$I$16,0),"") | J37: =IFERROR((I37-H37)/I37,"")
G38: =IF(F38-F38*$G$16=0,"",F38-F38*$G$16) | H38: =IFERROR(G38*$H$16,"") | I38: =IFERROR(ROUND(H38*$I$16,0),"") | J38: =IFERROR((I38-H38)/I38,"")
A39: X-Q852-WS-NC | B39: DiGiCo Quantum 852 surface - MADI / NC optics | E39: =ROUND(F39/0.55,0) -> 175865 | F39: 96726 | G39: =IF(F39-F39*$G$16=0,"",F39-F39*$G$16) -> 77380.8 | H39: =IFERROR(G39*$H$16,"") -> 11374978 | I39: =IFERROR(ROUND(H39*$I$16,0),"") -> 16152468 | J39: =IFERROR((I39-H39)/I39,"") -> 0.29577464
B40: 1 x Quantum 852 surface - 36+2+2 100mm faders, 12 60mm faders, 2 quantum engines, NC optics, 2 DMI slots, 8 BNC MADI, 2 PSU, 32 GPI/O | G40: =IF(F40-F40*$G$16=0,"",F40-F40*$G$16) | H40: =IFERROR(G40*$H$16,"") | I40: =IFERROR(ROUND(H40*$I$16,0),"") | J40: =IFERROR((I40-H40)/I40,"")
B41: 384 input channels, 192 output busses, 2 mono or stereo solo busses. LR, LCR, LCRS or 5.1 master buss | G41: =IF(F41-F41*$G$16=0,"",F41-F41*$G$16) | H41: =IFERROR(G41*$H$16,"") | I41: =IFERROR(ROUND(H41*$I$16,0),"") | J41: =IFERROR((I41-H41)/I41,"")
B42: 64 x 64 matrix, 36 CG/VCA, 64 FX (Max 32 Reverbs), 48 x 32 band graphic eq’s, | G42: =IF(F42-F42*$G$16=0,"",F42-F42*$G$16) | H42: =IFERROR(G42*$H$16,"") | I42: =IFERROR(ROUND(H42*$I$16,0),"") | J42: =IFERROR((I42-H42)/I42,"")
B43: 384 Nodal Processors, 128 Mustard Processors, 32 Spice FX | G43: =IF(F43-F43*$G$16=0,"",F43-F43*$G$16) | H43: =IFERROR(G43*$H$16,"") | I43: =IFERROR(ROUND(H43*$I$16,0),"") | J43: =IFERROR((I43-H43)/I43,"")
B44: Local I/O 12 x 32bit Mic inputs, 12 x 32bit Line outputs, 12 x AES I/O mono stream, dust cover | G44: =IF(F44-F44*$G$16=0,"",F44-F44*$G$16) | H44: =IFERROR(G44*$H$16,"") | I44: =IFERROR(ROUND(H44*$I$16,0),"") | J44: =IFERROR((I44-H44)/I44,"")
B45: Dimensions; 1767(w) x 1075(d) x 607(h) mm Weight; 120Kg | G45: =IF(F45-F45*$G$16=0,"",F45-F45*$G$16) | H45: =IFERROR(G45*$H$16,"") | I45: =IFERROR(ROUND(H45*$I$16,0),"") | J45: =IFERROR((I45-H45)/I45,"")
G46: =IF(F46-F46*$G$16=0,"",F46-F46*$G$16) | H46: =IFERROR(G46*$H$16,"") | I46: =IFERROR(ROUND(H46*$I$16,0),"") | J46: =IFERROR((I46-H46)/I46,"")
A47: X-Q852-WS-ST | B47: DiGiCo Quantum 852 surface - MADI / ST optics | E47: =ROUND(F47/0.55,0) -> 175440 | F47: 96492 | G47: =IF(F47-F47*$G$16=0,"",F47-F47*$G$16) -> 77193.6 | H47: =IFERROR(G47*$H$16,"") -> 11347459 | I47: =IFERROR(ROUND(H47*$I$16,0),"") -> 16113392 | J47: =IFERROR((I47-H47)/I47,"") -> 0.29577465
B48: 1 x Quantum 852 surface - 36+2+2 100mm faders, 12 60mm faders, 2 quantum engines, ST optics, 2 DMI slots, 8 BNC MADI, 2 PSU, 32 GPI/O | G48: =IF(F48-F48*$G$16=0,"",F48-F48*$G$16) | H48: =IFERROR(G48*$H$16,"") | I48: =IFERROR(ROUND(H48*$I$16,0),"") | J48: =IFERROR((I48-H48)/I48,"")
B49: 384 input channels, 192 output busses, 2 mono or stereo solo busses. LR, LCR, LCRS or 5.1 master buss | G49: =IF(F49-F49*$G$16=0,"",F49-F49*$G$16) | H49: =IFERROR(G49*$H$16,"") | I49: =IFERROR(ROUND(H49*$I$16,0),"") | J49: =IFERROR((I49-H49)/I49,"")
B50: 64 x 64 matrix, 36 CG/VCA, 64 FX (Max 32 Reverbs), 48 x 32 band graphic eq’s, | G50: =IF(F50-F50*$G$16=0,"",F50-F50*$G$16) | H50: =IFERROR(G50*$H$16,"") | I50: =IFERROR(ROUND(H50*$I$16,0),"") | J50: =IFERROR((I50-H50)/I50,"")
B51: 384 Nodal Processors, 128 Mustard Processors, 32 Spice FX | G51: =IF(F51-F51*$G$16=0,"",F51-F51*$G$16) | H51: =IFERROR(G51*$H$16,"") | I51: =IFERROR(ROUND(H51*$I$16,0),"") | J51: =IFERROR((I51-H51)/I51,"")
B52: Local I/O 12 x 32bit Mic inputs, 12 x 32bit Line outputs, 12 x AES I/O mono stream, dust cover | G52: =IF(F52-F52*$G$16=0,"",F52-F52*$G$16) | H52: =IFERROR(G52*$H$16,"") | I52: =IFERROR(ROUND(H52*$I$16,0),"") | J52: =IFERROR((I52-H52)/I52,"")
B53: Dimensions; 1767(w) x 1075(d) x 607(h) mm Weight; 120Kg | G53: =IF(F53-F53*$G$16=0,"",F53-F53*$G$16) | H53: =IFERROR(G53*$H$16,"") | I53: =IFERROR(ROUND(H53*$I$16,0),"") | J53: =IFERROR((I53-H53)/I53,"")
G54: =IF(F54-F54*$G$16=0,"",F54-F54*$G$16) | H54: =IFERROR(G54*$H$16,"") | I54: =IFERROR(ROUND(H54*$I$16,0),"") | J54: =IFERROR((I54-H54)/I54,"")
G55: =IF(F55-F55*$G$16=0,"",F55-F55*$G$16) | H55: =IFERROR(G55*$H$16,"") | I55: =IFERROR(ROUND(H55*$I$16,0),"") | J55: =IFERROR((I55-H55)/I55,"")
A56: DiGiCo Quantum 852 | G56: =IF(F56-F56*$G$16=0,"",F56-F56*$G$16) | H56: =IFERROR(G56*$H$16,"") | I56: =IFERROR(ROUND(H56*$I$16,0),"") | J56: =IFERROR((I56-H56)/I56,"")
G57: =IF(F57-F57*$G$16=0,"",F57-F57*$G$16) | H57: =IFERROR(G57*$H$16,"") | I57: =IFERROR(ROUND(H57*$I$16,0),"") | J57: =IFERROR((I57-H57)/I57,"")
A58: MOD-Q852-OP-2 | B58: DiGiCo Quantum 852 second optocore interface (HMA) | E58: =ROUND(F58/0.55,0) -> 7364 | F58: 4050 | G58: =IF(F58-F58*$G$16=0,"",F58-F58*$G$16) -> 3240 | H58: =IFERROR(G58*$H$16,"") -> 476280 | I58: =IFERROR(ROUND(H58*$I$16,0),"") -> 676318 | J58: =IFERROR((I58-H58)/I58,"") -> 0.29577506
B59: Factory fitted 2nd HMA Optocore Interface. Note two are required for dual engined surface. | G59: =IF(F59-F59*$G$16=0,"",F59-F59*$G$16) | H59: =IFERROR(G59*$H$16,"") | I59: =IFERROR(ROUND(H59*$I$16,0),"") | J59: =IFERROR((I59-H59)/I59,"")
G60: =IF(F60-F60*$G$16=0,"",F60-F60*$G$16) | H60: =IFERROR(G60*$H$16,"") | I60: =IFERROR(ROUND(H60*$I$16,0),"") | J60: =IFERROR((I60-H60)/I60,"")
A61: MOD-Q852-NC-2 | B61: DiGiCo Quantum 852 second optocore interface (NC) | E61: =ROUND(F61/0.55,0) -> 6251 | F61: 3438 | G61: =IF(F61-F61*$G$16=0,"",F61-F61*$G$16) -> 2750.4 | H61: =IFERROR(G61*$H$16,"") -> 404308.8 | I61: =IFERROR(ROUND(H61*$I$16,0),"") -> 574118 | J61: =IFERROR((I61-H61)/I61,"") -> 0.29577404
B62: Factory fitted 2nd NC Optocore Interface. Note two are required for dual engined surface. | G62: =IF(F62-F62*$G$16=0,"",F62-F62*$G$16) | H62: =IFERROR(G62*$H$16,"") | I62: =IFERROR(ROUND(H62*$I$16,0),"") | J62: =IFERROR((I62-H62)/I62,"")
G63: =IF(F63-F63*$G$16=0,"",F63-F63*$G$16) | H63: =IFERROR(G63*$H$16,"") | I63: =IFERROR(ROUND(H63*$I$16,0),"") | J63: =IFERROR((I63-H63)/I63,"")
A64: MOD-Q852-ST-2 | B64: DiGiCo Quantum 852 second optocore interface (ST) | E64: =ROUND(F64/0.55,0) -> 6038 | F64: 3321 | G64: =IF(F64-F64*$G$16=0,"",F64-F64*$G$16) -> 2656.8 | H64: =IFERROR(G64*$H$16,"") -> 390549.6 | I64: =IFERROR(ROUND(H64*$I$16,0),"") -> 554580 | J64: =IFERROR((I64-H64)/I64,"") -> 0.2957741
B65: Factory fitted 2nd ST Optocore Interface. Note two are required for dual engined surface. | G65: =IF(F65-F65*$G$16=0,"",F65-F65*$G$16) | H65: =IFERROR(G65*$H$16,"") | I65: =IFERROR(ROUND(H65*$I$16,0),"") | J65: =IFERROR((I65-H65)/I65,"")
G66: =IF(F66-F66*$G$16=0,"",F66-F66*$G$16) | H66: =IFERROR(G66*$H$16,"") | I66: =IFERROR(ROUND(H66*$I$16,0),"") | J66: =IFERROR((I66-H66)/I66,"")
A67: MOD-FOURIER-Q852 | B67: DiGiCo Quantum 852 Fourier Audio interface card | E67: =ROUND(F67/0.55,0) -> 1864 | F67: 1025 | G67: =IF(F67-F67*$G$16=0,"",F67-F67*$G$16) -> 820 | H67: =IFERROR(G67*$H$16,"") -> 120540 | I67: =IFERROR(ROUND(H67*$I$16,0),"") -> 171167 | J67: =IFERROR((I67-H67)/I67,"") -> 0.29577547
B68: Fourier Audio interface card. 64ch Dante I/O. 3 x RJ45, One required per engine. | G68: =IF(F68-F68*$G$16=0,"",F68-F68*$G$16) | H68: =IFERROR(G68*$H$16,"") | I68: =IFERROR(ROUND(H68*$I$16,0),"") | J68: =IFERROR((I68-H68)/I68,"")
G69: =IF(F69-F69*$G$16=0,"",F69-F69*$G$16) | H69: =IFERROR(G69*$H$16,"") | I69: =IFERROR(ROUND(H69*$I$16,0),"") | J69: =IFERROR((I69-H69)/I69,"")
A70: MOD-WAVES-Q852 | B70: DiGiCo Quantum 852 Waves interface card | E70: =ROUND(F70/0.55,0) -> 1864 | F70: 1025 | G70: =IF(F70-F70*$G$16=0,"",F70-F70*$G$16) -> 820 | H70: =IFERROR(G70*$H$16,"") -> 120540 | I70: =IFERROR(ROUND(H70*$I$16,0),"") -> 171167 | J70: =IFERROR((I70-H70)/I70,"") -> 0.29577547
B71: Waves interface card. 64ch Soundgrid I/O. RJ45. One required per engine. | G71: =IF(F71-F71*$G$16=0,"",F71-F71*$G$16) | H71: =IFERROR(G71*$H$16,"") | I71: =IFERROR(ROUND(H71*$I$16,0),"") | J71: =IFERROR((I71-H71)/I71,"")
G72: =IF(F72-F72*$G$16=0,"",F72-F72*$G$16) | H72: =IFERROR(G72*$H$16,"") | I72: =IFERROR(ROUND(H72*$I$16,0),"") | J72: =IFERROR((I72-H72)/I72,"")
A73: X-Q852-SCRIPT | B73: DiGiCo Quantum 852 script tray | F73: TBC | H73: =IFERROR(G73*$H$16,"") -> 0 | I73: =IFERROR(ROUND(H73*$I$16,0),"") -> 0 | J73: =IFERROR((I73-H73)/I73,"")
B74: Transparent Script tray for Q8 surface | G74: =IF(F74-F74*$G$16=0,"",F74-F74*$G$16) | H74: =IFERROR(G74*$H$16,"") | I74: =IFERROR(ROUND(H74*$I$16,0),"") | J74: =IFERROR((I74-H74)/I74,"")
G75: =IF(F75-F75*$G$16=0,"",F75-F75*$G$16) | H75: =IFERROR(G75*$H$16,"") | I75: =IFERROR(ROUND(H75*$I$16,0),"") | J75: =IFERROR((I75-H75)/I75,"")
A76: SOFTWARE-Q852T | B76: DiGiCo Quantum 852 theatre-specific application software | E76: =ROUND(F76/0.55,0) -> 14545 | F76: 8000 | G76: =IF(F76-F76*$G$16=0,"",F76-F76*$G$16) -> 6400 | H76: =IFERROR(G76*$H$16,"") -> 940800 | I76: =IFERROR(ROUND(H76*$I$16,0),"") -> 1335936 | J76: =IFERROR((I76-H76)/I76,"") -> 0.29577465
B77: Extensive Theatre specific software including - Auto Update, Cue Editor, Matrix nodal delay. | G77: =IF(F77-F77*$G$16=0,"",F77-F77*$G$16) | H77: =IFERROR(G77*$H$16,"") | I77: =IFERROR(ROUND(H77*$I$16,0),"") | J77: =IFERROR((I77-H77)/I77,"")
G78: =IF(F78-F78*$G$16=0,"",F78-F78*$G$16) | H78: =IFERROR(G78*$H$16,"") | I78: =IFERROR(ROUND(H78*$I$16,0),"") | J78: =IFERROR((I78-H78)/I78,"")
A79: FC-Q852 | B79: DiGiCo Quantum 852 flight case | E79: =ROUND(F79/0.55,0) -> 3364 | F79: 1850 | G79: =IF(F79-F79*$G$16=0,"",F79-F79*$G$16) -> 1480 | H79: =IFERROR(G79*$H$16,"") -> 217560 | I79: =IFERROR(ROUND(H79*$I$16,0),"") -> 308935 | J79: =IFERROR((I79-H79)/I79,"") -> 0.29577419
B80: Dimensions; 1896(w) x 708(d) x 1394(h) mm. Weight 131Kg
A82: FC-Q852-L | B82: DiGiCo Quantum 852 flight case - lightweight | F82: TBC
B83: Dimensions; TBC. Weight; TBC
B85: Please refer to Racks, Cables and Options Price List for any additional items required.
B86: All optics are Multimode as standard. Please call for prices on Singlemode.

Sheet Solutions
B1: DiGiCo Solutions Distributor Price List
B3: Sept 2024
B6: Unit 10 Silverglade Business Park, Leatherhead Road
B7: Chessington, Surrey, KT9 2QL
B8: Tel; +44 1372 845600
B9: Fax; +44 1372 845656
B10: email; sales@digiconsoles.com
B11: web; www.digiconsoles.com
B13: FCA Glenrothes KY7 4NX. E&OE. Prices, Products and Specification are subject to change without notice.
B14: This price list supercedes all previous price lists.
A16: Product Code | B16: Description | E16: List (£) | F16: Distributor (£) | G16: Disc. () | H16: HT Buy (INR) | I16: Customer Price | J16: Hi-Tech
H17: 147 | I17: 1.42 | J17: Margin
A18: DiGiCo Interface Boxes
A20: X-LRB | B20: DiGiCo Little Red Box | E20: =ROUND(F20/0.55,0) -> 817 | F20: 449.1 | G20: =IF(F20-F20*0%=0,"",F20-F20*0%) -> 449.1 | H20: =IFERROR(G20*$H$17,"") -> 66017.7 | I20: =IFERROR(ROUND(H20*$I$17,0),"") -> 93745 | J20: =IFERROR((I20-H20)/I20,"") -> 0.29577364
B21: Interface box. Includes 2m CAT5e cable and 2m USB cable | G21: =IF(F21-F21*0%=0,"",F21-F21*0%) | H21: =IFERROR(G21*$H$17,"") | I21: =IFERROR(ROUND(H21*$I$17,0),"") | J21: =IFERROR((I21-H21)/I21,"")
G22: =IF(F22-F22*0%=0,"",F22-F22*0%) | H22: =IFERROR(G22*$H$17,"") | I22: =IFERROR(ROUND(H22*$I$17,0),"") | J22: =IFERROR((I22-H22)/I22,"")
A23: X-LBB | B23: DiGiCo Little Blue Box | E23: =ROUND(F23/0.55,0) -> 817 | F23: 449.1 | G23: =IF(F23-F23*0%=0,"",F23-F23*0%) -> 449.1 | H23: =IFERROR(G23*$H$17,"") -> 66017.7 | I23: =IFERROR(ROUND(H23*$I$17,0),"") -> 93745 | J23: =IFERROR((I23-H23)/I23,"") -> 0.29577364
B24: Interface box. Includes 2m CAT5e cable and 2m USB cable | G24: =IF(F24-F24*0%=0,"",F24-F24*0%) | H24: =IFERROR(G24*$H$17,"") | I24: =IFERROR(ROUND(H24*$I$17,0),"") | J24: =IFERROR((I24-H24)/I24,"")
G25: =IF(F25-F25*0%=0,"",F25-F25*0%) | H25: =IFERROR(G25*$H$17,"") | I25: =IFERROR(ROUND(H25*$I$17,0),"") | J25: =IFERROR((I25-H25)/I25,"")
A26: MOD-LB-2U | B26: DiGiCo Rack Kit for two Little Box's (2U) | E26: =ROUND(F26/0.55,0) -> 44 | F26: 24.3 | G26: =IF(F26-F26*0%=0,"",F26-F26*0%) -> 24.3 | H26: =IFERROR(G26*$H$17,"") -> 3572.1 | I26: =IFERROR(ROUND(H26*$I$17,0),"") -> 5072 | J26: =IFERROR((I26-H26)/I26,"") -> 0.29572161
B27: Includes blank panel | G27: =IF(F27-F27*0%=0,"",F27-F27*0%) | H27: =IFERROR(G27*$H$17,"") | I27: =IFERROR(ROUND(H27*$I$17,0),"") | J27: =IFERROR((I27-H27)/I27,"")
G28: =IF(F28-F28*0%=0,"",F28-F28*0%) | H28: =IFERROR(G28*$H$17,"") | I28: =IFERROR(ROUND(H28*$I$17,0),"") | J28: =IFERROR((I28-H28)/I28,"")
A29: X-PB-OP | B29: DiGiCo Purple Box - Multimode HMA | E29: =ROUND(F29/0.55,0) -> 2700 | F29: 1485 | G29: =IF(F29-F29*0%=0,"",F29-F29*0%) -> 1485 | H29: =IFERROR(G29*$H$17,"") -> 218295 | I29: =IFERROR(ROUND(H29*$I$17,0),"") -> 309979 | J29: =IFERROR((I29-H29)/I29,"") -> 0.29577488
B30: 1U. 2 x MADI-Optical bi-directional converter. BNC & etherCON MADI / HMA. Dual PSU. Multimode Optics | G30: =IF(F30-F30*0%=0,"",F30-F30*0%) | H30: =IFERROR(G30*$H$17,"") | I30: =IFERROR(ROUND(H30*$I$17,0),"") | J30: =IFERROR((I30-H30)/I30,"")
G31: =IF(F31-F31*0%=0,"",F31-F31*0%) | H31: =IFERROR(G31*$H$17,"") | I31: =IFERROR(ROUND(H31*$I$17,0),"") | J31: =IFERROR((I31-H31)/I31,"")
A32: X-PB-NC | B32: DiGiCo Purple Box - Multimode OpticalCON | E32: =ROUND(F32/0.55,0) -> 1718 | F32: 945 | G32: =IF(F32-F32*0%=0,"",F32-F32*0%) -> 945 | H32: =IFERROR(G32*$H$17,"") -> 138915 | I32: =IFERROR(ROUND(H32*$I$17,0),"") -> 197259 | J32: =IFERROR((I32-H32)/I32,"") -> 0.29577358
B33: 1U. 2 x MADI-Optical bi-directional converter. BNC & etherCON MADI / NC. Dual PSU. Multimode Optics | G33: =IF(F33-F33*0%=0,"",F33-F33*0%) | H33: =IFERROR(G33*$H$17,"") | I33: =IFERROR(ROUND(H33*$I$17,0),"") | J33: =IFERROR((I33-H33)/I33,"")
G34: =IF(F34-F34*0%=0,"",F34-F34*0%) | H34: =IFERROR(G34*$H$17,"") | I34: =IFERROR(ROUND(H34*$I$17,0),"") | J34: =IFERROR((I34-H34)/I34,"")
A35: X-PB-ST | B35: DiGiCo Purple Box - Multimode ST | E35: =ROUND(F35/0.55,0) -> 1497 | F35: 823.5 | G35: =IF(F35-F35*0%=0,"",F35-F35*0%) -> 823.5 | H35: =IFERROR(G35*$H$17,"") -> 121054.5 | I35: =IFERROR(ROUND(H35*$I$17,0),"") -> 171897 | J35: =IFERROR((I35-H35)/I35,"") -> 0.29577305
B36: 1U. 2 x MADI-Optical bi-directional converter. BNC & etherCON MADI / ST. Dual PSU. Multimode Optics | G36: =IF(F36-F36*0%=0,"",F36-F36*0%) | H36: =IFERROR(G36*$H$17,"") | I36: =IFERROR(ROUND(H36*$I$17,0),"") | J36: =IFERROR((I36-H36)/I36,"")
G37: =IF(F37-F37*0%=0,"",F37-F37*0%) | H37: =IFERROR(G37*$H$17,"") | I37: =IFERROR(ROUND(H37*$I$17,0),"") | J37: =IFERROR((I37-H37)/I37,"")
A38: X-PB-OP-S | B38: DiGiCo Purple Box - Singlemode HMA | E38: =ROUND(F38/0.55,0) -> 6055 | F38: 3330 | G38: =IF(F38-F38*0%=0,"",F38-F38*0%) -> 3330 | H38: =IFERROR(G38*$H$17,"") -> 489510 | I38: =IFERROR(ROUND(H38*$I$17,0),"") -> 695104 | J38: =IFERROR((I38-H38)/I38,"") -> 0.29577445
B39: 1U. 2 x MADI-Optical bi-directional converter. BNC & etherCON MADI / HMA. Dual PSU. Singlemode Optics | G39: =IF(F39-F39*0%=0,"",F39-F39*0%) | H39: =IFERROR(G39*$H$17,"") | I39: =IFERROR(ROUND(H39*$I$17,0),"") | J39: =IFERROR((I39-H39)/I39,"")
G40: =IF(F40-F40*0%=0,"",F40-F40*0%) | H40: =IFERROR(G40*$H$17,"") | I40: =IFERROR(ROUND(H40*$I$17,0),"") | J40: =IFERROR((I40-H40)/I40,"")
A41: X-PB-NC-S | B41: DiGiCo Purple Box - Singlemode OpticalCON | E41: =ROUND(F41/0.55,0) -> 3845 | F41: 2115 | G41: =IF(F41-F41*0%=0,"",F41-F41*0%) -> 2115 | H41: =IFERROR(G41*$H$17,"") -> 310905 | I41: =IFERROR(ROUND(H41*$I$17,0),"") -> 441485 | J41: =IFERROR((I41-H41)/I41,"") -> 0.29577449
B42: 1U. 2 x MADI-Optical bi-directional converter. BNC & etherCON MADI / NC. Dual PSU. Singlemode Optics | G42: =IF(F42-F42*0%=0,"",F42-F42*0%) | H42: =IFERROR(G42*$H$17,"") | I42: =IFERROR(ROUND(H42*$I$17,0),"") | J42: =IFERROR((I42-H42)/I42,"")
G43: =IF(F43-F43*0%=0,"",F43-F43*0%) | H43: =IFERROR(G43*$H$17,"") | I43: =IFERROR(ROUND(H43*$I$17,0),"") | J43: =IFERROR((I43-H43)/I43,"")
A44: X-PB-ST-S | B44: DiGiCo Purple Box - Singlemode ST | E44: =ROUND(F44/0.55,0) -> 3215 | F44: 1768.5 | G44: =IF(F44-F44*0%=0,"",F44-F44*0%) -> 1768.5 | H44: =IFERROR(G44*$H$17,"") -> 259969.5 | I44: =IFERROR(ROUND(H44*$I$17,0),"") -> 369157 | J44: =IFERROR((I44-H44)/I44,"") -> 0.29577524
B45: 1U. 2 x MADI-Optical bi-directional converter. BNC & etherCON MADI / ST. Dual PSU. Singlemode Optics | G45: =IF(F45-F45*0%=0,"",F45-F45*0%) | H45: =IFERROR(G45*$H$17,"") | I45: =IFERROR(ROUND(H45*$I$17,0),"") | J45: =IFERROR((I45-H45)/I45,"")
J46: =IFERROR((I46-H46)/I46,"")
J47: =IFERROR((I47-H47)/I47,"")
J48: =IFERROR((I48-H48)/I48,"")
A49: Product Code | B49: Description | E49: MAP (£) | F49: Distributor (£) | G49: Disc. () | J49: =IFERROR((I49-H49)/I49,"")
J50: =IFERROR((I50-H50)/I50,"")
A51: DiGiCo UB MADI, Orange Box and DMI Card Options (please refer to compatability chart below) | F51: 0 | J51: =IFERROR((I51-H51)/I51,"")
J52: =IFERROR((I52-H52)/I52,"")
A53: X-UBMADI | B53: DiGiCo UB MADI | E53: 528 | F53: 337.5 | G53: =IF(F53-F53*0%=0,"",F53-F53*0%) -> 337.5 | H53: =IFERROR(G53*$H$17,"") -> 49612.5 | I53: =IFERROR(ROUND(H53*$I$17,0),"") -> 70450 | J53: =IFERROR((I53-H53)/I53,"") -> 0.29577715
B54: 48ch MADI to USB2 interface. Includes USB cable and Drivers. 48kHz sampling rate only. | G54: =IF(F54-F54*0%=0,"",F54-F54*0%) | H54: =IFERROR(G54*$H$17,"") | I54: =IFERROR(ROUND(H54*$I$17,0),"") | J54: =IFERROR((I54-H54)/I54,"")
G55: =IF(F55-F55*0%=0,"",F55-F55*0%) | H55: =IFERROR(G55*$H$17,"") | I55: =IFERROR(ROUND(H55*$I$17,0),"") | J55: =IFERROR((I55-H55)/I55,"")
A56: X-OB | B56: DiGiCo Orange Box | E56: =ROUND(F56/0.54,0) -> 1098 | F56: 592.875 | G56: =IF(F56-F56*0%=0,"",F56-F56*0%) -> 592.875 | H56: =IFERROR(G56*$H$17,"") -> 87152.625 | I56: =IFERROR(ROUND(H56*$I$17,0),"") -> 123757 | J56: =IFERROR((I56-H56)/I56,"") -> 0.2957762
B57: 2U. Format Converter. 2 DMI slots, 2 PSU. | G57: =IF(F57-F57*0%=0,"",F57-F57*0%) | H57: =IFERROR(G57*$H$17,"") | I57: =IFERROR(ROUND(H57*$I$17,0),"") | J57: =IFERROR((I57-H57)/I57,"")
G58: =IF(F58-F58*0%=0,"",F58-F58*0%) | H58: =IFERROR(G58*$H$17,"") | I58: =IFERROR(ROUND(H58*$I$17,0),"") | J58: =IFERROR((I58-H58)/I58,"")
A59: MOD-DMI-MADI-B | B59: DiGiCo DMI MADI BNC I/O card | E59: =ROUND(F59/0.54,0) -> 619 | F59: 334.125 | G59: =IF(F59-F59*0%=0,"",F59-F59*0%) -> 334.125 | H59: =IFERROR(G59*$H$17,"") -> 49116.375 | I59: =IFERROR(ROUND(H59*$I$17,0),"") -> 69745 | J59: =IFERROR((I59-H59)/I59,"") -> 0.2957721
B60: Console Spec: 56/64ch MADI interface at 48KHz or 96Khz. | G60: =IF(F60-F60*0%=0,"",F60-F60*0%) | H60: =IFERROR(G60*$H$17,"") | I60: =IFERROR(ROUND(H60*$I$17,0),"") | J60: =IFERROR((I60-H60)/I60,"")
B61: OB Spec: 112/128ch at 48kHz or 56/64ch at 96Khz MADI interface. 2pr BNC | G61: =IF(F61-F61*0%=0,"",F61-F61*0%) | H61: =IFERROR(G61*$H$17,"") | I61: =IFERROR(ROUND(H61*$I$17,0),"") | J61: =IFERROR((I61-H61)/I61,"")
G62: =IF(F62-F62*0%=0,"",F62-F62*0%) | H62: =IFERROR(G62*$H$17,"") | I62: =IFERROR(ROUND(H62*$I$17,0),"") | J62: =IFERROR((I62-H62)/I62,"")
A63: MOD-DMI-MADI-C | B63: DiGiCo DMI MADI CAT5 I/O card | E63: =ROUND(F63/0.54,0) -> 619 | F63: 334.125 | G63: =IF(F63-F63*0%=0,"",F63-F63*0%) -> 334.125 | H63: =IFERROR(G63*$H$17,"") -> 49116.375 | I63: =IFERROR(ROUND(H63*$I$17,0),"") -> 69745 | J63: =IFERROR((I63-H63)/I63,"") -> 0.2957721
B64: Console Spec: 56/64ch MADI interface at 48KHz or 96Khz. | G64: =IF(F64-F64*0%=0,"",F64-F64*0%) | H64: =IFERROR(G64*$H$17,"") | I64: =IFERROR(ROUND(H64*$I$17,0),"") | J64: =IFERROR((I64-H64)/I64,"")
B65: OB Spec: 112/128ch at 48kHz or 56/64ch at 96Khz MADI interface. 2 etherCON. | G65: =IF(F65-F65*0%=0,"",F65-F65*0%) | H65: =IFERROR(G65*$H$17,"") | I65: =IFERROR(ROUND(H65*$I$17,0),"") | J65: =IFERROR((I65-H65)/I65,"")
G66: =IF(F66-F66*0%=0,"",F66-F66*0%) | H66: =IFERROR(G66*$H$17,"") | I66: =IFERROR(ROUND(H66*$I$17,0),"") | J66: =IFERROR((I66-H66)/I66,"")
A67: MOD-DMI-MICPRE | B67: DiGiCo DMI mic preamp input module | E67: =ROUND(F67/0.54,0) -> 765 | F67: 412.875 | G67: =IF(F67-F67*0%=0,"",F67-F67*0%) -> 412.875 | H67: =IFERROR(G67*$H$17,"") -> 60692.625 | I67: =IFERROR(ROUND(H67*$I$17,0),"") -> 86184 | J67: =IFERROR((I67-H67)/I67,"") -> 0.29577851
B68: 8 mic preamp inputs. 1 x 25-way D-type connection. | G68: =IF(F68-F68*0%=0,"",F68-F68*0%) | H68: =IFERROR(G68*$H$17,"") | I68: =IFERROR(ROUND(H68*$I$17,0),"") | J68: =IFERROR((I68-H68)/I68,"")
G69: =IF(F69-F69*0%=0,"",F69-F69*0%) | H69: =IFERROR(G69*$H$17,"") | I69: =IFERROR(ROUND(H69*$I$17,0),"") | J69: =IFERROR((I69-H69)/I69,"")
A70: MOD-DMI-ADC | B70: DiGiCo DMI line input card | E70: =ROUND(F70/0.54,0) -> 619 | F70: 334.125 | G70: =IF(F70-F70*0%=0,"",F70-F70*0%) -> 334.125 | H70: =IFERROR(G70*$H$17,"") -> 49116.375 | I70: =IFERROR(ROUND(H70*$I$17,0),"") -> 69745 | J70: =IFERROR((I70-H70)/I70,"") -> 0.2957721
B71: 16 line inputs. 2 x 25-way D-type connection. | G71: =IF(F71-F71*0%=0,"",F71-F71*0%) | H71: =IFERROR(G71*$H$17,"") | I71: =IFERROR(ROUND(H71*$I$17,0),"") | J71: =IFERROR((I71-H71)/I71,"")
G72: =IF(F72-F72*0%=0,"",F72-F72*0%) | H72: =IFERROR(G72*$H$17,"") | I72: =IFERROR(ROUND(H72*$I$17,0),"") | J72: =IFERROR((I72-H72)/I72,"")
A73: MOD-DMI-DAC | B73: DiGiCo DMI line output card | E73: =ROUND(F73/0.54,0) -> 817 | F73: 441 | G73: =IF(F73-F73*0%=0,"",F73-F73*0%) -> 441 | H73: =IFERROR(G73*$H$17,"") -> 64827 | I73: =IFERROR(ROUND(H73*$I$17,0),"") -> 92054 | J73: =IFERROR((I73-H73)/I73,"") -> 0.29577205
B74: 16 line outputs. 2 x 25-way D-type connection. | G74: =IF(F74-F74*0%=0,"",F74-F74*0%) | H74: =IFERROR(G74*$H$17,"") | I74: =IFERROR(ROUND(H74*$I$17,0),"") | J74: =IFERROR((I74-H74)/I74,"")
G75: =IF(F75-F75*0%=0,"",F75-F75*0%) | H75: =IFERROR(G75*$H$17,"") | I75: =IFERROR(ROUND(H75*$I$17,0),"") | J75: =IFERROR((I75-H75)/I75,"")
A76: MOD-DMI-AES | B76: DiGiCo DMI AES I/O card | E76: =ROUND(F76/0.54,0) -> 760 | F76: 410.625 | G76: =IF(F76-F76*0%=0,"",F76-F76*0%) -> 410.625 | H76: =IFERROR(G76*$H$17,"") -> 60361.875 | I76: =IFERROR(ROUND(H76*$I$17,0),"") -> 85714 | J76: =IFERROR((I76-H76)/I76,"") -> 0.29577578
B77: 16 AES3 mono I/O. 2 x 25-way D-type connection. | G77: =IF(F77-F77*0%=0,"",F77-F77*0%) | H77: =IFERROR(G77*$H$17,"") | I77: =IFERROR(ROUND(H77*$I$17,0),"") | J77: =IFERROR((I77-H77)/I77,"")
G78: =IF(F78-F78*0%=0,"",F78-F78*0%) | H78: =IFERROR(G78*$H$17,"") | I78: =IFERROR(ROUND(H78*$I$17,0),"") | J78: =IFERROR((I78-H78)/I78,"")
A79: MOD-DMI-DANTE2 | B79: DiGiCo DMI Dante 64@96 SRC I/O card | E79: =ROUND(F79/0.54,0) -> 1202 | F79: 649 | G79: =IF(F79-F79*20%=0,"",F79-F79*20%) -> 519.2 | H79: =IFERROR(G79*$H$17,"") -> 76322.4 | I79: =IFERROR(ROUND(H79*$I$17,0),"") -> 108378 | J79: =IFERROR((I79-H79)/I79,"") -> 0.2957759
B80: 64ch (48/96kHz) Dante interface with SRC. 2 etherCON, RJ45. | G80: =IF(F80-F80*20%=0,"",F80-F80*20%) | H80: =IFERROR(G80*$H$17,"") | I80: =IFERROR(ROUND(H80*$I$17,0),"") | J80: =IFERROR((I80-H80)/I80,"")
G81: =IF(F81-F81*20%=0,"",F81-F81*20%) | H81: =IFERROR(G81*$H$17,"") | I81: =IFERROR(ROUND(H81*$I$17,0),"") | J81: =IFERROR((I81-H81)/I81,"")
A82: MOD-DMI-WAVES | B82: DiGiCo DMI Waves I/O card | E82: =ROUND(F82/0.54,0) -> 1072 | F82: 579 | G82: =IF(F82-F82*0%=0,"",F82-F82*0%) -> 579 | H82: =IFERROR(G82*$H$17,"") -> 85113 | I82: =IFERROR(ROUND(H82*$I$17,0),"") -> 120860 | J82: =IFERROR((I82-H82)/I82,"") -> 0.29577197
B83: 64ch Waves Soundgrid interface. 2 etherCON | G83: =IF(F83-F83*0%=0,"",F83-F83*0%) | H83: =IFERROR(G83*$H$17,"") | I83: =IFERROR(ROUND(H83*$I$17,0),"") | J83: =IFERROR((I83-H83)/I83,"")
G84: =IF(F84-F84*0%=0,"",F84-F84*0%) | H84: =IFERROR(G84*$H$17,"") | I84: =IFERROR(ROUND(H84*$I$17,0),"") | J84: =IFERROR((I84-H84)/I84,"")
A85: MOD-DMI-HYDRA2 | B85: DiGiCo DMI Hydra 2 I/O card | E85: =ROUND(F85/0.54,0) -> 2531 | F85: 1366.875 | G85: =IF(F85-F85*0%=0,"",F85-F85*0%) -> 1366.875 | H85: =IFERROR(G85*$H$17,"") -> 200930.62 | I85: =IFERROR(ROUND(H85*$I$17,0),"") -> 285321 | J85: =IFERROR((I85-H85)/I85,"") -> 0.29577344
B86: 56ch 48kHz Calrec Hydra 2 interface. 2 LC optical. | G86: =IF(F86-F86*0%=0,"",F86-F86*0%) | H86: =IFERROR(G86*$H$17,"") | I86: =IFERROR(ROUND(H86*$I$17,0),"") | J86: =IFERROR((I86-H86)/I86,"")
G87: =IF(F87-F87*0%=0,"",F87-F87*0%) | H87: =IFERROR(G87*$H$17,"") | I87: =IFERROR(ROUND(H87*$I$17,0),"") | J87: =IFERROR((I87-H87)/I87,"")
A88: MOD-DMI-AMM | B88: DiGiCo DMI Automatic mic mixer card | E88: =ROUND(F88/0.54,0) -> 619 | F88: 334.125 | G88: =IF(F88-F88*0%=0,"",F88-F88*0%) -> 334.125 | H88: =IFERROR(G88*$H$17,"") -> 49116.375 | I88: =IFERROR(ROUND(H88*$I$17,0),"") -> 69745 | J88: =IFERROR((I88-H88)/I88,"") -> 0.2957721
B89: 48ch S-Series / 64ch Quantum & SD-Series automatic microphone mixing processing module. | G89: =IF(F89-F89*0%=0,"",F89-F89*0%) | H89: =IFERROR(G89*$H$17,"") | I89: =IFERROR(ROUND(H89*$I$17,0),"") | J89: =IFERROR((I89-H89)/I89,"")
G90: =IF(F90-F90*0%=0,"",F90-F90*0%) | H90: =IFERROR(G90*$H$17,"") | I90: =IFERROR(ROUND(H90*$I$17,0),"") | J90: =IFERROR((I90-H90)/I90,"")
A91: MOD-DMI-ME | B91: DiGiCo DMI ME output card | E91: =ROUND(F91/0.54,0) -> 692 | F91: 373.5 | G91: =IF(F91-F91*0%=0,"",F91-F91*0%) -> 373.5 | H91: =IFERROR(G91*$H$17,"") -> 54904.5 | I91: =IFERROR(ROUND(H91*$I$17,0),"") -> 77964 | J91: =IFERROR((I91-H91)/I91,"") -> 0.29577113
B92: 40ch ME output module. Provides compatibility with A&H Personal Mixing System. etherCON | G92: =IF(F92-F92*0%=0,"",F92-F92*0%) | H92: =IFERROR(G92*$H$17,"") | I92: =IFERROR(ROUND(H92*$I$17,0),"") | J92: =IFERROR((I92-H92)/I92,"")
G93: =IF(F93-F93*0%=0,"",F93-F93*0%) | H93: =IFERROR(G93*$H$17,"") | I93: =IFERROR(ROUND(H93*$I$17,0),"") | J93: =IFERROR((I93-H93)/I93,"")
A94: MOD-DMI-A3232 | B94: DiGiCo DMI A3232 I/O card | E94: =ROUND(F94/0.54,0) -> 504 | F94: 272.25 | G94: =IF(F94-F94*0%=0,"",F94-F94*0%) -> 272.25 | H94: =IFERROR(G94*$H$17,"") -> 40020.75 | I94: =IFERROR(ROUND(H94*$I$17,0),"") -> 56829 | J94: =IFERROR((I94-H94)/I94,"") -> 0.29576889
B95: 64ch A3232 interface. 2 etherCON | G95: =IF(F95-F95*0%=0,"",F95-F95*0%) | H95: =IFERROR(G95*$H$17,"") | I95: =IFERROR(ROUND(H95*$I$17,0),"") | J95: =IFERROR((I95-H95)/I95,"")
G96: =IF(F96-F96*0%=0,"",F96-F96*0%) | H96: =IFERROR(G96*$H$17,"") | I96: =IFERROR(ROUND(H96*$I$17,0),"") | J96: =IFERROR((I96-H96)/I96,"")
A97: MOD-DMI-KLANG | B97: DiGiCo DMI KLANG processing card | E97: =ROUND(F97/0.54,0) -> 4063 | F97: 2193.75 | G97: =IF(F97-F97*0%=0,"",F97-F97*0%) -> 2193.75 | H97: =IFERROR(G97*$H$17,"") -> 322481.25 | I97: =IFERROR(ROUND(H97*$I$17,0),"") -> 457923 | J97: =IFERROR((I97-H97)/I97,"") -> 0.29577407
B98: KLANG processing module. 64 inputs. 16 Immersive outputs. 2 etherCON, RJ45, USB | G98: =IF(F98-F98*0%=0,"",F98-F98*0%) | H98: =IFERROR(G98*$H$17,"") | I98: =IFERROR(ROUND(H98*$I$17,0),"") | J98: =IFERROR((I98-H98)/I98,"")
G99: =IF(F99-F99*0%=0,"",F99-F99*0%) | H99: =IFERROR(G99*$H$17,"") | I99: =IFERROR(ROUND(H99*$I$17,0),"") | J99: =IFERROR((I99-H99)/I99,"")
A100: MOD-DMI-AVB | B100: DiGiCo DMI AVB I/O card | E100: =ROUND(F100/0.54,0) -> 1202 | F100: 649 | G100: =IF(F100-F100*15%=0,"",F100-F100*15%) -> 551.65 | H100: =IFERROR(G100*$H$17,"") -> 81092.55 | I100: =IFERROR(ROUND(H100*$I$17,0),"") -> 115151 | J100: =IFERROR((I100-H100)/I100,"") -> 0.29577207
B101: 64ch (48/96kHz) AVB interface. 2 x etherCON, USB | G101: =IF(F101-F101*15%=0,"",F101-F101*15%) | H101: =IFERROR(G101*$H$17,"") | I101: =IFERROR(ROUND(H101*$I$17,0),"") | J101: =IFERROR((I101-H101)/I101,"")
G102: =IF(F102-F102*15%=0,"",F102-F102*15%) | H102: =IFERROR(G102*$H$17,"") | I102: =IFERROR(ROUND(H102*$I$17,0),"") | J102: =IFERROR((I102-H102)/I102,"")
A103: MOD-DMI-OPTO | B103: DiGiCo DMI Optocore I/O card - HMA | E103: =ROUND(F103/0.54,0) -> 3369 | F103: 1819.125 | G103: =IF(F103-F103*0%=0,"",F103-F103*0%) -> 1819.125 | H103: =IFERROR(G103*$H$17,"") -> 267411.38 | I103: =IFERROR(ROUND(H103*$I$17,0),"") -> 379724 | J103: =IFERROR((I103-H103)/I103,"") -> 0.29577437
B104: OB Spec: 128ch at 48kHz or 64ch at 96kHz Optocore interface. HMA expanded beam optic connection. | G104: =IF(F104-F104*0%=0,"",F104-F104*0%) | H104: =IFERROR(G104*$H$17,"") | I104: =IFERROR(ROUND(H104*$I$17,0),"") | J104: =IFERROR((I104-H104)/I104,"")
G105: =IF(F105-F105*0%=0,"",F105-F105*0%) | H105: =IFERROR(G105*$H$17,"") | I105: =IFERROR(ROUND(H105*$I$17,0),"") | J105: =IFERROR((I105-H105)/I105,"")
A106: MOD-DMI-OP-NC | B106: DiGiCo DMI Optocore I/O card - OpticalCON | E106: =ROUND(F106/0.54,0) -> 2194 | F106: 1184.625 | G106: =IF(F106-F106*0%=0,"",F106-F106*0%) -> 1184.625 | H106: =IFERROR(G106*$H$17,"") -> 174139.88 | I106: =IFERROR(ROUND(H106*$I$17,0),"") -> 247279 | J106: =IFERROR((I106-H106)/I106,"") -> 0.29577572
...

Sheet Racks
B2: DiGiCo Racks, Cards & Cables Distributor Price List
B4: Sept 2024
B6: Unit 10 Silverglade Business Park, Leatherhead Road
B7: Chessington, Surrey, KT9 2QL
B8: Tel; +44 1372 845600
B9: Fax; +44 1372 845656
B10: email; sales@digiconsoles.com
B11: web; www.digiconsoles.com
B13: FCA Glenrothes KY7 4NX. E&OE. Prices, Products and Specification are subject to change without notice.
B14: This price list supercedes all previous price lists.
A16: Product Code | B16: Description | E16: List (£) | F16: Distributor (£) | G16: Disc. () | H16: HT Buy (INR) | I16: Customer Price | J16: Hi-Tech
H17: 147 | I17: 1.42 | J17: Margin
A18: DiGiCo SD-Rack
A20: X-SD-RACK | B20: DiGiCo SD-Rack 192khz (unloaded) | E20: =ROUND(F20/0.55,0) -> 6218 | F20: 3420 | G20: =IF(F20-F20*20%=0,"",F20-F20*20%) -> 2736 | H20: =IFERROR(G20*$H$17,"") -> 402192 | I20: =IFERROR(ROUND(H20*$I$17,0),"") -> 571113 | J20: =IFERROR((I20-H20)/I20,"") -> 0.29577509
B21: 10u Rackframe, 2 PSU's, 14 slots, 2 BNC MADI, 2 Splits, rack kit | G21: =IF(F21-F21*20%=0,"",F21-F21*20%) | H21: =IFERROR(G21*$H$17,"") | I21: =IFERROR(ROUND(H21*$I$17,0),"") | J21: =IFERROR((I21-H21)/I21,"")
B22: 2 x 5m BNC cable, 2 x 100m BNC cable | G22: =IF(F22-F22*20%=0,"",F22-F22*20%) | H22: =IFERROR(G22*$H$17,"") | I22: =IFERROR(ROUND(H22*$I$17,0),"") | J22: =IFERROR((I22-H22)/I22,"")
B23: Dimensions; 483(w) x 444(h) x 371(d) mm Weight; 24Kg | G23: =IF(F23-F23*20%=0,"",F23-F23*20%) | H23: =IFERROR(G23*$H$17,"") | I23: =IFERROR(ROUND(H23*$I$17,0),"") | J23: =IFERROR((I23-H23)/I23,"")
G24: =IF(F24-F24*20%=0,"",F24-F24*20%) | H24: =IFERROR(G24*$H$17,"") | I24: =IFERROR(ROUND(H24*$I$17,0),"") | J24: =IFERROR((I24-H24)/I24,"")
A25: X-SD-RACK-O | B25: DiGiCo SD-Rack 192khz (unloaded) with HMA Optics | E25: =ROUND(F25/0.55,0) -> 9444 | F25: 5194.125 | G25: =IF(F25-F25*20%=0,"",F25-F25*20%) -> 4155.3 | H25: =IFERROR(G25*$H$17,"") -> 610829.1 | I25: =IFERROR(ROUND(H25*$I$17,0),"") -> 867377 | J25: =IFERROR((I25-H25)/I25,"") -> 0.29577439
B26: 10u Rackframe, 2 PSU's, 14 slots, 2 BNC MADI, 2 Splits, 2 HMA optic connections, rack kit | G26: =IF(F26-F26*20%=0,"",F26-F26*20%) | H26: =IFERROR(G26*$H$17,"") | I26: =IFERROR(ROUND(H26*$I$17,0),"") | J26: =IFERROR((I26-H26)/I26,"")
B27: 2 x 5m BNC cable, 2 x 100m BNC cable | G27: =IF(F27-F27*20%=0,"",F27-F27*20%) | H27: =IFERROR(G27*$H$17,"") | I27: =IFERROR(ROUND(H27*$I$17,0),"") | J27: =IFERROR((I27-H27)/I27,"")
B28: Dimensions; 483(w) x 444(h) x 371(d) mm Weight; 24Kg | G28: =IF(F28-F28*20%=0,"",F28-F28*20%) | H28: =IFERROR(G28*$H$17,"") | I28: =IFERROR(ROUND(H28*$I$17,0),"") | J28: =IFERROR((I28-H28)/I28,"")
G29: =IF(F29-F29*20%=0,"",F29-F29*20%) | H29: =IFERROR(G29*$H$17,"") | I29: =IFERROR(ROUND(H29*$I$17,0),"") | J29: =IFERROR((I29-H29)/I29,"")
A30: X-SD-RACK-NC | B30: DiGiCo SD-Rack 192khz (unloaded) with OpticalCON Optics | E30: =ROUND(F30/0.55,0) -> 8331 | F30: 4582.125 | G30: =IF(F30-F30*20%=0,"",F30-F30*20%) -> 3665.7 | H30: =IFERROR(G30*$H$17,"") -> 538857.9 | I30: =IFERROR(ROUND(H30*$I$17,0),"") -> 765178 | J30: =IFERROR((I30-H30)/I30,"") -> 0.29577445
B31: 10u Rackframe, 2 PSU's, 14 slots, 2 BNC MADI, 2 Splits, 2 OpticalCON connections, rack kit | G31: =IF(F31-F31*20%=0,"",F31-F31*20%) | H31: =IFERROR(G31*$H$17,"") | I31: =IFERROR(ROUND(H31*$I$17,0),"") | J31: =IFERROR((I31-H31)/I31,"")
B32: 2 x 5m BNC cable, 2 x 100m BNC cable | G32: =IF(F32-F32*20%=0,"",F32-F32*20%) | H32: =IFERROR(G32*$H$17,"") | I32: =IFERROR(ROUND(H32*$I$17,0),"") | J32: =IFERROR((I32-H32)/I32,"")
B33: Dimensions; 483(w) x 444(h) x 371(d) mm Weight; 24Kg | G33: =IF(F33-F33*20%=0,"",F33-F33*20%) | H33: =IFERROR(G33*$H$17,"") | I33: =IFERROR(ROUND(H33*$I$17,0),"") | J33: =IFERROR((I33-H33)/I33,"")
G34: =IF(F34-F34*20%=0,"",F34-F34*20%) | H34: =IFERROR(G34*$H$17,"") | I34: =IFERROR(ROUND(H34*$I$17,0),"") | J34: =IFERROR((I34-H34)/I34,"")
A35: X-SD-RACK-ST | B35: DiGiCo SD-Rack 192khz (unloaded) with ST Optics | E35: =ROUND(F35/0.55,0) -> 8118 | F35: 4465.125 | G35: =IF(F35-F35*20%=0,"",F35-F35*20%) -> 3572.1 | H35: =IFERROR(G35*$H$17,"") -> 525098.7 | I35: =IFERROR(ROUND(H35*$I$17,0),"") -> 745640 | J35: =IFERROR((I35-H35)/I35,"") -> 0.2957745
B36: 10u Rackframe, 2 PSU's, 14 slots, 2 BNC MADI, 2 Splits, 2 ST optic connections, rack kit | G36: =IF(F36-F36*20%=0,"",F36-F36*20%) | H36: =IFERROR(G36*$H$17,"") | I36: =IFERROR(ROUND(H36*$I$17,0),"") | J36: =IFERROR((I36-H36)/I36,"")
B37: 2 x 5m BNC cable, 2 x 100m BNC cable | G37: =IF(F37-F37*20%=0,"",F37-F37*20%) | H37: =IFERROR(G37*$H$17,"") | I37: =IFERROR(ROUND(H37*$I$17,0),"") | J37: =IFERROR((I37-H37)/I37,"")
B38: Dimensions; 483(w) x 444(h) x 371(d) mm Weight; 24Kg | G38: =IF(F38-F38*20%=0,"",F38-F38*20%) | H38: =IFERROR(G38*$H$17,"") | I38: =IFERROR(ROUND(H38*$I$17,0),"") | J38: =IFERROR((I38-H38)/I38,"")
G39: =IF(F39-F39*20%=0,"",F39-F39*20%) | H39: =IFERROR(G39*$H$17,"") | I39: =IFERROR(ROUND(H39*$I$17,0),"") | J39: =IFERROR((I39-H39)/I39,"")
A40: DiGiCo SD-MINI Rack | E40: =ROUND(F40/0.55,0) -> 0 | G40: =IF(F40-F40*20%=0,"",F40-F40*20%) | H40: =IFERROR(G40*$H$17,"") | I40: =IFERROR(ROUND(H40*$I$17,0),"") | J40: =IFERROR((I40-H40)/I40,"")
G41: =IF(F41-F41*15%=0,"",F41-F41*15%) | H41: =IFERROR(G41*$H$17,"") | I41: =IFERROR(ROUND(H41*$I$17,0),"") | J41: =IFERROR((I41-H41)/I41,"")
A42: X-SDRM-MADI | B42: DiGiCo SD-MINI Rack 192khz (unloaded) | E42: =ROUND(F42/0.55,0) -> 3878 | F42: 2133 | G42: =IF(F42-F42*15%=0,"",F42-F42*15%) -> 1813.05 | H42: =IFERROR(G42*$H$17,"") -> 266518.35 | I42: =IFERROR(ROUND(H42*$I$17,0),"") -> 378456 | J42: =IFERROR((I42-H42)/I42,"") -> 0.29577454
B43: 4u Rackframe, 2 PSU's, 4 slots, 2 BNC MADI, 2 Splits, rack kit, 2 x 5m BNC cable | G43: =IF(F43-F43*15%=0,"",F43-F43*15%) | H43: =IFERROR(G43*$H$17,"") | I43: =IFERROR(ROUND(H43*$I$17,0),"") | J43: =IFERROR((I43-H43)/I43,"")
B44: Dimensions; 483(w) x 177(h) x 408(d) mm Weight; 12Kg | G44: =IF(F44-F44*15%=0,"",F44-F44*15%) | H44: =IFERROR(G44*$H$17,"") | I44: =IFERROR(ROUND(H44*$I$17,0),"") | J44: =IFERROR((I44-H44)/I44,"")
G45: =IF(F45-F45*15%=0,"",F45-F45*15%) | H45: =IFERROR(G45*$H$17,"") | I45: =IFERROR(ROUND(H45*$I$17,0),"") | J45: =IFERROR((I45-H45)/I45,"")
A46: X-SDRM-OP | B46: DiGiCo SD-MINI Rack 192khz (unloaded) with HMA Optics | E46: =ROUND(F46/0.55,0) -> 7102 | F46: 3906 | G46: =IF(F46-F46*15%=0,"",F46-F46*15%) -> 3320.1 | H46: =IFERROR(G46*$H$17,"") -> 488054.7 | I46: =IFERROR(ROUND(H46*$I$17,0),"") -> 693038 | J46: =IFERROR((I46-H46)/I46,"") -> 0.29577498
B47: 4u Rackframe, 2 PSU's, 4 slots, 2 BNC MADI, 2 Splits, 2 HMA optic connections, rack kit, 2 x 5m BNC cable | G47: =IF(F47-F47*15%=0,"",F47-F47*15%) | H47: =IFERROR(G47*$H$17,"") | I47: =IFERROR(ROUND(H47*$I$17,0),"") | J47: =IFERROR((I47-H47)/I47,"")
B48: Dimensions; 483(w) x 177(h) x 408(d) mm Weight; 12Kg | G48: =IF(F48-F48*15%=0,"",F48-F48*15%) | H48: =IFERROR(G48*$H$17,"") | I48: =IFERROR(ROUND(H48*$I$17,0),"") | J48: =IFERROR((I48-H48)/I48,"")
G49: =IF(F49-F49*15%=0,"",F49-F49*15%) | H49: =IFERROR(G49*$H$17,"") | I49: =IFERROR(ROUND(H49*$I$17,0),"") | J49: =IFERROR((I49-H49)/I49,"")
A50: X-SDRM-NC | B50: DiGiCo SD-MINI Rack 192khz (unloaded) with OpticalCON Optics | E50: =ROUND(F50/0.55,0) -> 5989 | F50: 3294 | G50: =IF(F50-F50*15%=0,"",F50-F50*15%) -> 2799.9 | H50: =IFERROR(G50*$H$17,"") -> 411585.3 | I50: =IFERROR(ROUND(H50*$I$17,0),"") -> 584451 | J50: =IFERROR((I50-H50)/I50,"") -> 0.2957745
B51: 4u Rackframe, 2 PSU's, 4 slots, 2 BNC MADI, 2 Splits, 2 OpticalCON connections, rack kit, 2 x 5m BNC cable | G51: =IF(F51-F51*15%=0,"",F51-F51*15%) | H51: =IFERROR(G51*$H$17,"") | I51: =IFERROR(ROUND(H51*$I$17,0),"") | J51: =IFERROR((I51-H51)/I51,"")
B52: Dimensions; 483(w) x 177(h) x 408(d) mm Weight; 12Kg | G52: =IF(F52-F52*15%=0,"",F52-F52*15%) | H52: =IFERROR(G52*$H$17,"") | I52: =IFERROR(ROUND(H52*$I$17,0),"") | J52: =IFERROR((I52-H52)/I52,"")
G53: =IF(F53-F53*15%=0,"",F53-F53*15%) | H53: =IFERROR(G53*$H$17,"") | I53: =IFERROR(ROUND(H53*$I$17,0),"") | J53: =IFERROR((I53-H53)/I53,"")
A54: X-SDRM-ST | B54: DiGiCo SD-MINI Rack 192khz (unloaded) with ST Optics | E54: =ROUND(F54/0.55,0) -> 5776 | F54: 3177 | G54: =IF(F54-F54*15%=0,"",F54-F54*15%) -> 2700.45 | H54: =IFERROR(G54*$H$17,"") -> 396966.15 | I54: =IFERROR(ROUND(H54*$I$17,0),"") -> 563692 | J54: =IFERROR((I54-H54)/I54,"") -> 0.29577473
B55: 4u Rackframe, 2 PSU's, 4 slots, 2 BNC MADI, 2 Splits, 2 ST optic connections, rack kit,,2 x 5m BNC cable | G55: =IF(F55-F55*15%=0,"",F55-F55*15%) | H55: =IFERROR(G55*$H$17,"") | I55: =IFERROR(ROUND(H55*$I$17,0),"") | J55: =IFERROR((I55-H55)/I55,"")
B56: Dimensions; 483(w) x 177(h) x 408(d) mm Weight; 12Kg | G56: =IF(F56-F56*15%=0,"",F56-F56*15%) | H56: =IFERROR(G56*$H$17,"") | I56: =IFERROR(ROUND(H56*$I$17,0),"") | J56: =IFERROR((I56-H56)/I56,"")
G57: =IF(F57-F57*15%=0,"",F57-F57*15%) | H57: =IFERROR(G57*$H$17,"") | I57: =IFERROR(ROUND(H57*$I$17,0),"") | J57: =IFERROR((I57-H57)/I57,"")
A58: DiGiCo SD-NANO Rack | E58: =ROUND(F58/0.55,0) -> 0 | G58: =IF(F58-F58*15%=0,"",F58-F58*15%) | H58: =IFERROR(G58*$H$17,"") | I58: =IFERROR(ROUND(H58*$I$17,0),"") | J58: =IFERROR((I58-H58)/I58,"")
G59: =IF(F59-F59*15%=0,"",F59-F59*15%) | H59: =IFERROR(G59*$H$17,"") | I59: =IFERROR(ROUND(H59*$I$17,0),"") | J59: =IFERROR((I59-H59)/I59,"")
A60: X-SDRN-OP | B60: DiGiCo SD-NANO Rack 192khz (unloaded) with HMA Optics | E60: =ROUND(F60/0.55,0) -> 4754 | F60: 2614.5 | G60: =IF(F60-F60*15%=0,"",F60-F60*15%) -> 2222.325 | H60: =IFERROR(G60*$H$17,"") -> 326681.77 | I60: =IFERROR(ROUND(H60*$I$17,0),"") -> 463888 | J60: =IFERROR((I60-H60)/I60,"") -> 0.29577446
B61: 2u Rackframe, 2 PSU's, 2 slots, 2 Splits, 2 HMA connections, rack kit | G61: =IF(F61-F61*15%=0,"",F61-F61*15%) | H61: =IFERROR(G61*$H$17,"") | I61: =IFERROR(ROUND(H61*$I$17,0),"") | J61: =IFERROR((I61-H61)/I61,"")
B62: Dimensions; 483(w) x 88(h) x 442(d) mm Weight; 8Kg | G62: =IF(F62-F62*15%=0,"",F62-F62*15%) | H62: =IFERROR(G62*$H$17,"") | I62: =IFERROR(ROUND(H62*$I$17,0),"") | J62: =IFERROR((I62-H62)/I62,"")
G63: =IF(F63-F63*15%=0,"",F63-F63*15%) | H63: =IFERROR(G63*$H$17,"") | I63: =IFERROR(ROUND(H63*$I$17,0),"") | J63: =IFERROR((I63-H63)/I63,"")
A64: X-SDRN-NC | B64: DiGiCo SD-NANO Rack 192khz (unloaded) with OpticalCON Optics | E64: =ROUND(F64/0.55,0) -> 3625 | F64: 1993.5 | G64: =IF(F64-F64*15%=0,"",F64-F64*15%) -> 1694.475 | H64: =IFERROR(G64*$H$17,"") -> 249087.82 | I64: =IFERROR(ROUND(H64*$I$17,0),"") -> 353705 | J64: =IFERROR((I64-H64)/I64,"") -> 0.29577522
B65: 2u Rackframe, 2 PSU's, 2 slots, 2 Splits, 2 OpticalCON connections, rack kit | G65: =IF(F65-F65*15%=0,"",F65-F65*15%) | H65: =IFERROR(G65*$H$17,"") | I65: =IFERROR(ROUND(H65*$I$17,0),"") | J65: =IFERROR((I65-H65)/I65,"")
B66: Dimensions; 483(w) x 88(h) x 442(d) mm Weight; 8Kg | G66: =IF(F66-F66*15%=0,"",F66-F66*15%) | H66: =IFERROR(G66*$H$17,"") | I66: =IFERROR(ROUND(H66*$I$17,0),"") | J66: =IFERROR((I66-H66)/I66,"")
G67: =IF(F67-F67*15%=0,"",F67-F67*15%) | H67: =IFERROR(G67*$H$17,"") | I67: =IFERROR(ROUND(H67*$I$17,0),"") | J67: =IFERROR((I67-H67)/I67,"")
A68: X-SDRN-ST | B68: DiGiCo SD-NANO Rack 192khz (unloaded) with ST Optics | E68: =ROUND(F68/0.55,0) -> 3428 | F68: 1885.5 | G68: =IF(F68-F68*15%=0,"",F68-F68*15%) -> 1602.675 | H68: =IFERROR(G68*$H$17,"") -> 235593.23 | I68: =IFERROR(ROUND(H68*$I$17,0),"") -> 334542 | J68: =IFERROR((I68-H68)/I68,"") -> 0.29577385
B69: 2u Rackframe, 2 PSU's, 2 slots, 2 Splits, 2 ST optic connections, rack kit | G69: =IF(F69-F69*15%=0,"",F69-F69*15%) | H69: =IFERROR(G69*$H$17,"") | I69: =IFERROR(ROUND(H69*$I$17,0),"") | J69: =IFERROR((I69-H69)/I69,"")
B70: Dimensions; 483(w) x 88(h) x 442(d) mm Weight; 8Kg | G70: =IF(F70-F70*15%=0,"",F70-F70*15%) | H70: =IFERROR(G70*$H$17,"") | I70: =IFERROR(ROUND(H70*$I$17,0),"") | J70: =IFERROR((I70-H70)/I70,"")
G71: =IF(F71-F71*15%=0,"",F71-F71*15%) | H71: =IFERROR(G71*$H$17,"") | I71: =IFERROR(ROUND(H71*$I$17,0),"") | J71: =IFERROR((I71-H71)/I71,"")
A72: DiGiCo SD-Rack Options | E72: =ROUND(F72/0.55,0) -> 0 | G72: =IF(F72-F72*15%=0,"",F72-F72*15%) | H72: =IFERROR(G72*$H$17,"") | I72: =IFERROR(ROUND(H72*$I$17,0),"") | J72: =IFERROR((I72-H72)/I72,"")
G73: =IF(F73-F73*15%=0,"",F73-F73*15%) | H73: =IFERROR(G73*$H$17,"") | I73: =IFERROR(ROUND(H73*$I$17,0),"") | J73: =IFERROR((I73-H73)/I73,"")
A74: MOD-SDR-OP-UP | B74: DiGiCo SD-Rack HMA optics upgrade | E74: =ROUND(F74/0.55,0) -> 3224 | F74: 1773 | G74: =IF(F74-F74*15%=0,"",F74-F74*15%) -> 1507.05 | H74: =IFERROR(G74*$H$17,"") -> 221536.35 | I74: =IFERROR(ROUND(H74*$I$17,0),"") -> 314582 | J74: =IFERROR((I74-H74)/I74,"") -> 0.29577551
B75: SD-Rack HMA optics upgrade | G75: =IF(F75-F75*15%=0,"",F75-F75*15%) | H75: =IFERROR(G75*$H$17,"") | I75: =IFERROR(ROUND(H75*$I$17,0),"") | J75: =IFERROR((I75-H75)/I75,"")
G76: =IF(F76-F76*15%=0,"",F76-F76*15%) | H76: =IFERROR(G76*$H$17,"") | I76: =IFERROR(ROUND(H76*$I$17,0),"") | J76: =IFERROR((I76-H76)/I76,"")
A77: MOD-SDR-NC-UP | B77: DiGiCo SD-Rack OpticalCON optics upgrade | E77: =ROUND(F77/0.55,0) -> 2111 | F77: 1161 | G77: =IF(F77-F77*15%=0,"",F77-F77*15%) -> 986.85 | H77: =IFERROR(G77*$H$17,"") -> 145066.95 | I77: =IFERROR(ROUND(H77*$I$17,0),"") -> 205995 | J77: =IFERROR((I77-H77)/I77,"") -> 0.29577441
B78: SD-Rack OpticalCON optics upgrade | G78: =IF(F78-F78*15%=0,"",F78-F78*15%) | H78: =IFERROR(G78*$H$17,"") | I78: =IFERROR(ROUND(H78*$I$17,0),"") | J78: =IFERROR((I78-H78)/I78,"")
G79: =IF(F79-F79*15%=0,"",F79-F79*15%) | H79: =IFERROR(G79*$H$17,"") | I79: =IFERROR(ROUND(H79*$I$17,0),"") | J79: =IFERROR((I79-H79)/I79,"")
A80: MOD-SDR-ST-UP | B80: DiGiCo SD-Rack ST optics upgrade | E80: =ROUND(F80/0.55,0) -> 1898 | F80: 1044 | G80: =IF(F80-F80*15%=0,"",F80-F80*15%) -> 887.4 | H80: =IFERROR(G80*$H$17,"") -> 130447.8 | I80: =IFERROR(ROUND(H80*$I$17,0),"") -> 185236 | J80: =IFERROR((I80-H80)/I80,"") -> 0.29577512
B81: SD-Rack ST optics upgrade | G81: =IF(F81-F81*15%=0,"",F81-F81*15%) | H81: =IFERROR(G81*$H$17,"") | I81: =IFERROR(ROUND(H81*$I$17,0),"") | J81: =IFERROR((I81-H81)/I81,"")
G82: =IF(F82-F82*15%=0,"",F82-F82*15%) | H82: =IFERROR(G82*$H$17,"") | I82: =IFERROR(ROUND(H82*$I$17,0),"") | J82: =IFERROR((I82-H82)/I82,"")
A83: MOD-SDR-ADC32B | B83: DiGiCo SD-Rack 32bit 8ch analogue mic & line input card | E83: =ROUND(F83/0.55,0) -> 1628 | F83: 895.5 | G83: =IF(F83-F83*15%=0,"",F83-F83*15%) -> 761.175 | H83: =IFERROR(G83*$H$17,"") -> 111892.72 | I83: =IFERROR(ROUND(H83*$I$17,0),"") -> 158888 | J83: =IFERROR((I83-H83)/I83,"") -> 0.29577611 | K83: here 15% but when it comes with Q338 set and X-SDRACK-O it comes with 20% disc.
B84: SD-Rack 32bit 8 x mic & line input card with remote gain control. XLR | G84: =IF(F84-F84*15%=0,"",F84-F84*15%) | H84: =IFERROR(G84*$H$17,"") | I84: =IFERROR(ROUND(H84*$I$17,0),"") | J84: =IFERROR((I84-H84)/I84,"")
G85: =IF(F85-F85*15%=0,"",F85-F85*15%) | H85: =IFERROR(G85*$H$17,"") | I85: =IFERROR(ROUND(H85*$I$17,0),"") | J85: =IFERROR((I85-H85)/I85,"")
A86: MOD-SDR-ADC | B86: DiGiCo SD-Rack 8ch analogue mic & line input card | E86: =ROUND(F86/0.55,0) -> 1186 | F86: 652.5 | G86: =IF(F86-F86*15%=0,"",F86-F86*15%) -> 554.625 | H86: =IFERROR(G86*$H$17,"") -> 81529.875 | I86: =IFERROR(ROUND(H86*$I$17,0),"") -> 115772 | J86: =IFERROR((I86-H86)/I86,"") -> 0.29577208
B87: SD-Rack 8 x mic & line input card with remote gain control. XLR | G87: =IF(F87-F87*15%=0,"",F87-F87*15%) | H87: =IFERROR(G87*$H$17,"") | I87: =IFERROR(ROUND(H87*$I$17,0),"") | J87: =IFERROR((I87-H87)/I87,"")
G88: =IF(F88-F88*15%=0,"",F88-F88*15%) | H88: =IFERROR(G88*$H$17,"") | I88: =IFERROR(ROUND(H88*$I$17,0),"") | J88: =IFERROR((I88-H88)/I88,"")
A89: MOD-SDR-DAC32B | B89: DiGiCo SD-Rack 32bit 8ch analogue line output card | E89: =ROUND(F89/0.55,0) -> 1105 | F89: 607.5 | G89: =IF(F89-F89*15%=0,"",F89-F89*15%) -> 516.375 | H89: =IFERROR(G89*$H$17,"") -> 75907.125 | I89: =IFERROR(ROUND(H89*$I$17,0),"") -> 107788 | J89: =IFERROR((I89-H89)/I89,"") -> 0.29577388 | K89: here 15% but when it comes with Q338 set and X-SDRACK-O it comes with 20% disc.
B90: SD-Rack 32bit 8 x line output card. XLR | G90: =IF(F90-F90*15%=0,"",F90-F90*15%) | H90: =IFERROR(G90*$H$17,"") | I90: =IFERROR(ROUND(H90*$I$17,0),"") | J90: =IFERROR((I90-H90)/I90,"")
G91: =IF(F91-F91*15%=0,"",F91-F91*15%) | H91: =IFERROR(G91*$H$17,"") | I91: =IFERROR(ROUND(H91*$I$17,0),"") | J91: =IFERROR((I91-H91)/I91,"")
A92: MOD-SDR-DAC | B92: DiGiCo SD-Rack 8ch analogue line output card | E92: =ROUND(F92/0.55,0) -> 747 | F92: 410.625 | G92: =IF(F92-F92*15%=0,"",F92-F92*15%) -> 349.03125 | H92: =IFERROR(G92*$H$17,"") -> 51307.594 | I92: =IFERROR(ROUND(H92*$I$17,0),"") -> 72857 | J92: =IFERROR((I92-H92)/I92,"") -> 0.29577674
B93: SD-Rack 8 x line output card. XLR | G93: =IF(F93-F93*15%=0,"",F93-F93*15%) | H93: =IFERROR(G93*$H$17,"") | I93: =IFERROR(ROUND(H93*$I$17,0),"") | J93: =IFERROR((I93-H93)/I93,"")
G94: =IF(F94-F94*15%=0,"",F94-F94*15%) | H94: =IFERROR(G94*$H$17,"") | I94: =IFERROR(ROUND(H94*$I$17,0),"") | J94: =IFERROR((I94-H94)/I94,"")
A95: MOD-SDR-AES-IO | B95: DiGiCo SD-Rack 8ch digital AES I/O card with XLR | E95: =ROUND(F95/0.55,0) -> 937 | F95: 515.25 | G95: =IF(F95-F95*15%=0,"",F95-F95*15%) -> 437.9625 | H95: =IFERROR(G95*$H$17,"") -> 64380.487 | I95: =IFERROR(ROUND(H95*$I$17,0),"") -> 91420 | J95: =IFERROR((I95-H95)/I95,"") -> 0.2957724
B96: SD-Rack 8 x digital mono AES IO card with sample rate conversion. XLR | G96: =IF(F96-F96*15%=0,"",F96-F96*15%) | H96: =IFERROR(G96*$H$17,"") | I96: =IFERROR(ROUND(H96*$I$17,0),"") | J96: =IFERROR((I96-H96)/I96,"")
G97: =IF(F97-F97*15%=0,"",F97-F97*15%) | H97: =IFERROR(G97*$H$17,"") | I97: =IFERROR(ROUND(H97*$I$17,0),"") | J97: =IFERROR((I97-H97)/I97,"")
A98: MOD-SDR-AES-B | B98: DiGiCo SD-Rack 8ch digital AES I/O card with BNC | E98: =ROUND(F98/0.55,0) -> 1309 | F98: 720 | G98: =IF(F98-F98*15%=0,"",F98-F98*15%) -> 612 | H98: =IFERROR(G98*$H$17,"") -> 89964 | I98: =IFERROR(ROUND(H98*$I$17,0),"") -> 127749 | J98: =IFERROR((I98-H98)/I98,"") -> 0.29577531
B99: SD-Rack 8 x digital mono AES IO card with sample rate conversion. BNC | G99: =IF(F99-F99*15%=0,"",F99-F99*15%) | H99: =IFERROR(G99*$H$17,"") | I99: =IFERROR(ROUND(H99*$I$17,0),"") | J99: =IFERROR((I99-H99)/I99,"")
G100: =IF(F100-F100*15%=0,"",F100-F100*15%) | H100: =IFERROR(G100*$H$17,"") | I100: =IFERROR(ROUND(H100*$I$17,0),"") | J100: =IFERROR((I100-H100)/I100,"")
A101: MOD-SDR-AES-I | B101: DiGiCo SD-Rack 8ch digital AES input card | E101: =ROUND(F101/0.55,0) -> 747 | F101: 410.625 | G101: =IF(F101-F101*15%=0,"",F101-F101*15%) -> 349.03125 | H101: =IFERROR(G101*$H$17,"") -> 51307.594 | I101: =IFERROR(ROUND(H101*$I$17,0),"") -> 72857 | J101: =IFERROR((I101-H101)/I101,"") -> 0.29577674
B102: SD-Rack 8 x digital mono AES input only card. XLR | G102: =IF(F102-F102*15%=0,"",F102-F102*15%) | H102: =IFERROR(G102*$H$17,"") | I102: =IFERROR(ROUND(H102*$I$17,0),"") | J102: =IFERROR((I102-H102)/I102,"")
G103: =IF(F103-F103*15%=0,"",F103-F103*15%) | H103: =IFERROR(G103*$H$17,"") | I103: =IFERROR(ROUND(H103*$I$17,0),"") | J103: =IFERROR((I103-H103)/I103,"")
A104: MOD-SDR-AES-O | B104: DiGiCo SD-Rack 8ch digital AES output card | E104: =ROUND(F104/0.55,0) -> 747 | F104: 410.625 | G104: =IF(F104-F104*15%=0,"",F104-F104*15%) -> 349.03125 | H104: =IFERROR(G104*$H$17,"") -> 51307.594 | I104: =IFERROR(ROUND(H104*$I$17,0),"") -> 72857 | J104: =IFERROR((I104-H104)/I104,"") -> 0.29577674
B105: SD-Rack 8 x digital mono AES output only card. XLR | G105: =IF(F105-F105*15%=0,"",F105-F105*15%) | H105: =IFERROR(G105*$H$17,"") | I105: =IFERROR(ROUND(H105*$I$17,0),"") | J105: =IFERROR((I105-H105)/I105,"")
G106: =IF(F106-F106*15%=0,"",F106-F106*15%) | H106: =IFERROR(G106*$H$17,"") | I106: =IFERROR(ROUND(H106*$I$17,0),"") | J106: =IFERROR((I106-H106)/I106,"")
...

Sheet Klang
B1: KLANG Distributor Price List
B3: Jan 2026
B5: Unit 10 Silverglade Business Park, Leatherhead Road
B6: Chessington, Surrey, KT9 2QL
B7: Tel; +44 1372 845600
B8: Fax; +44 1372 845656
B9: email; sales@digiconsoles.com
B10: web; www.digiconsoles.com
B12: FCA Glenrothes KY7 4PA. E&OE. Prices, Products and Specification are subject to change without notice.
B13: This price list supercedes all previous price lists
A15: Product Code | B15: Description | C15: Insert Picture | E15: Pro User (£) | F15: Distributor (£) | G15: Disc. (%) | H15: HT Buy (INR) | I15: Customer Price | J15: Hi-Tech
G16: 0.1 | H16: 147 | I16: 1.42 | J16: Margin
A17: Klang Konductor Packages
A19: X-KG-KOND-OP | B19: KLANG:konductor 128 input Optocore package (HMA) | E19: =ROUND(F19/0.54,0) -> 12358 | F19: 6673.5 | G19: =IF(F19-F19*$G$16=0,"",F19-F19*$G$16) -> 6006.15 | H19: =IFERROR(G19*$H$16,"") -> 882904.05 | I19: =IFERROR(ROUND(H19*$I$16,0),"") -> 1253724 | J19: =IFERROR((I19-H19)/I19,"") -> 0.29577479
B20: Includes 2 x MOD-DMI-OPTO Optocore DMI cards (HMA connectivity) | G20: =IF(F20-F20*$G$16=0,"",F20-F20*$G$16) | H20: =IFERROR(G20*$H$16,"") | I20: =IFERROR(ROUND(H20*$I$16,0),"") | J20: =IFERROR((I20-H20)/I20,"")
B21: 16 immersive in-ear mixes | G21: =IF(F21-F21*$G$16=0,"",F21-F21*$G$16) | H21: =IFERROR(G21*$H$16,"") | I21: =IFERROR(ROUND(H21*$I$16,0),"") | J21: =IFERROR((I21-H21)/I21,"")
B22: 128 inputs | G22: =IF(F22-F22*$G$16=0,"",F22-F22*$G$16) | H22: =IFERROR(G22*$H$16,"") | I22: =IFERROR(ROUND(H22*$I$16,0),"") | J22: =IFERROR((I22-H22)/I22,"")
B23: Parametric EQ for Inputs & Outputs. Channel tone filter | G23: =IF(F23-F23*$G$16=0,"",F23-F23*$G$16) | H23: =IFERROR(G23*$H$16,"") | I23: =IFERROR(ROUND(H23*$I$16,0),"") | J23: =IFERROR((I23-H23)/I23,"")
B24: Headphone amp with volume control | G24: =IF(F24-F24*$G$16=0,"",F24-F24*$G$16) | H24: =IFERROR(G24*$H$16,"") | I24: =IFERROR(ROUND(H24*$I$16,0),"") | J24: =IFERROR((I24-H24)/I24,"")
B25: 7" touch screen | G25: =IF(F25-F25*$G$16=0,"",F25-F25*$G$16) | H25: =IFERROR(G25*$H$16,"") | I25: =IFERROR(ROUND(H25*$I$16,0),"") | J25: =IFERROR((I25-H25)/I25,"")
B26: 96 kHz | 48 kHz, word clock I/O | G26: =IF(F26-F26*$G$16=0,"",F26-F26*$G$16) | H26: =IFERROR(G26*$H$16,"") | I26: =IFERROR(ROUND(H26*$I$16,0),"") | J26: =IFERROR((I26-H26)/I26,"")
B27: 3 etherCON, RJ45, 2 USB | G27: =IF(F27-F27*$G$16=0,"",F27-F27*$G$16) | H27: =IFERROR(G27*$H$16,"") | I27: =IFERROR(ROUND(H27*$I$16,0),"") | J27: =IFERROR((I27-H27)/I27,"")
B28: 2 PSU | G28: =IF(F28-F28*$G$16=0,"",F28-F28*$G$16) | H28: =IFERROR(G28*$H$16,"") | I28: =IFERROR(ROUND(H28*$I$16,0),"") | J28: =IFERROR((I28-H28)/I28,"")
E29: =ROUND(F29/0.54,0) -> 10006 | F29: 5403.375 | G29: =IF(F29-F29*$G$16=0,"",F29-F29*$G$16) -> 4863.0375 | H29: =IFERROR(G29*$H$16,"") -> 714866.51 | I29: =IFERROR(ROUND(H29*$I$16,0),"") -> 1015110 | J29: =IFERROR((I29-H29)/I29,"") -> 0.29577434
A30: X-KG-KOND-NC | B30: KLANG:konductor 128 input Optocore package (NC) | G30: =IF(F30-F30*$G$16=0,"",F30-F30*$G$16) | H30: =IFERROR(G30*$H$16,"") | I30: =IFERROR(ROUND(H30*$I$16,0),"") | J30: =IFERROR((I30-H30)/I30,"")
B31: Includes 2 x MOD-DMI-NC Optocore DMI cards (OpticalCON connectivity) | G31: =IF(F31-F31*$G$16=0,"",F31-F31*$G$16) | H31: =IFERROR(G31*$H$16,"") | I31: =IFERROR(ROUND(H31*$I$16,0),"") | J31: =IFERROR((I31-H31)/I31,"")
B32: 16 immersive in-ear mixes | G32: =IF(F32-F32*$G$16=0,"",F32-F32*$G$16) | H32: =IFERROR(G32*$H$16,"") | I32: =IFERROR(ROUND(H32*$I$16,0),"") | J32: =IFERROR((I32-H32)/I32,"")
B33: 128 inputs | G33: =IF(F33-F33*$G$16=0,"",F33-F33*$G$16) | H33: =IFERROR(G33*$H$16,"") | I33: =IFERROR(ROUND(H33*$I$16,0),"") | J33: =IFERROR((I33-H33)/I33,"")
B34: Parametric EQ for Inputs & Outputs. Channel tone filter | G34: =IF(F34-F34*$G$16=0,"",F34-F34*$G$16) | H34: =IFERROR(G34*$H$16,"") | I34: =IFERROR(ROUND(H34*$I$16,0),"") | J34: =IFERROR((I34-H34)/I34,"")
B35: Headphone amp with volume control | G35: =IF(F35-F35*$G$16=0,"",F35-F35*$G$16) | H35: =IFERROR(G35*$H$16,"") | I35: =IFERROR(ROUND(H35*$I$16,0),"") | J35: =IFERROR((I35-H35)/I35,"")
B36: 7" touch screen | G36: =IF(F36-F36*$G$16=0,"",F36-F36*$G$16) | H36: =IFERROR(G36*$H$16,"") | I36: =IFERROR(ROUND(H36*$I$16,0),"") | J36: =IFERROR((I36-H36)/I36,"")
B37: 96 kHz | 48 kHz, word clock I/O | G37: =IF(F37-F37*$G$16=0,"",F37-F37*$G$16) | H37: =IFERROR(G37*$H$16,"") | I37: =IFERROR(ROUND(H37*$I$16,0),"") | J37: =IFERROR((I37-H37)/I37,"")
B38: 3 etherCON, RJ45, 2 USB | G38: =IF(F38-F38*$G$16=0,"",F38-F38*$G$16) | H38: =IFERROR(G38*$H$16,"") | I38: =IFERROR(ROUND(H38*$I$16,0),"") | J38: =IFERROR((I38-H38)/I38,"")
B39: 2 PSU | G39: =IF(F39-F39*$G$16=0,"",F39-F39*$G$16) | H39: =IFERROR(G39*$H$16,"") | I39: =IFERROR(ROUND(H39*$I$16,0),"") | J39: =IFERROR((I39-H39)/I39,"")
G40: =IF(F40-F40*$G$16=0,"",F40-F40*$G$16) | H40: =IFERROR(G40*$H$16,"") | I40: =IFERROR(ROUND(H40*$I$16,0),"") | J40: =IFERROR((I40-H40)/I40,"")
A41: X-KG-KOND-ST | B41: KLANG:konductor 128 input Optocore package (ST) | E41: =ROUND(F41/0.54,0) -> 9556 | F41: 5160.375 | G41: =IF(F41-F41*$G$16=0,"",F41-F41*$G$16) -> 4644.3375 | H41: =IFERROR(G41*$H$16,"") -> 682717.61 | I41: =IFERROR(ROUND(H41*$I$16,0),"") -> 969459 | J41: =IFERROR((I41-H41)/I41,"") -> 0.29577464
B42: Includes 2 x MOD-DMI-OPTO Optocore DMI cards (ST connectivity) | G42: =IF(F42-F42*$G$16=0,"",F42-F42*$G$16) | H42: =IFERROR(G42*$H$16,"") | I42: =IFERROR(ROUND(H42*$I$16,0),"") | J42: =IFERROR((I42-H42)/I42,"")
B43: 16 immersive in-ear mixes | G43: =IF(F43-F43*$G$16=0,"",F43-F43*$G$16) | H43: =IFERROR(G43*$H$16,"") | I43: =IFERROR(ROUND(H43*$I$16,0),"") | J43: =IFERROR((I43-H43)/I43,"")
B44: 128 inputs | G44: =IF(F44-F44*$G$16=0,"",F44-F44*$G$16) | H44: =IFERROR(G44*$H$16,"") | I44: =IFERROR(ROUND(H44*$I$16,0),"") | J44: =IFERROR((I44-H44)/I44,"")
B45: Parametric EQ for Inputs & Outputs. Channel tone filter | G45: =IF(F45-F45*$G$16=0,"",F45-F45*$G$16) | H45: =IFERROR(G45*$H$16,"") | I45: =IFERROR(ROUND(H45*$I$16,0),"") | J45: =IFERROR((I45-H45)/I45,"")
B46: Headphone amp with volume control | G46: =IF(F46-F46*$G$16=0,"",F46-F46*$G$16) | H46: =IFERROR(G46*$H$16,"") | I46: =IFERROR(ROUND(H46*$I$16,0),"") | J46: =IFERROR((I46-H46)/I46,"")
B47: 7" touch screen | G47: =IF(F47-F47*$G$16=0,"",F47-F47*$G$16) | H47: =IFERROR(G47*$H$16,"") | I47: =IFERROR(ROUND(H47*$I$16,0),"") | J47: =IFERROR((I47-H47)/I47,"")
B48: 96 kHz | 48 kHz, word clock I/O | G48: =IF(F48-F48*$G$16=0,"",F48-F48*$G$16) | H48: =IFERROR(G48*$H$16,"") | I48: =IFERROR(ROUND(H48*$I$16,0),"") | J48: =IFERROR((I48-H48)/I48,"")
B49: 3 etherCON, RJ45, 2 USB | G49: =IF(F49-F49*$G$16=0,"",F49-F49*$G$16) | H49: =IFERROR(G49*$H$16,"") | I49: =IFERROR(ROUND(H49*$I$16,0),"") | J49: =IFERROR((I49-H49)/I49,"")
B50: 2 PSU | G50: =IF(F50-F50*$G$16=0,"",F50-F50*$G$16) | H50: =IFERROR(G50*$H$16,"") | I50: =IFERROR(ROUND(H50*$I$16,0),"") | J50: =IFERROR((I50-H50)/I50,"")
G51: =IF(F51-F51*$G$16=0,"",F51-F51*$G$16) | H51: =IFERROR(G51*$H$16,"") | I51: =IFERROR(ROUND(H51*$I$16,0),"") | J51: =IFERROR((I51-H51)/I51,"")
A52: X-KG-KOND-DAN2 | B52: KLANG:konductor 128 input Dante package | E52: =ROUND(F52/0.54,0) -> 8028 | F52: 4335 | G52: =IF(F52-F52*$G$16=0,"",F52-F52*$G$16) -> 3901.5 | H52: =IFERROR(G52*$H$16,"") -> 573520.5 | I52: =IFERROR(ROUND(H52*$I$16,0),"") -> 814399 | J52: =IFERROR((I52-H52)/I52,"") -> 0.29577455
B53: Includes 2 x MOD-DMI-DANTE2 Dante® 64@96 DMI cards | G53: =IF(F53-F53*$G$16=0,"",F53-F53*$G$16) | H53: =IFERROR(G53*$H$16,"") | I53: =IFERROR(ROUND(H53*$I$16,0),"") | J53: =IFERROR((I53-H53)/I53,"")
B54: 16 immersive in-ear mixes | G54: =IF(F54-F54*$G$16=0,"",F54-F54*$G$16) | H54: =IFERROR(G54*$H$16,"") | I54: =IFERROR(ROUND(H54*$I$16,0),"") | J54: =IFERROR((I54-H54)/I54,"")
B55: 128 inputs | G55: =IF(F55-F55*$G$16=0,"",F55-F55*$G$16) | H55: =IFERROR(G55*$H$16,"") | I55: =IFERROR(ROUND(H55*$I$16,0),"") | J55: =IFERROR((I55-H55)/I55,"")
B56: Parametric EQ for Inputs & Outputs. Channel tone filter | G56: =IF(F56-F56*$G$16=0,"",F56-F56*$G$16) | H56: =IFERROR(G56*$H$16,"") | I56: =IFERROR(ROUND(H56*$I$16,0),"") | J56: =IFERROR((I56-H56)/I56,"")
B57: Headphone amp with volume control | G57: =IF(F57-F57*$G$16=0,"",F57-F57*$G$16) | H57: =IFERROR(G57*$H$16,"") | I57: =IFERROR(ROUND(H57*$I$16,0),"") | J57: =IFERROR((I57-H57)/I57,"")
B58: 7" touch screen | G58: =IF(F58-F58*$G$16=0,"",F58-F58*$G$16) | H58: =IFERROR(G58*$H$16,"") | I58: =IFERROR(ROUND(H58*$I$16,0),"") | J58: =IFERROR((I58-H58)/I58,"")
B59: 96 kHz | 48 kHz, word clock I/O | G59: =IF(F59-F59*$G$16=0,"",F59-F59*$G$16) | H59: =IFERROR(G59*$H$16,"") | I59: =IFERROR(ROUND(H59*$I$16,0),"") | J59: =IFERROR((I59-H59)/I59,"")
B60: 3 etherCON, RJ45, 2 USB | G60: =IF(F60-F60*$G$16=0,"",F60-F60*$G$16) | H60: =IFERROR(G60*$H$16,"") | I60: =IFERROR(ROUND(H60*$I$16,0),"") | J60: =IFERROR((I60-H60)/I60,"")
B61: 2 PSU | G61: =IF(F61-F61*$G$16=0,"",F61-F61*$G$16) | H61: =IFERROR(G61*$H$16,"") | I61: =IFERROR(ROUND(H61*$I$16,0),"") | J61: =IFERROR((I61-H61)/I61,"")
G62: =IF(F62-F62*$G$16=0,"",F62-F62*$G$16) | H62: =IFERROR(G62*$H$16,"") | I62: =IFERROR(ROUND(H62*$I$16,0),"") | J62: =IFERROR((I62-H62)/I62,"")
A63: X-KG-KOND-MADI | B63: KLANG:konductor 128 input MADI package | E63: =ROUND(F63/0.54,0) -> 6854 | F63: 3701.25 | G63: =IF(F63-F63*$G$16=0,"",F63-F63*$G$16) -> 3331.125 | H63: =IFERROR(G63*$H$16,"") -> 489675.38 | I63: =IFERROR(ROUND(H63*$I$16,0),"") -> 695339 | J63: =IFERROR((I63-H63)/I63,"") -> 0.29577461
B64: Includes 2 x MOD-DMI-MADI-B MADI BNC DMI cards | G64: =IF(F64-F64*$G$16=0,"",F64-F64*$G$16) | H64: =IFERROR(G64*$H$16,"") | I64: =IFERROR(ROUND(H64*$I$16,0),"") | J64: =IFERROR((I64-H64)/I64,"")
B65: 16 immersive in-ear mixes | G65: =IF(F65-F65*$G$16=0,"",F65-F65*$G$16) | H65: =IFERROR(G65*$H$16,"") | I65: =IFERROR(ROUND(H65*$I$16,0),"") | J65: =IFERROR((I65-H65)/I65,"")
B66: 128 inputs | G66: =IF(F66-F66*$G$16=0,"",F66-F66*$G$16) | H66: =IFERROR(G66*$H$16,"") | I66: =IFERROR(ROUND(H66*$I$16,0),"") | J66: =IFERROR((I66-H66)/I66,"")
B67: Parametric EQ for Inputs & Outputs. Channel tone filter | G67: =IF(F67-F67*$G$16=0,"",F67-F67*$G$16) | H67: =IFERROR(G67*$H$16,"") | I67: =IFERROR(ROUND(H67*$I$16,0),"") | J67: =IFERROR((I67-H67)/I67,"")
B68: Headphone amp with volume control | G68: =IF(F68-F68*$G$16=0,"",F68-F68*$G$16) | H68: =IFERROR(G68*$H$16,"") | I68: =IFERROR(ROUND(H68*$I$16,0),"") | J68: =IFERROR((I68-H68)/I68,"")
B69: 7" touch screen | G69: =IF(F69-F69*$G$16=0,"",F69-F69*$G$16) | H69: =IFERROR(G69*$H$16,"") | I69: =IFERROR(ROUND(H69*$I$16,0),"") | J69: =IFERROR((I69-H69)/I69,"")
B70: 96 kHz | 48 kHz, word clock I/O | G70: =IF(F70-F70*$G$16=0,"",F70-F70*$G$16) | H70: =IFERROR(G70*$H$16,"") | I70: =IFERROR(ROUND(H70*$I$16,0),"") | J70: =IFERROR((I70-H70)/I70,"")
B71: 3 etherCON, RJ45, 2 USB | G71: =IF(F71-F71*$G$16=0,"",F71-F71*$G$16) | H71: =IFERROR(G71*$H$16,"") | I71: =IFERROR(ROUND(H71*$I$16,0),"") | J71: =IFERROR((I71-H71)/I71,"")
B72: 2 PSU | G72: =IF(F72-F72*$G$16=0,"",F72-F72*$G$16) | H72: =IFERROR(G72*$H$16,"") | I72: =IFERROR(ROUND(H72*$I$16,0),"") | J72: =IFERROR((I72-H72)/I72,"")
G73: =IF(F73-F73*$G$16=0,"",F73-F73*$G$16) | H73: =IFERROR(G73*$H$16,"") | I73: =IFERROR(ROUND(H73*$I$16,0),"") | J73: =IFERROR((I73-H73)/I73,"")
A74: Klang Immersive In-Ear Monitoring Processors | G74: =IF(F74-F74*$G$16=0,"",F74-F74*$G$16) | H74: =IFERROR(G74*$H$16,"") | I74: =IFERROR(ROUND(H74*$I$16,0),"") | J74: =IFERROR((I74-H74)/I74,"")
G75: =IF(F75-F75*$G$16=0,"",F75-F75*$G$16) | H75: =IFERROR(G75*$H$16,"") | I75: =IFERROR(ROUND(H75*$I$16,0),"") | J75: =IFERROR((I75-H75)/I75,"")
A76: X-KG-KOND | B76: KLANG:konductor | E76: =ROUND(F76/0.54,0) -> 5619 | F76: 3034.125 | G76: =IF(F76-F76*$G$16=0,"",F76-F76*$G$16) -> 2730.7125 | H76: =IFERROR(G76*$H$16,"") -> 401414.74 | I76: =IFERROR(ROUND(H76*$I$16,0),"") -> 570009 | J76: =IFERROR((I76-H76)/I76,"") -> 0.29577474
B77: 16 immersive in-ear mixes | G77: =IF(F77-F77*$G$16=0,"",F77-F77*$G$16) | H77: =IFERROR(G77*$H$16,"") | I77: =IFERROR(ROUND(H77*$I$16,0),"") | J77: =IFERROR((I77-H77)/I77,"")
B78: 128 inputs (DMI expansion cards required) | G78: =IF(F78-F78*$G$16=0,"",F78-F78*$G$16) | H78: =IFERROR(G78*$H$16,"") | I78: =IFERROR(ROUND(H78*$I$16,0),"") | J78: =IFERROR((I78-H78)/I78,"")
B79: 3 x 64ch DMI expansion slots | G79: =IF(F79-F79*$G$16=0,"",F79-F79*$G$16) | H79: =IFERROR(G79*$H$16,"") | I79: =IFERROR(ROUND(H79*$I$16,0),"") | J79: =IFERROR((I79-H79)/I79,"")
B80: Parametric EQ for Inputs & Outputs. Channel tone filter | G80: =IF(F80-F80*$G$16=0,"",F80-F80*$G$16) | H80: =IFERROR(G80*$H$16,"") | I80: =IFERROR(ROUND(H80*$I$16,0),"") | J80: =IFERROR((I80-H80)/I80,"")
B81: Headphone amp with volume control | G81: =IF(F81-F81*$G$16=0,"",F81-F81*$G$16) | H81: =IFERROR(G81*$H$16,"") | I81: =IFERROR(ROUND(H81*$I$16,0),"") | J81: =IFERROR((I81-H81)/I81,"")
B82: 7" touch screen | G82: =IF(F82-F82*$G$16=0,"",F82-F82*$G$16) | H82: =IFERROR(G82*$H$16,"") | I82: =IFERROR(ROUND(H82*$I$16,0),"") | J82: =IFERROR((I82-H82)/I82,"")
B83: 96 kHz | 48 kHz, word clock I/O | G83: =IF(F83-F83*$G$16=0,"",F83-F83*$G$16) | H83: =IFERROR(G83*$H$16,"") | I83: =IFERROR(ROUND(H83*$I$16,0),"") | J83: =IFERROR((I83-H83)/I83,"")
B84: 3 etherCON, RJ45, 2 USB | G84: =IF(F84-F84*$G$16=0,"",F84-F84*$G$16) | H84: =IFERROR(G84*$H$16,"") | I84: =IFERROR(ROUND(H84*$I$16,0),"") | J84: =IFERROR((I84-H84)/I84,"")
B85: 2 PSU | G85: =IF(F85-F85*$G$16=0,"",F85-F85*$G$16) | H85: =IFERROR(G85*$H$16,"") | I85: =IFERROR(ROUND(H85*$I$16,0),"") | J85: =IFERROR((I85-H85)/I85,"")
B86: Dimensions: 3U. 435(w) x 135(h) x 268(d) mm, Front panel (width): 485 mm, Weight: 6.3 kg | G86: =IF(F86-F86*$G$16=0,"",F86-F86*$G$16) | H86: =IFERROR(G86*$H$16,"") | I86: =IFERROR(ROUND(H86*$I$16,0),"") | J86: =IFERROR((I86-H86)/I86,"")
G87: =IF(F87-F87*$G$16=0,"",F87-F87*$G$16) | H87: =IFERROR(G87*$H$16,"") | I87: =IFERROR(ROUND(H87*$I$16,0),"") | J87: =IFERROR((I87-H87)/I87,"")
A88: X-KG-VOKAL | B88: KLANG:vokal | E88: =ROUND(F88/0.55,0) -> 2725 | F88: 1499 | G88: =IF(F88-F88*$G$16=0,"",F88-F88*$G$16) -> 1349.1 | H88: =IFERROR(G88*$H$16,"") -> 198317.7 | I88: =IFERROR(ROUND(H88*$I$16,0),"") -> 281611 | J88: =IFERROR((I88-H88)/I88,"") -> 0.29577431
B89: 12 immersive in-ear mixes | G89: =IF(F89-F89*$G$16=0,"",F89-F89*$G$16) | H89: =IFERROR(G89*$H$16,"") | I89: =IFERROR(ROUND(H89*$I$16,0),"") | J89: =IFERROR((I89-H89)/I89,"")
B90: 24 Mono or Stereo Inputs per mix | G90: =IF(F90-F90*$G$16=0,"",F90-F90*$G$16) | H90: =IFERROR(G90*$H$16,"") | I90: =IFERROR(ROUND(H90*$I$16,0),"") | J90: =IFERROR((I90-H90)/I90,"")
B91: Parametric EQ for Inputs & Outputs. Channel tone filter | G91: =IF(F91-F91*$G$16=0,"",F91-F91*$G$16) | H91: =IFERROR(G91*$H$16,"") | I91: =IFERROR(ROUND(H91*$I$16,0),"") | J91: =IFERROR((I91-H91)/I91,"")
B92: Dante® etherCON I/O. 64ch @ 48kHz/ 96kHz | G92: =IF(F92-F92*$G$16=0,"",F92-F92*$G$16) | H92: =IFERROR(G92*$H$16,"") | I92: =IFERROR(ROUND(H92*$I$16,0),"") | J92: =IFERROR((I92-H92)/I92,"")
B93: MADI BNC I/O. 64ch @48kHz or 32ch @ 96kHz | G93: =IF(F93-F93*$G$16=0,"",F93-F93*$G$16) | H93: =IFERROR(G93*$H$16,"") | I93: =IFERROR(ROUND(H93*$I$16,0),"") | J93: =IFERROR((I93-H93)/I93,"")
B94: 96 kHz | 48 kHz, word clock I/O | G94: =IF(F94-F94*$G$16=0,"",F94-F94*$G$16) | H94: =IFERROR(G94*$H$16,"") | I94: =IFERROR(ROUND(H94*$I$16,0),"") | J94: =IFERROR((I94-H94)/I94,"")
B95: 1 PSU | G95: =IF(F95-F95*$G$16=0,"",F95-F95*$G$16) | H95: =IFERROR(G95*$H$16,"") | I95: =IFERROR(ROUND(H95*$I$16,0),"") | J95: =IFERROR((I95-H95)/I95,"")
B96: Dimensions: 1U. 445(w) / 45(h) x 275(d) mm, Front panel (width): 485mm, Weight: 3.6kg | G96: =IF(F96-F96*$G$16=0,"",F96-F96*$G$16) | H96: =IFERROR(G96*$H$16,"") | I96: =IFERROR(ROUND(H96*$I$16,0),"") | J96: =IFERROR((I96-H96)/I96,"")
G97: =IF(F97-F97*$G$16=0,"",F97-F97*$G$16) | H97: =IFERROR(G97*$H$16,"") | I97: =IFERROR(ROUND(H97*$I$16,0),"") | J97: =IFERROR((I97-H97)/I97,"")
A98: MOD-DMI-KLANG | B98: KLANG:dmi | E98: =ROUND(F98/0.55,0) -> 3989 | F98: 2193.75 | G98: =IF(F98-F98*$G$16=0,"",F98-F98*$G$16) -> 1974.375 | H98: =IFERROR(G98*$H$16,"") -> 290233.12 | I98: =IFERROR(ROUND(H98*$I$16,0),"") -> 412131 | J98: =IFERROR((I98-H98)/I98,"") -> 0.29577458
B99: 16 immersive in-ear mixes | G99: =IF(F99-F99*$G$16=0,"",F99-F99*$G$16) | H99: =IFERROR(G99*$H$16,"") | I99: =IFERROR(ROUND(H99*$I$16,0),"") | J99: =IFERROR((I99-H99)/I99,"")
B100: 64 Inputs | G100: =IF(F100-F100*$G$16=0,"",F100-F100*$G$16) | H100: =IFERROR(G100*$H$16,"") | I100: =IFERROR(ROUND(H100*$I$16,0),"") | J100: =IFERROR((I100-H100)/I100,"")
B101: 96 kHz | 48 kHz | G101: =IF(F101-F101*$G$16=0,"",F101-F101*$G$16) | H101: =IFERROR(G101*$H$16,"") | I101: =IFERROR(ROUND(H101*$I$16,0),"") | J101: =IFERROR((I101-H101)/I101,"")
B102: 2 etherCON, RJ45, USB | G102: =IF(F102-F102*$G$16=0,"",F102-F102*$G$16) | H102: =IFERROR(G102*$H$16,"") | I102: =IFERROR(ROUND(H102*$I$16,0),"") | J102: =IFERROR((I102-H102)/I102,"")
B103: Only suitable for DiGiCo Consoles with DMI expansion slots and the Orange Box. | G103: =IF(F103-F103*$G$16=0,"",F103-F103*$G$16) | H103: =IFERROR(G103*$H$16,"") | I103: =IFERROR(ROUND(H103*$I$16,0),"") | J103: =IFERROR((I103-H103)/I103,"")
G104: =IF(F104-F104*$G$16=0,"",F104-F104*$G$16) | H104: =IFERROR(G104*$H$16,"") | I104: =IFERROR(ROUND(H104*$I$16,0),"") | J104: =IFERROR((I104-H104)/I104,"")
A105: X-KG-ONE-PRO | B105: KLANG:one Pro * | E105: =ROUND(F105/0.55,0) -> 1095 | F105: 602.25 | G105: =IF(F105-F105*$G$16=0,"",F105-F105*$G$16) -> 542.025 | H105: =IFERROR(G105*$H$16,"") -> 79677.675 | I105: =IFERROR(ROUND(H105*$I$16,0),"") -> 113142 | J105: =IFERROR((I105-H105)/I105,"") -> 0.29577279
...

Sheet Fourier
B1: Fourier Audio Distributor Price List
B3: Jan 2026
B5: Unit 10 Silverglade Business Park, Leatherhead Road
B6: Chessington, Surrey, KT9 2QL
B7: Tel; +44 1372 845600
B8: Fax; +44 1372 845656
B9: email; sales@digiconsoles.com
B10: web; www.digiconsoles.com
B12: FCA Glenrothes KY7 4PA. E&OE. Prices, Products and Specification are subject to change without notice.
B13: This price list supercedes all previous price lists
A15: Product Code | B15: Description | E15: List Price (£) | F15: Distributor (£) | G15: Disc. (%) | H15: HT Buy (INR) | I15: Customer Price | J15: Hi-Tech
G16: 0.1 | H16: 147 | I16: 1.42 | J16: Margin
A17: Fourier Engine
A19: X-FA-TE | B19: Fourier Audio transform.engine | E19: 7273 | F19: 4000 | G19: =IF(F19-F19*$G$16=0,"",F19-F19*$G$16) -> 3600 | H19: =IFERROR(G19*$H$16,"") -> 529200 | I19: =IFERROR(ROUND(H19*$I$16,0),"") -> 751464 | J19: =IFERROR((I19-H19)/I19,"") -> 0.29577465
B20: VST3 plugin host server. | G20: =IF(F20-F20*$G$16=0,"",F20-F20*$G$16) | H20: =IFERROR(G20*$H$16,"") | I20: =IFERROR(ROUND(H20*$I$16,0),"") | J20: =IFERROR((I20-H20)/I20,"")
B21: 2 Dante/ HYPERPORT/ gigaACE/ DX etherCON (primary / secondary). 64ch I/O @ 44.1kHz/48kHz/96kHz. | G21: =IF(F21-F21*$G$16=0,"",F21-F21*$G$16) | H21: =IFERROR(G21*$H$16,"") | I21: =IFERROR(ROUND(H21*$I$16,0),"") | J21: =IFERROR((I21-H21)/I21,"")
B22: 1 etherCON control port. 2 USB (front panel), 4 USB (rear secure bay). 2 PSU. 5 pin din + TCP/IP MIDI. | G22: =IF(F22-F22*$G$16=0,"",F22-F22*$G$16) | H22: =IFERROR(G22*$H$16,"") | I22: =IFERROR(ROUND(H22*$I$16,0),"") | J22: =IFERROR((I22-H22)/I22,"")
B23: Dimensions: 2U. 433(w) x 89(h) x 385(d) mm, Weight: 5.5 kg | G23: =IF(F23-F23*$G$16=0,"",F23-F23*$G$16) | H23: =IFERROR(G23*$H$16,"") | I23: =IFERROR(ROUND(H23*$I$16,0),"") | J23: =IFERROR((I23-H23)/I23,"")
G24: =IF(F24-F24*$G$16=0,"",F24-F24*$G$16) | H24: =IFERROR(G24*$H$16,"") | I24: =IFERROR(ROUND(H24*$I$16,0),"") | J24: =IFERROR((I24-H24)/I24,"")
A25: X-FA-TG | B25: Fourier Audio transform.go | E25: 2800 | F25: 1540 | G25: =IF(F25-F25*$G$16=0,"",F25-F25*$G$16) -> 1386 | H25: =IFERROR(G25*$H$16,"") -> 203742 | I25: =IFERROR(ROUND(H25*$I$16,0),"") -> 289314 | J25: =IFERROR((I25-H25)/I25,"") -> 0.29577552
B26: VST3 plugin host server.
B27: 2 Dante/ HYPERPORT/ gigaACE/ DX etherCON (primary / secondary). 16ch I/O @ 44.1kHz/48kHz/96kHz.
B28: 1 etherCON control port. 1 USB (front panel), 2 USB (rear secure bay). 1 PSU. TCP/IP MIDI.
B29: Dimensions: 2U. 217(w) x 85(h) x 283(d) mm, Weight: 3.7 kg

Sheet Q1
B1: DiGiCo Quantum 112 Distributor Price List
B3: Apr 2026
B5: Unit 10 Silverglade Business Park, Leatherhead Road
B6: Chessington, Surrey, KT9 2QL
B7: Tel; +44 1372 845600
B8: Fax; +44 1372 845656
B9: email; sales@digiconsoles.com
B10: web; www.digiconsoles.com
B12: FCA Glenrothes KY7 4NX. E&OE. Prices, Products and Specification are subject to change without notice.
B13: This price list supercedes all previous price lists.
A15: Product Code | B15: Description | E15: List (£) | F15: Distributor (£) | G15: Disc. (%) | H15: HT Buy (INR) | I15: Customer Price | J15: Hi-Tech
G16: 0 | H16: 147 | I16: 1.42 | J16: Margin
A17: DiGiCo Quantum 225 Systems
A19: X-Q112-MQ | B19: DiGiCo Quantum 112 system - MADI | E19: =ROUND(F19/0.55,0) -> 24545 | F19: 13500 | G19: =IF(F19-F19*$G$16=0,"",F19-F19*$G$16) -> 13500 | H19: =IFERROR(G19*$H$16,"") -> 1984500 | I19: =IFERROR(ROUND(H19*$I$16,0),"") -> 2817990 | J19: =IFERROR((I19-H19)/I19,"") -> 0.29577465
B20: 1 x Quantum 112 surface - 12 faders, 2 DMI slots, Dante 64ch I/O, USB Audio 32ch I/O, 4 BNC MADI | G20: =IF(F20-F20*$G$16=0,"",F20-F20*$G$16) | H20: =IFERROR(G20*$H$16,"") | I20: =IFERROR(ROUND(H20*$I$16,0),"") | J20: =IFERROR((I20-H20)/I20,"")
B21: 80 mono input channels, 24 mono output busses, | G21: =IF(F21-F21*$G$16=0,"",F21-F21*$G$16) | H21: =IFERROR(G21*$H$16,"") | I21: =IFERROR(ROUND(H21*$I$16,0),"") | J21: =IFERROR((I21-H21)/I21,"")
B22: 2 mono or stereo solo busses. LR or LCR master buss | G22: =IF(F22-F22*$G$16=0,"",F22-F22*$G$16) | H22: =IFERROR(G22*$H$16,"") | I22: =IFERROR(ROUND(H22*$I$16,0),"") | J22: =IFERROR((I22-H22)/I22,"")
B23: 12 x 8 matrix, 12 CG/VCA, 8 FX, 12 x 32 band graphic eq’s | G23: =IF(F23-F23*$G$16=0,"",F23-F23*$G$16) | H23: =IFERROR(G23*$H$16,"") | I23: =IFERROR(ROUND(H23*$I$16,0),"") | J23: =IFERROR((I23-H23)/I23,"")
B24: 24 Nodal Processors, 20 Mustard Processors, 6 Spice FX | G24: =IF(F24-F24*$G$16=0,"",F24-F24*$G$16) | H24: =IFERROR(G24*$H$16,"") | I24: =IFERROR(ROUND(H24*$I$16,0),"") | J24: =IFERROR((I24-H24)/I24,"")
B25: Local I/O 16 x Mic/Line inputs, 8 x Line outputs, AES I/O, 2 PSU, 2 GPIO, dust cover, carton | G25: =IF(F25-F25*$G$16=0,"",F25-F25*$G$16) | H25: =IFERROR(G25*$H$16,"") | I25: =IFERROR(ROUND(H25*$I$16,0),"") | J25: =IFERROR((I25-H25)/I25,"")
B26: 1 x Quantum MADI Rack, 2 BNC MADI, dual PSU - 48 mic/line in / up to 24 line out / up to 8 AES output (mono), carton | G26: =IF(F26-F26*$G$16=0,"",F26-F26*$G$16) | H26: =IFERROR(G26*$H$16,"") | I26: =IFERROR(ROUND(H26*$I$16,0),"") | J26: =IFERROR((I26-H26)/I26,"")
B27: 2 x 100m BNC Cables | G27: =IF(F27-F27*$G$16=0,"",F27-F27*$G$16) | H27: =IFERROR(G27*$H$16,"") | I27: =IFERROR(ROUND(H27*$I$16,0),"") | J27: =IFERROR((I27-H27)/I27,"")
G28: =IF(F28-F28*$G$16=0,"",F28-F28*$G$16) | H28: =IFERROR(G28*$H$16,"") | I28: =IFERROR(ROUND(H28*$I$16,0),"") | J28: =IFERROR((I28-H28)/I28,"")
A29: X-Q112-DQ | B29: DiGiCo Quantum 112 system - DANTE | E29: =ROUND(F29/0.55,0) -> 25091 | F29: 13800 | G29: =IF(F29-F29*$G$16=0,"",F29-F29*$G$16) -> 13800 | H29: =IFERROR(G29*$H$16,"") -> 2028600 | I29: =IFERROR(ROUND(H29*$I$16,0),"") -> 2880612 | J29: =IFERROR((I29-H29)/I29,"") -> 0.29577465
B30: 1 x Quantum 112 surface - 12 faders, 2 DMI slots, Dante 64ch I/O, USB Audio 32ch I/O, 4 BNC MADI | G30: =IF(F30-F30*$G$16=0,"",F30-F30*$G$16) | H30: =IFERROR(G30*$H$16,"") | I30: =IFERROR(ROUND(H30*$I$16,0),"") | J30: =IFERROR((I30-H30)/I30,"")
B31: 80 mono input channels, 24 mono output busses, | G31: =IF(F31-F31*$G$16=0,"",F31-F31*$G$16) | H31: =IFERROR(G31*$H$16,"") | I31: =IFERROR(ROUND(H31*$I$16,0),"") | J31: =IFERROR((I31-H31)/I31,"")
B32: 2 mono or stereo solo busses. LR or LCR master buss | G32: =IF(F32-F32*$G$16=0,"",F32-F32*$G$16) | H32: =IFERROR(G32*$H$16,"") | I32: =IFERROR(ROUND(H32*$I$16,0),"") | J32: =IFERROR((I32-H32)/I32,"")
B33: 12 x 8 matrix, 12 CG/VCA, 8 FX, 12 x 32 band graphic eq’s | G33: =IF(F33-F33*$G$16=0,"",F33-F33*$G$16) | H33: =IFERROR(G33*$H$16,"") | I33: =IFERROR(ROUND(H33*$I$16,0),"") | J33: =IFERROR((I33-H33)/I33,"")
B34: 24 Nodal Processors, 20 Mustard Processors, 6 Spice FX | G34: =IF(F34-F34*$G$16=0,"",F34-F34*$G$16) | H34: =IFERROR(G34*$H$16,"") | I34: =IFERROR(ROUND(H34*$I$16,0),"") | J34: =IFERROR((I34-H34)/I34,"")
B35: Local I/O 16 x Mic/Line inputs, 8 x Line outputs, AES I/O, 2 PSU, 2 GPIO, dust cover, carton | G35: =IF(F35-F35*$G$16=0,"",F35-F35*$G$16) | H35: =IFERROR(G35*$H$16,"") | I35: =IFERROR(ROUND(H35*$I$16,0),"") | J35: =IFERROR((I35-H35)/I35,"")
B36: 1 x Quantum Dante Rack, 2 etherCON, dual PSU - 48 mic/line in / up to 24 line out / up to 8 AES output (mono), carton | G36: =IF(F36-F36*$G$16=0,"",F36-F36*$G$16) | H36: =IFERROR(G36*$H$16,"") | I36: =IFERROR(ROUND(H36*$I$16,0),"") | J36: =IFERROR((I36-H36)/I36,"")
B37: 1 x 75m CAT6 Cable | G37: =IF(F37-F37*$G$16=0,"",F37-F37*$G$16) | H37: =IFERROR(G37*$H$16,"") | I37: =IFERROR(ROUND(H37*$I$16,0),"") | J37: =IFERROR((I37-H37)/I37,"")
G38: =IF(F38-F38*$G$16=0,"",F38-F38*$G$16) | H38: =IFERROR(G38*$H$16,"") | I38: =IFERROR(ROUND(H38*$I$16,0),"") | J38: =IFERROR((I38-H38)/I38,"")
A39: DiGiCo Quantum 225 Surface | G39: =IF(F39-F39*$G$16=0,"",F39-F39*$G$16) | H39: =IFERROR(G39*$H$16,"") | I39: =IFERROR(ROUND(H39*$I$16,0),"") | J39: =IFERROR((I39-H39)/I39,"")
G40: =IF(F40-F40*$G$16=0,"",F40-F40*$G$16) | H40: =IFERROR(G40*$H$16,"") | I40: =IFERROR(ROUND(H40*$I$16,0),"") | J40: =IFERROR((I40-H40)/I40,"")
A41: X-Q112-WS | B41: DiGiCo Quantum 112 surface | E41: =ROUND(F41/0.55,0) -> 17455 | F41: 9600 | G41: =IF(F41-F41*$G$16=0,"",F41-F41*$G$16) -> 9600 | H41: =IFERROR(G41*$H$16,"") -> 1411200 | I41: =IFERROR(ROUND(H41*$I$16,0),"") -> 2003904 | J41: =IFERROR((I41-H41)/I41,"") -> 0.29577465
B42: Quantum 112 surface - 12 faders, 2 DMI slots, Dante 64ch I/O, USB Audio 32ch I/O, 4 BNC MADI | G42: =IF(F42-F42*$G$16=0,"",F42-F42*$G$16) | H42: =IFERROR(G42*$H$16,"") | I42: =IFERROR(ROUND(H42*$I$16,0),"") | J42: =IFERROR((I42-H42)/I42,"")
B43: 80 mono input channels, 24 mono output busses, | G43: =IF(F43-F43*$G$16=0,"",F43-F43*$G$16) | H43: =IFERROR(G43*$H$16,"") | I43: =IFERROR(ROUND(H43*$I$16,0),"") | J43: =IFERROR((I43-H43)/I43,"")
B44: 2 mono or stereo solo busses. LR or LCR master buss | G44: =IF(F44-F44*$G$16=0,"",F44-F44*$G$16) | H44: =IFERROR(G44*$H$16,"") | I44: =IFERROR(ROUND(H44*$I$16,0),"") | J44: =IFERROR((I44-H44)/I44,"")
B45: 12 x 8 matrix, 12 CG/VCA, 8 FX, 12 x 32 band graphic eq’s | G45: =IF(F45-F45*$G$16=0,"",F45-F45*$G$16) | H45: =IFERROR(G45*$H$16,"") | I45: =IFERROR(ROUND(H45*$I$16,0),"") | J45: =IFERROR((I45-H45)/I45,"")
B46: 24 Nodal Processors, 20 Mustard Processors, 6 Spice FX | G46: =IF(F46-F46*$G$16=0,"",F46-F46*$G$16) | H46: =IFERROR(G46*$H$16,"") | I46: =IFERROR(ROUND(H46*$I$16,0),"") | J46: =IFERROR((I46-H46)/I46,"")
B47: Local I/O 16 x Mic/Line inputs, 8 x Line outputs, AES I/O, 2 PSU, 2 GPIO, dust cover, carton | G47: =IF(F47-F47*$G$16=0,"",F47-F47*$G$16) | H47: =IFERROR(G47*$H$16,"") | I47: =IFERROR(ROUND(H47*$I$16,0),"") | J47: =IFERROR((I47-H47)/I47,"")
B48: Dimensions; 440(w) x 575(d) x 325(h) mm Weight; 14.35kg | G48: =IF(F48-F48*$G$16=0,"",F48-F48*$G$16) | H48: =IFERROR(G48*$H$16,"") | I48: =IFERROR(ROUND(H48*$I$16,0),"") | J48: =IFERROR((I48-H48)/I48,"")
G49: =IF(F49-F49*$G$16=0,"",F49-F49*$G$16) | H49: =IFERROR(G49*$H$16,"") | I49: =IFERROR(ROUND(H49*$I$16,0),"") | J49: =IFERROR((I49-H49)/I49,"")
A50: DiGiCo Quantum 225 Surface Options | G50: =IF(F50-F50*$G$16=0,"",F50-F50*$G$16) | H50: =IFERROR(G50*$H$16,"") | I50: =IFERROR(ROUND(H50*$I$16,0),"") | J50: =IFERROR((I50-H50)/I50,"")
G51: =IF(F51-F51*$G$16=0,"",F51-F51*$G$16) | H51: =IFERROR(G51*$H$16,"") | I51: =IFERROR(ROUND(H51*$I$16,0),"") | J51: =IFERROR((I51-H51)/I51,"")
A52: MOD-Q1-OP-HMA | B52: DiGiCo Quantum 112 Optocore interface (HMA) | E52: =ROUND(F52/0.55,0) -> 7364 | F52: 4050 | G52: =IF(F52-F52*$G$16=0,"",F52-F52*$G$16) -> 4050 | H52: =IFERROR(G52*$H$16,"") -> 595350 | I52: =IFERROR(ROUND(H52*$I$16,0),"") -> 845397 | J52: =IFERROR((I52-H52)/I52,"") -> 0.29577465
B53: Factory fitted HMA expanded beam optics upgrade for surface | G53: =IF(F53-F53*$G$16=0,"",F53-F53*$G$16) | H53: =IFERROR(G53*$H$16,"") | I53: =IFERROR(ROUND(H53*$I$16,0),"") | J53: =IFERROR((I53-H53)/I53,"")
G54: =IF(F54-F54*$G$16=0,"",F54-F54*$G$16) | H54: =IFERROR(G54*$H$16,"") | I54: =IFERROR(ROUND(H54*$I$16,0),"") | J54: =IFERROR((I54-H54)/I54,"")
A55: MOD-Q1-OP-NC | B55: DiGiCo Quantum 112 Optocore interface (NC) | E55: =ROUND(F55/0.55,0) -> 6251 | F55: 3438 | G55: =IF(F55-F55*$G$16=0,"",F55-F55*$G$16) -> 3438 | H55: =IFERROR(G55*$H$16,"") -> 505386 | I55: =IFERROR(ROUND(H55*$I$16,0),"") -> 717648 | J55: =IFERROR((I55-H55)/I55,"") -> 0.29577453
B56: Factory fitted NC optics upgrade for surface | G56: =IF(F56-F56*$G$16=0,"",F56-F56*$G$16) | H56: =IFERROR(G56*$H$16,"") | I56: =IFERROR(ROUND(H56*$I$16,0),"") | J56: =IFERROR((I56-H56)/I56,"")
G57: =IF(F57-F57*$G$16=0,"",F57-F57*$G$16) | H57: =IFERROR(G57*$H$16,"") | I57: =IFERROR(ROUND(H57*$I$16,0),"") | J57: =IFERROR((I57-H57)/I57,"")
A58: MOD-Q1-OP-ST | B58: DiGiCo Quantum 112 Optocore intercace (ST) | E58: =ROUND(F58/0.55,0) -> 6038 | F58: 3321 | G58: =IF(F58-F58*$G$16=0,"",F58-F58*$G$16) -> 3321 | H58: =IFERROR(G58*$H$16,"") -> 488187 | I58: =IFERROR(ROUND(H58*$I$16,0),"") -> 693226 | J58: =IFERROR((I58-H58)/I58,"") -> 0.29577512
B59: Factory fitted ST optics upgrade for surface | G59: =IF(F59-F59*$G$16=0,"",F59-F59*$G$16) | H59: =IFERROR(G59*$H$16,"") | I59: =IFERROR(ROUND(H59*$I$16,0),"") | J59: =IFERROR((I59-H59)/I59,"")
G60: =IF(F60-F60*$G$16=0,"",F60-F60*$G$16) | H60: =IFERROR(G60*$H$16,"") | I60: =IFERROR(ROUND(H60*$I$16,0),"") | J60: =IFERROR((I60-H60)/I60,"")
A61: FC-Q112 | B61: DiGiCo Quantum 112 3-piece surface touring flight case | E61: =ROUND(F61/0.55,0) -> 1591 | F61: 875 | G61: =IF(F61-F61*$G$16=0,"",F61-F61*$G$16) -> 875 | H61: =IFERROR(G61*$H$16,"") -> 128625 | I61: =IFERROR(ROUND(H61*$I$16,0),"") -> 182648 | J61: =IFERROR((I61-H61)/I61,"") -> 0.29577658
B62: Dimensions; 546(w) x 488(d) x 914(h) mm Weight; 41.60Kg | G62: =IF(F62-F62*$G$16=0,"",F62-F62*$G$16) | H62: =IFERROR(G62*$H$16,"") | I62: =IFERROR(ROUND(H62*$I$16,0),"") | J62: =IFERROR((I62-H62)/I62,"")
G63: =IF(F63-F63*$G$16=0,"",F63-F63*$G$16) | H63: =IFERROR(G63*$H$16,"") | I63: =IFERROR(ROUND(H63*$I$16,0),"") | J63: =IFERROR((I63-H63)/I63,"")
A64: FC-Q112-PELI | B64: DiGiCo Quantum 112 custom Peli Air 1637 Case | E64: =ROUND(F64/0.55,0) -> 1113 | F64: 612 | G64: =IF(F64-F64*$G$16=0,"",F64-F64*$G$16) -> 612 | H64: =IFERROR(G64*$H$16,"") -> 89964 | I64: =IFERROR(ROUND(H64*$I$16,0),"") -> 127749 | J64: =IFERROR((I64-H64)/I64,"") -> 0.29577531
B65: Dimensions; 525(w) x 378(d) x 525(h) mm Weight; 7.80Kg
B67: Please refer to the 'Racks, Cables and Options' and 'DiGiCo Solutions' Price Lists for additional options.
B68: All optics are Multimode as standard. Please call for prices on Singlemode.

Sheet Q 3
B1: DiGiCo Quantum 3 Distributor Price List
B3: Sept 2024
B5: Unit 10 Silverglade Business Park, Leatherhead Road | F5: Pound considered @ INR 127.5
B6: Chessington, Surrey, KT9 2QL
B7: Tel; +44 1372 845600
B8: Fax; +44 1372 845656 | F8: Freight @ 2.5%
B9: email; sales@digiconsoles.com | F9: Custom @ 8.5%
B10: web; www.digiconsoles.com | F10: Clearance @ 1%
B12: FCA Glenrothes KY7 4NX. E&OE. Prices, Products and Specification are subject to change without notice.
B13: This price list supercedes all previous price lists
A15: Product Code | B15: Description | E15: List (£) | F15: Distributor (£) | G15: Disc. (20%) | H15: HT Buy (INR) | I15: Customer Price | J15: Hi-Tech
G16: 0.2 | H16: 147 | I16: 1.42 | J16: Margin
A17: DiGiCo Quantum 338 32bit System
B19: DiGiCo Quantum 338 system | E19: =ROUND(F19/0.55,0) -> 97867 | F19: 53826.75 | G19: =IF(F19-F19*$G$16=0,"",F19-F19*$G$16) -> 43061.4 | H19: =IFERROR(G19*$H$16,"") -> 6330025.8 | I19: =IFERROR(ROUND(H19*$I$16,0),"") -> 8988637 | J19: =IFERROR((I19-H19)/I19,"") -> 0.29577468
B20: 1 x Quantum 338 surface - 36+2 faders, HMA optics, 2 DMI slots, USB Audio I/O, 6 BNC MADI, 2 PSU, 16 GPIO | G20: =IF(F20-F20*$G$16=0,"",F20-F20*$G$16) | H20: =IFERROR(G20*$H$16,"") | I20: =IFERROR(ROUND(H20*$I$16,0),"") | J20: =IFERROR((I20-H20)/I20,"")
B21: 128 mono input channels, 64 mono output busses, | G21: =IF(F21-F21*$G$16=0,"",F21-F21*$G$16) | H21: =IFERROR(G21*$H$16,"") | I21: =IFERROR(ROUND(H21*$I$16,0),"") | J21: =IFERROR((I21-H21)/I21,"")
B22: 2 mono or stereo solo busses. LR or LCR master buss | G22: =IF(F22-F22*$G$16=0,"",F22-F22*$G$16) | H22: =IFERROR(G22*$H$16,"") | I22: =IFERROR(ROUND(H22*$I$16,0),"") | J22: =IFERROR((I22-H22)/I22,"")
B23: 24 x 24 matrix, 24 CG/VCA, 24 FX, 24 x 32 band graphic eq’s, | G23: =IF(F23-F23*$G$16=0,"",F23-F23*$G$16) | H23: =IFERROR(G23*$H$16,"") | I23: =IFERROR(ROUND(H23*$I$16,0),"") | J23: =IFERROR((I23-H23)/I23,"")
B24: 64 Nodal Processors, 36 Mustard Processors, 8 Spice FX | G24: =IF(F24-F24*$G$16=0,"",F24-F24*$G$16) | H24: =IFERROR(G24*$H$16,"") | I24: =IFERROR(ROUND(H24*$I$16,0),"") | J24: =IFERROR((I24-H24)/I24,"")
B25: Local I/O 8 x 32bit Mic/Line inputs, 8 x 32bit Line outputs, 8 x AES I/O mono stream, dust cover, carton | G25: =IF(F25-F25*$G$16=0,"",F25-F25*$G$16) | H25: =IFERROR(G25*$H$16,"") | I25: =IFERROR(ROUND(H25*$I$16,0),"") | J25: =IFERROR((I25-H25)/I25,"")
B26: 1 x Stage SD-Rack, HMA optics, 2 BNC MADI, dual PSU - 56 32bit mic/line in / 40 32bit line out / 16 AES outputs | G26: =IF(F26-F26*$G$16=0,"",F26-F26*$G$16) | H26: =IFERROR(G26*$H$16,"") | I26: =IFERROR(ROUND(H26*$I$16,0),"") | J26: =IFERROR((I26-H26)/I26,"")
B27: 2 x 150m optical cable on drum | G27: =IF(F27-F27*$G$16=0,"",F27-F27*$G$16) | H27: =IFERROR(G27*$H$16,"") | I27: =IFERROR(ROUND(H27*$I$16,0),"") | J27: =IFERROR((I27-H27)/I27,"")
G28: =IF(F28-F28*$G$16=0,"",F28-F28*$G$16) | H28: =IFERROR(G28*$H$16,"") | I28: =IFERROR(ROUND(H28*$I$16,0),"") | J28: =IFERROR((I28-H28)/I28,"")
A29: DiGiCo Quantum 3 Surfaces | G29: =IF(F29-F29*$G$16=0,"",F29-F29*$G$16) | H29: =IFERROR(G29*$H$16,"") | I29: =IFERROR(ROUND(H29*$I$16,0),"") | J29: =IFERROR((I29-H29)/I29,"")
G30: =IF(F30-F30*$G$16=0,"",F30-F30*$G$16) | H30: =IFERROR(G30*$H$16,"") | I30: =IFERROR(ROUND(H30*$I$16,0),"") | J30: =IFERROR((I30-H30)/I30,"")
A31: X-Q338-WS | B31: DiGiCo Quantum 338 surface | E31: =ROUND(F31/0.55,0) -> 57426 | F31: 31584.375 | G31: =IF(F31-F31*$G$16=0,"",F31-F31*$G$16) -> 25267.5 | H31: =IFERROR(G31*$H$16,"") -> 3714322.5 | I31: =IFERROR(ROUND(H31*$I$16,0),"") -> 5274338 | J31: =IFERROR((I31-H31)/I31,"") -> 0.29577465
B32: Quantum 338 surface - 36+2 faders, 2 DMI slots, USB Audio I/O, 6 BNC MADI, 2 PSU, 16 GPIO | G32: =IF(F32-F32*$G$16=0,"",F32-F32*$G$16) | H32: =IFERROR(G32*$H$16,"") | I32: =IFERROR(ROUND(H32*$I$16,0),"") | J32: =IFERROR((I32-H32)/I32,"")
B33: 128 mono input channels, 64 mono output busses, | G33: =IF(F33-F33*$G$16=0,"",F33-F33*$G$16) | H33: =IFERROR(G33*$H$16,"") | I33: =IFERROR(ROUND(H33*$I$16,0),"") | J33: =IFERROR((I33-H33)/I33,"")
B34: 2 mono or stereo solo busses. LR or LCR master buss | G34: =IF(F34-F34*$G$16=0,"",F34-F34*$G$16) | H34: =IFERROR(G34*$H$16,"") | I34: =IFERROR(ROUND(H34*$I$16,0),"") | J34: =IFERROR((I34-H34)/I34,"")
B35: 24 x 24 matrix, 24 CG/VCA, 24 FX, 24 x 32 band graphic eq’s, | G35: =IF(F35-F35*$G$16=0,"",F35-F35*$G$16) | H35: =IFERROR(G35*$H$16,"") | I35: =IFERROR(ROUND(H35*$I$16,0),"") | J35: =IFERROR((I35-H35)/I35,"")
B36: 64 Nodal Processors, 36 Mustard Processors, 8 Spice FX | G36: =IF(F36-F36*$G$16=0,"",F36-F36*$G$16) | H36: =IFERROR(G36*$H$16,"") | I36: =IFERROR(ROUND(H36*$I$16,0),"") | J36: =IFERROR((I36-H36)/I36,"")
B37: Local I/O 8 x 32bit Mic/Line inputs, 8 x 32bit Line outputs, 8 x AES I/O mono stream, dust cover, carton | G37: =IF(F37-F37*$G$16=0,"",F37-F37*$G$16) | H37: =IFERROR(G37*$H$16,"") | I37: =IFERROR(ROUND(H37*$I$16,0),"") | J37: =IFERROR((I37-H37)/I37,"")
B38: Dimensions; 1595(w) x 805(d) x 482(h) mm Weight; 66kg | G38: =IF(F38-F38*$G$16=0,"",F38-F38*$G$16) | H38: =IFERROR(G38*$H$16,"") | I38: =IFERROR(ROUND(H38*$I$16,0),"") | J38: =IFERROR((I38-H38)/I38,"")
G39: =IF(F39-F39*$G$16=0,"",F39-F39*$G$16) | H39: =IFERROR(G39*$H$16,"") | I39: =IFERROR(ROUND(H39*$I$16,0),"") | J39: =IFERROR((I39-H39)/I39,"")
A40: X-Q338-WS-OP | B40: DiGiCo Quantum 338 surface - HMA optics | E40: =ROUND(F40/0.55,0) -> 64790 | F40: 35634.375 | G40: =IF(F40-F40*$G$16=0,"",F40-F40*$G$16) -> 28507.5 | H40: =IFERROR(G40*$H$16,"") -> 4190602.5 | I40: =IFERROR(ROUND(H40*$I$16,0),"") -> 5950656 | J40: =IFERROR((I40-H40)/I40,"") -> 0.2957747
B41: Quantum 338 surface - 36+2 faders, HMA optics, 2 DMI slots, USB Audio I/O, 6 BNC MADI, 2 PSU, 16 GPIO | G41: =IF(F41-F41*$G$16=0,"",F41-F41*$G$16) | H41: =IFERROR(G41*$H$16,"") | I41: =IFERROR(ROUND(H41*$I$16,0),"") | J41: =IFERROR((I41-H41)/I41,"")
B42: 128 mono input channels, 64 mono output busses, | G42: =IF(F42-F42*$G$16=0,"",F42-F42*$G$16) | H42: =IFERROR(G42*$H$16,"") | I42: =IFERROR(ROUND(H42*$I$16,0),"") | J42: =IFERROR((I42-H42)/I42,"")
B43: 2 mono or stereo solo busses. LR or LCR master buss | G43: =IF(F43-F43*$G$16=0,"",F43-F43*$G$16) | H43: =IFERROR(G43*$H$16,"") | I43: =IFERROR(ROUND(H43*$I$16,0),"") | J43: =IFERROR((I43-H43)/I43,"")
B44: 24 x 24 matrix, 24 CG/VCA, 24 FX, 24 x 32 band graphic eq’s, | G44: =IF(F44-F44*$G$16=0,"",F44-F44*$G$16) | H44: =IFERROR(G44*$H$16,"") | I44: =IFERROR(ROUND(H44*$I$16,0),"") | J44: =IFERROR((I44-H44)/I44,"")
B45: 64 Nodal Processors, 36 Mustard Processors, 8 Spice FX | G45: =IF(F45-F45*$G$16=0,"",F45-F45*$G$16) | H45: =IFERROR(G45*$H$16,"") | I45: =IFERROR(ROUND(H45*$I$16,0),"") | J45: =IFERROR((I45-H45)/I45,"")
B46: Local I/O 8 x 32bit Mic/Line inputs, 8 x 32bit Line outputs, 8 x AES I/O mono stream, dust cover, carton | G46: =IF(F46-F46*$G$16=0,"",F46-F46*$G$16) | H46: =IFERROR(G46*$H$16,"") | I46: =IFERROR(ROUND(H46*$I$16,0),"") | J46: =IFERROR((I46-H46)/I46,"")
B47: Dimensions; 1595(w) x 805(d) x 482(h) mm Weight; 66kg | G47: =IF(F47-F47*$G$16=0,"",F47-F47*$G$16) | H47: =IFERROR(G47*$H$16,"") | I47: =IFERROR(ROUND(H47*$I$16,0),"") | J47: =IFERROR((I47-H47)/I47,"")
G48: =IF(F48-F48*$G$16=0,"",F48-F48*$G$16) | H48: =IFERROR(G48*$H$16,"") | I48: =IFERROR(ROUND(H48*$I$16,0),"") | J48: =IFERROR((I48-H48)/I48,"")
A49: X-Q338-WS-NC | B49: DiGiCo Quantum 338 surface - NC optics | E49: =ROUND(F49/0.55,0) -> 63640 | F49: 35002.125 | G49: =IF(F49-F49*$G$16=0,"",F49-F49*$G$16) -> 28001.7 | H49: =IFERROR(G49*$H$16,"") -> 4116249.9 | I49: =IFERROR(ROUND(H49*$I$16,0),"") -> 5845075 | J49: =IFERROR((I49-H49)/I49,"") -> 0.29577466
B50: Quantum 338 surface - 36+2 faders, NC optics, 2 DMI slots, USB Audio I/O, 6 BNC MADI, 2 PSU, 16 GPIO | G50: =IF(F50-F50*$G$16=0,"",F50-F50*$G$16) | H50: =IFERROR(G50*$H$16,"") | I50: =IFERROR(ROUND(H50*$I$16,0),"") | J50: =IFERROR((I50-H50)/I50,"")
B51: 128 mono input channels, 64 mono output busses, | G51: =IF(F51-F51*$G$16=0,"",F51-F51*$G$16) | H51: =IFERROR(G51*$H$16,"") | I51: =IFERROR(ROUND(H51*$I$16,0),"") | J51: =IFERROR((I51-H51)/I51,"")
B52: 2 mono or stereo solo busses. LR or LCR master buss | G52: =IF(F52-F52*$G$16=0,"",F52-F52*$G$16) | H52: =IFERROR(G52*$H$16,"") | I52: =IFERROR(ROUND(H52*$I$16,0),"") | J52: =IFERROR((I52-H52)/I52,"")
B53: 24 x 24 matrix, 24 CG/VCA, 24 FX, 24 x 32 band graphic eq’s, | G53: =IF(F53-F53*$G$16=0,"",F53-F53*$G$16) | H53: =IFERROR(G53*$H$16,"") | I53: =IFERROR(ROUND(H53*$I$16,0),"") | J53: =IFERROR((I53-H53)/I53,"")
B54: 64 Nodal Processors, 36 Mustard Processors, 8 Spice FX | G54: =IF(F54-F54*$G$16=0,"",F54-F54*$G$16) | H54: =IFERROR(G54*$H$16,"") | I54: =IFERROR(ROUND(H54*$I$16,0),"") | J54: =IFERROR((I54-H54)/I54,"")
B55: Local I/O 8 x 32bit Mic/Line inputs, 8 x 32bit Line outputs, 8 x AES I/O mono stream, dust cover, carton | G55: =IF(F55-F55*$G$16=0,"",F55-F55*$G$16) | H55: =IFERROR(G55*$H$16,"") | I55: =IFERROR(ROUND(H55*$I$16,0),"") | J55: =IFERROR((I55-H55)/I55,"")
B56: Dimensions; 1595(w) x 805(d) x 482(h) mm Weight; 66kg | G56: =IF(F56-F56*$G$16=0,"",F56-F56*$G$16) | H56: =IFERROR(G56*$H$16,"") | I56: =IFERROR(ROUND(H56*$I$16,0),"") | J56: =IFERROR((I56-H56)/I56,"")
G57: =IF(F57-F57*$G$16=0,"",F57-F57*$G$16) | H57: =IFERROR(G57*$H$16,"") | I57: =IFERROR(ROUND(H57*$I$16,0),"") | J57: =IFERROR((I57-H57)/I57,"")
A58: X-Q338-WS-ST | B58: DiGiCo Quantum 338 surface - ST optics | E58: =ROUND(F58/0.55,0) -> 63464 | F58: 34905.375 | G58: =IF(F58-F58*$G$16=0,"",F58-F58*$G$16) -> 27924.3 | H58: =IFERROR(G58*$H$16,"") -> 4104872.1 | I58: =IFERROR(ROUND(H58*$I$16,0),"") -> 5828918 | J58: =IFERROR((I58-H58)/I58,"") -> 0.2957746
B59: Quantum 338 surface - 36+2 faders, ST optics, 2 DMI slots, USB Audio I/O, 6 BNC MADI, 2 PSU, 16 GPIO | G59: =IF(F59-F59*$G$16=0,"",F59-F59*$G$16) | H59: =IFERROR(G59*$H$16,"") | I59: =IFERROR(ROUND(H59*$I$16,0),"") | J59: =IFERROR((I59-H59)/I59,"")
B60: 128 mono input channels, 64 mono output busses, | G60: =IF(F60-F60*$G$16=0,"",F60-F60*$G$16) | H60: =IFERROR(G60*$H$16,"") | I60: =IFERROR(ROUND(H60*$I$16,0),"") | J60: =IFERROR((I60-H60)/I60,"")
B61: 2 mono or stereo solo busses. LR or LCR master buss | G61: =IF(F61-F61*$G$16=0,"",F61-F61*$G$16) | H61: =IFERROR(G61*$H$16,"") | I61: =IFERROR(ROUND(H61*$I$16,0),"") | J61: =IFERROR((I61-H61)/I61,"")
B62: 24 x 24 matrix, 24 CG/VCA, 24 FX, 24 x 32 band graphic eq’s, | G62: =IF(F62-F62*$G$16=0,"",F62-F62*$G$16) | H62: =IFERROR(G62*$H$16,"") | I62: =IFERROR(ROUND(H62*$I$16,0),"") | J62: =IFERROR((I62-H62)/I62,"")
B63: 64 Nodal Processors, 36 Mustard Processors, 8 Spice FX | G63: =IF(F63-F63*$G$16=0,"",F63-F63*$G$16) | H63: =IFERROR(G63*$H$16,"") | I63: =IFERROR(ROUND(H63*$I$16,0),"") | J63: =IFERROR((I63-H63)/I63,"")
B64: Local I/O 8 x 32bit Mic/Line inputs, 8 x 32bit Line outputs, 8 x AES I/O mono stream, dust cover, carton | G64: =IF(F64-F64*$G$16=0,"",F64-F64*$G$16) | H64: =IFERROR(G64*$H$16,"") | I64: =IFERROR(ROUND(H64*$I$16,0),"") | J64: =IFERROR((I64-H64)/I64,"")
B65: Dimensions; 1595(w) x 805(d) x 482(h) mm Weight; 66kg | G65: =IF(F65-F65*$G$16=0,"",F65-F65*$G$16) | H65: =IFERROR(G65*$H$16,"") | I65: =IFERROR(ROUND(H65*$I$16,0),"") | J65: =IFERROR((I65-H65)/I65,"")
G66: =IF(F66-F66*$G$16=0,"",F66-F66*$G$16) | H66: =IFERROR(G66*$H$16,"") | I66: =IFERROR(ROUND(H66*$I$16,0),"") | J66: =IFERROR((I66-H66)/I66,"")
A67: X-Q326-WS | B67: DiGiCo Quantum 326 surface | E67: =ROUND(F67/0.55,0) -> 49356 | F67: 27146 | G67: =IF(F67-F67*$G$16=0,"",F67-F67*$G$16) -> 21716.8 | H67: =IFERROR(G67*$H$16,"") -> 3192369.6 | I67: =IFERROR(ROUND(H67*$I$16,0),"") -> 4533165 | J67: =IFERROR((I67-H67)/I67,"") -> 0.29577467
B68: Quantum 326 surface - 24+2 faders, 2 DMI slots, USB Audio I/O, 6 BNC MADI, 2 PSU, 16 GPIO | G68: =IF(F68-F68*$G$16=0,"",F68-F68*$G$16) | H68: =IFERROR(G68*$H$16,"") | I68: =IFERROR(ROUND(H68*$I$16,0),"") | J68: =IFERROR((I68-H68)/I68,"")
B69: 128 mono input channels, 64 mono output busses, | G69: =IF(F69-F69*$G$16=0,"",F69-F69*$G$16) | H69: =IFERROR(G69*$H$16,"") | I69: =IFERROR(ROUND(H69*$I$16,0),"") | J69: =IFERROR((I69-H69)/I69,"")
B70: 2 mono or stereo solo busses. LR or LCR master buss | G70: =IF(F70-F70*$G$16=0,"",F70-F70*$G$16) | H70: =IFERROR(G70*$H$16,"") | I70: =IFERROR(ROUND(H70*$I$16,0),"") | J70: =IFERROR((I70-H70)/I70,"")
B71: 24 x 24 matrix, 24 CG/VCA, 24 FX, 24 x 32 band graphic eq’s, | G71: =IF(F71-F71*$G$16=0,"",F71-F71*$G$16) | H71: =IFERROR(G71*$H$16,"") | I71: =IFERROR(ROUND(H71*$I$16,0),"") | J71: =IFERROR((I71-H71)/I71,"")
B72: 64 Nodal Processors, 36 Mustard Processors, 8 Spice FX | G72: =IF(F72-F72*$G$16=0,"",F72-F72*$G$16) | H72: =IFERROR(G72*$H$16,"") | I72: =IFERROR(ROUND(H72*$I$16,0),"") | J72: =IFERROR((I72-H72)/I72,"")
B73: Local I/O 8 x 32bit Mic/Line inputs, 8 x 32bit Line outputs, 8 x AES I/O mono stream, dust cover, carton | G73: =IF(F73-F73*$G$16=0,"",F73-F73*$G$16) | H73: =IFERROR(G73*$H$16,"") | I73: =IFERROR(ROUND(H73*$I$16,0),"") | J73: =IFERROR((I73-H73)/I73,"")
B74: Dimensions; 1124(w) x 805(d) x 482(h) mm Weight; 52kg | G74: =IF(F74-F74*$G$16=0,"",F74-F74*$G$16) | H74: =IFERROR(G74*$H$16,"") | I74: =IFERROR(ROUND(H74*$I$16,0),"") | J74: =IFERROR((I74-H74)/I74,"")
G75: =IF(F75-F75*$G$16=0,"",F75-F75*$G$16) | H75: =IFERROR(G75*$H$16,"") | I75: =IFERROR(ROUND(H75*$I$16,0),"") | J75: =IFERROR((I75-H75)/I75,"")
A76: X-Q326-WS-OP | B76: DiGiCo Quantum 326 surface - HMA optics | E76: =ROUND(F76/0.55,0) -> 56720 | F76: 31196 | G76: =IF(F76-F76*$G$16=0,"",F76-F76*$G$16) -> 24956.8 | H76: =IFERROR(G76*$H$16,"") -> 3668649.6 | I76: =IFERROR(ROUND(H76*$I$16,0),"") -> 5209482 | J76: =IFERROR((I76-H76)/I76,"") -> 0.29577459
B77: Quantum 326 surface - 24+2 faders, HMA optics, 2 DMI slots, USB Audio I/O, 6 BNC MADI, 2 PSU, 16 GPIO | G77: =IF(F77-F77*$G$16=0,"",F77-F77*$G$16) | H77: =IFERROR(G77*$H$16,"") | I77: =IFERROR(ROUND(H77*$I$16,0),"") | J77: =IFERROR((I77-H77)/I77,"")
B78: 128 mono input channels, 64 mono output busses, | G78: =IF(F78-F78*$G$16=0,"",F78-F78*$G$16) | H78: =IFERROR(G78*$H$16,"") | I78: =IFERROR(ROUND(H78*$I$16,0),"") | J78: =IFERROR((I78-H78)/I78,"")
B79: 2 mono or stereo solo busses. LR or LCR master buss | G79: =IF(F79-F79*$G$16=0,"",F79-F79*$G$16) | H79: =IFERROR(G79*$H$16,"") | I79: =IFERROR(ROUND(H79*$I$16,0),"") | J79: =IFERROR((I79-H79)/I79,"")
B80: 24 x 24 matrix, 24 CG/VCA, 24 FX, 24 x 32 band graphic eq’s, | G80: =IF(F80-F80*$G$16=0,"",F80-F80*$G$16) | H80: =IFERROR(G80*$H$16,"") | I80: =IFERROR(ROUND(H80*$I$16,0),"") | J80: =IFERROR((I80-H80)/I80,"")
B81: 64 Nodal Processors, 36 Mustard Processors, 8 Spice FX | G81: =IF(F81-F81*$G$16=0,"",F81-F81*$G$16) | H81: =IFERROR(G81*$H$16,"") | I81: =IFERROR(ROUND(H81*$I$16,0),"") | J81: =IFERROR((I81-H81)/I81,"")
B82: Local I/O 8 x 32bit Mic/Line inputs, 8 x 32bit Line outputs, 8 x AES I/O mono stream, dust cover, carton | G82: =IF(F82-F82*$G$16=0,"",F82-F82*$G$16) | H82: =IFERROR(G82*$H$16,"") | I82: =IFERROR(ROUND(H82*$I$16,0),"") | J82: =IFERROR((I82-H82)/I82,"")
B83: Dimensions; 1124(w) x 805(d) x 482(h) mm Weight; 52kg | G83: =IF(F83-F83*$G$16=0,"",F83-F83*$G$16) | H83: =IFERROR(G83*$H$16,"") | I83: =IFERROR(ROUND(H83*$I$16,0),"") | J83: =IFERROR((I83-H83)/I83,"")
G84: =IF(F84-F84*$G$16=0,"",F84-F84*$G$16) | H84: =IFERROR(G84*$H$16,"") | I84: =IFERROR(ROUND(H84*$I$16,0),"") | J84: =IFERROR((I84-H84)/I84,"")
A85: X-Q326-WS-NC | B85: DiGiCo Quantum 326 surface - NC optics | E85: =ROUND(F85/0.55,0) -> 55607 | F85: 30584 | G85: =IF(F85-F85*$G$16=0,"",F85-F85*$G$16) -> 24467.2 | H85: =IFERROR(G85*$H$16,"") -> 3596678.4 | I85: =IFERROR(ROUND(H85*$I$16,0),"") -> 5107283 | J85: =IFERROR((I85-H85)/I85,"") -> 0.2957746
B86: Quantum 326 surface - 24+2 faders, NC optics, 2 DMI slots, USB Audio I/O, 6 BNC MADI, 2 PSU, 16 GPIO | G86: =IF(F86-F86*$G$16=0,"",F86-F86*$G$16) | H86: =IFERROR(G86*$H$16,"") | I86: =IFERROR(ROUND(H86*$I$16,0),"") | J86: =IFERROR((I86-H86)/I86,"")
B87: 128 mono input channels, 64 mono output busses, | G87: =IF(F87-F87*$G$16=0,"",F87-F87*$G$16) | H87: =IFERROR(G87*$H$16,"") | I87: =IFERROR(ROUND(H87*$I$16,0),"") | J87: =IFERROR((I87-H87)/I87,"")
B88: 2 mono or stereo solo busses. LR or LCR master buss | G88: =IF(F88-F88*$G$16=0,"",F88-F88*$G$16) | H88: =IFERROR(G88*$H$16,"") | I88: =IFERROR(ROUND(H88*$I$16,0),"") | J88: =IFERROR((I88-H88)/I88,"")
B89: 24 x 24 matrix, 24 CG/VCA, 24 FX, 24 x 32 band graphic eq’s, | G89: =IF(F89-F89*$G$16=0,"",F89-F89*$G$16) | H89: =IFERROR(G89*$H$16,"") | I89: =IFERROR(ROUND(H89*$I$16,0),"") | J89: =IFERROR((I89-H89)/I89,"")
B90: 64 Nodal Processors, 36 Mustard Processors, 8 Spice FX | G90: =IF(F90-F90*$G$16=0,"",F90-F90*$G$16) | H90: =IFERROR(G90*$H$16,"") | I90: =IFERROR(ROUND(H90*$I$16,0),"") | J90: =IFERROR((I90-H90)/I90,"")
B91: Local I/O 8 x 32bit Mic/Line inputs, 8 x 32bit Line outputs, 8 x AES I/O mono stream, dust cover, carton | G91: =IF(F91-F91*$G$16=0,"",F91-F91*$G$16) | H91: =IFERROR(G91*$H$16,"") | I91: =IFERROR(ROUND(H91*$I$16,0),"") | J91: =IFERROR((I91-H91)/I91,"")
B92: Dimensions; 1124(w) x 805(d) x 482(h) mm Weight; 52kg | G92: =IF(F92-F92*$G$16=0,"",F92-F92*$G$16) | H92: =IFERROR(G92*$H$16,"") | I92: =IFERROR(ROUND(H92*$I$16,0),"") | J92: =IFERROR((I92-H92)/I92,"")
G93: =IF(F93-F93*$G$16=0,"",F93-F93*$G$16) | H93: =IFERROR(G93*$H$16,"") | I93: =IFERROR(ROUND(H93*$I$16,0),"") | J93: =IFERROR((I93-H93)/I93,"")
A94: X-Q326-WS-ST | B94: DiGiCo Quantum 326 surface - ST optics | E94: =ROUND(F94/0.55,0) -> 55395 | F94: 30467 | G94: =IF(F94-F94*$G$16=0,"",F94-F94*$G$16) -> 24373.6 | H94: =IFERROR(G94*$H$16,"") -> 3582919.2 | I94: =IFERROR(ROUND(H94*$I$16,0),"") -> 5087745 | J94: =IFERROR((I94-H94)/I94,"") -> 0.29577461
B95: Quantum 326 surface - 24+2 faders, ST optics, 2 DMI slots, USB Audio I/O, 6 BNC MADI, 2 PSU, 16 GPIO | G95: =IF(F95-F95*$G$16=0,"",F95-F95*$G$16) | H95: =IFERROR(G95*$H$16,"") | I95: =IFERROR(ROUND(H95*$I$16,0),"") | J95: =IFERROR((I95-H95)/I95,"")
B96: 128 mono input channels, 64 mono output busses, | G96: =IF(F96-F96*$G$16=0,"",F96-F96*$G$16) | H96: =IFERROR(G96*$H$16,"") | I96: =IFERROR(ROUND(H96*$I$16,0),"") | J96: =IFERROR((I96-H96)/I96,"")
B97: 2 mono or stereo solo busses. LR or LCR master buss | G97: =IF(F97-F97*$G$16=0,"",F97-F97*$G$16) | H97: =IFERROR(G97*$H$16,"") | I97: =IFERROR(ROUND(H97*$I$16,0),"") | J97: =IFERROR((I97-H97)/I97,"")
B98: 24 x 24 matrix, 24 CG/VCA, 24 FX, 24 x 32 band graphic eq’s, | G98: =IF(F98-F98*$G$16=0,"",F98-F98*$G$16) | H98: =IFERROR(G98*$H$16,"") | I98: =IFERROR(ROUND(H98*$I$16,0),"") | J98: =IFERROR((I98-H98)/I98,"")
B99: 64 Nodal Processors, 36 Mustard Processors, 8 Spice FX | G99: =IF(F99-F99*$G$16=0,"",F99-F99*$G$16) | H99: =IFERROR(G99*$H$16,"") | I99: =IFERROR(ROUND(H99*$I$16,0),"") | J99: =IFERROR((I99-H99)/I99,"")
B100: Local I/O 8 x 32bit Mic/Line inputs, 8 x 32bit Line outputs, 8 x AES I/O mono stream, dust cover, carton | G100: =IF(F100-F100*$G$16=0,"",F100-F100*$G$16) | H100: =IFERROR(G100*$H$16,"") | I100: =IFERROR(ROUND(H100*$I$16,0),"") | J100: =IFERROR((I100-H100)/I100,"")
B101: Dimensions; 1124(w) x 805(d) x 482(h) mm Weight; 52kg | G101: =IF(F101-F101*$G$16=0,"",F101-F101*$G$16) | H101: =IFERROR(G101*$H$16,"") | I101: =IFERROR(ROUND(H101*$I$16,0),"") | J101: =IFERROR((I101-H101)/I101,"")
G102: =IF(F102-F102*$G$16=0,"",F102-F102*$G$16) | H102: =IFERROR(G102*$H$16,"") | I102: =IFERROR(ROUND(H102*$I$16,0),"") | J102: =IFERROR((I102-H102)/I102,"")
A103: DiGiCo Quantum 3 Surface Options | G103: =IF(F103-F103*$G$16=0,"",F103-F103*$G$16) | H103: =IFERROR(G103*$H$16,"") | I103: =IFERROR(ROUND(H103*$I$16,0),"") | J103: =IFERROR((I103-H103)/I103,"")
G104: =IF(F104-F104*$G$16=0,"",F104-F104*$G$16) | H104: =IFERROR(G104*$H$16,"") | I104: =IFERROR(ROUND(H104*$I$16,0),"") | J104: =IFERROR((I104-H104)/I104,"")
A105: MOD-Q3-OPTO | B105: DiGiCo Quantum 3 Optocore interface (HMA) | E105: =ROUND(F105/0.55,0) -> 7364 | F105: 4050 | G105: =IF(F105-F105*$G$16=0,"",F105-F105*$G$16) -> 3240 | H105: =IFERROR(G105*$H$16,"") -> 476280 | I105: =IFERROR(ROUND(H105*$I$16,0),"") -> 676318 | J105: =IFERROR((I105-H105)/I105,"") -> 0.29577506
...

Sheet Q 5
B1: DiGiCo Quantum 5 Distributor Price List
B3: Sept 2024
B5: Unit 10 Silverglade Business Park, Leatherhead Road
B6: Chessington, Surrey, KT9 2QL
B7: Tel; +44 1372 845600
B8: Fax; +44 1372 845656
B9: email; sales@digiconsoles.com
B10: web; www.digiconsoles.com
B12: FCA Glenrothes KY7 4NX. E&OE. Prices, Products and Specification are subject to change without notice.
B13: This price list supercedes all previous price lists.
A15: Product Code | B15: Description | E15: List (£) | F15: Distributor (£) | G15: Disc. | H15: HT Buy (INR) | I15: Customer Price | J15: Hi-Tech
G16: 0 | H16: 147 | I16: 1.42 | J16: Margin
A17: DiGiCo Quantum 5 32Bit System
B19: DiGiCo Quantum 5 32bit touring system | E19: =ROUND(F19/0.55,0) -> 144627 | F19: 79544.88 | G19: =IF(F19-F19*$G$16=0,"",F19-F19*$G$16) -> 79544.88 | H19: =IFERROR(G19*$H$16,"") -> 11693097 | I19: =IFERROR(ROUND(H19*$I$16,0),"") -> 16604198 | J19: =IFERROR((I19-H19)/I19,"") -> 0.29577464
B20: 1 x Quantum 5 surface - 36+1 faders, HMA optics, 2 DMI slots, USB Audio I/O, 8 BNC MADI, 2 PSU, 16 GPI/O | G20: =IF(F20-F20*$G$16=0,"",F20-F20*$G$16) | H20: =IFERROR(G20*$H$16,"") | I20: =IFERROR(ROUND(H20*$I$16,0),"") | J20: =IFERROR((I20-H20)/I20,"")
B21: 288 processing paths where up to 128 can be output busses | G21: =IF(F21-F21*$G$16=0,"",F21-F21*$G$16) | H21: =IFERROR(G21*$H$16,"") | I21: =IFERROR(ROUND(H21*$I$16,0),"") | J21: =IFERROR((I21-H21)/I21,"")
B22: 2 mono or stereo solo busses. LR, LCR. LCRS or 5.1 master buss | G22: =IF(F22-F22*$G$16=0,"",F22-F22*$G$16) | H22: =IFERROR(G22*$H$16,"") | I22: =IFERROR(ROUND(H22*$I$16,0),"") | J22: =IFERROR((I22-H22)/I22,"")
B23: 48ch USB audio I/O, 64ch plugin I/O (Fourier or Waves), 36 x 36 matrix, 36 CG/VCA, 36 FX, 32 x 32 band graphic eq’s | G23: =IF(F23-F23*$G$16=0,"",F23-F23*$G$16) | H23: =IFERROR(G23*$H$16,"") | I23: =IFERROR(ROUND(H23*$I$16,0),"") | J23: =IFERROR((I23-H23)/I23,"")
B24: 128 Nodal Processors, 64 Mustard Processors, 12 Spice FX | G24: =IF(F24-F24*$G$16=0,"",F24-F24*$G$16) | H24: =IFERROR(G24*$H$16,"") | I24: =IFERROR(ROUND(H24*$I$16,0),"") | J24: =IFERROR((I24-H24)/I24,"")
B25: Local I/O 8 x Mic/Line inputs, 8 x Line outputs, 8 x AES I/O mono stream, dust cover | G25: =IF(F25-F25*$G$16=0,"",F25-F25*$G$16) | H25: =IFERROR(G25*$H$16,"") | I25: =IFERROR(ROUND(H25*$I$16,0),"") | J25: =IFERROR((I25-H25)/I25,"")
B26: 1 x Stage SD-Rack, HMA optics, 2 BNC MADI, 2 MADI splits, dual PSU - 56 32bit mic/line in / 40 32bit line out / 16 AES out, packing carton | G26: =IF(F26-F26*$G$16=0,"",F26-F26*$G$16) | H26: =IFERROR(G26*$H$16,"") | I26: =IFERROR(ROUND(H26*$I$16,0),"") | J26: =IFERROR((I26-H26)/I26,"")
B27: 2 x 150m HMA optical cable on drum | G27: =IF(F27-F27*$G$16=0,"",F27-F27*$G$16) | H27: =IFERROR(G27*$H$16,"") | I27: =IFERROR(ROUND(H27*$I$16,0),"") | J27: =IFERROR((I27-H27)/I27,"")
B28: 1 x Touring surface flight case | G28: =IF(F28-F28*$G$16=0,"",F28-F28*$G$16) | H28: =IFERROR(G28*$H$16,"") | I28: =IFERROR(ROUND(H28*$I$16,0),"") | J28: =IFERROR((I28-H28)/I28,"")
G29: =IF(F29-F29*$G$16=0,"",F29-F29*$G$16) | H29: =IFERROR(G29*$H$16,"") | I29: =IFERROR(ROUND(H29*$I$16,0),"") | J29: =IFERROR((I29-H29)/I29,"")
A30: DiGiCo Quantum 5 Surface | E30: =ROUND(F30/0.55,0) -> 0 | G30: =IF(F30-F30*$G$16=0,"",F30-F30*$G$16) | H30: =IFERROR(G30*$H$16,"") | I30: =IFERROR(ROUND(H30*$I$16,0),"") | J30: =IFERROR((I30-H30)/I30,"")
G31: =IF(F31-F31*$G$16=0,"",F31-F31*$G$16) | H31: =IFERROR(G31*$H$16,"") | I31: =IFERROR(ROUND(H31*$I$16,0),"") | J31: =IFERROR((I31-H31)/I31,"")
A32: X-Q5-WS | B32: DiGiCo Quantum 5 Surface - MADI | E32: =ROUND(F32/0.55,0) -> 100162 | F32: 55088.88 | G32: =IF(F32-F32*$G$16=0,"",F32-F32*$G$16) -> 55088.88 | H32: =IFERROR(G32*$H$16,"") -> 8098065.4 | I32: =IFERROR(ROUND(H32*$I$16,0),"") -> 11499253 | J32: =IFERROR((I32-H32)/I32,"") -> 0.29577466
B33: Quantum 5 surface - 36+1 faders, 2 DMI slots, USB Audio I/O, 8 BNC MADI, 2 PSU, 16 GPI/O | G33: =IF(F33-F33*$G$16=0,"",F33-F33*$G$16) | H33: =IFERROR(G33*$H$16,"") | I33: =IFERROR(ROUND(H33*$I$16,0),"") | J33: =IFERROR((I33-H33)/I33,"")
B34: 288 processing paths where up to 128 can be output busses | G34: =IF(F34-F34*$G$16=0,"",F34-F34*$G$16) | H34: =IFERROR(G34*$H$16,"") | I34: =IFERROR(ROUND(H34*$I$16,0),"") | J34: =IFERROR((I34-H34)/I34,"")
B35: 2 mono or stereo solo busses. LR, LCR. LCRS or 5.1 master buss | G35: =IF(F35-F35*$G$16=0,"",F35-F35*$G$16) | H35: =IFERROR(G35*$H$16,"") | I35: =IFERROR(ROUND(H35*$I$16,0),"") | J35: =IFERROR((I35-H35)/I35,"")
B36: 48ch USB audio I/O, 36 x 36 matrix, 36 CG/VCA, 36 FX, 32 x 32 band graphic eq’s | G36: =IF(F36-F36*$G$16=0,"",F36-F36*$G$16) | H36: =IFERROR(G36*$H$16,"") | I36: =IFERROR(ROUND(H36*$I$16,0),"") | J36: =IFERROR((I36-H36)/I36,"")
B37: 128 Nodal Processors, 64 Mustard Processors, 12 Spice FX | G37: =IF(F37-F37*$G$16=0,"",F37-F37*$G$16) | H37: =IFERROR(G37*$H$16,"") | I37: =IFERROR(ROUND(H37*$I$16,0),"") | J37: =IFERROR((I37-H37)/I37,"")
B38: Local I/O 8 x Mic/Line inputs, 8 x Line outputs, 8 x AES I/O mono stream, dust cover | G38: =IF(F38-F38*$G$16=0,"",F38-F38*$G$16) | H38: =IFERROR(G38*$H$16,"") | I38: =IFERROR(ROUND(H38*$I$16,0),"") | J38: =IFERROR((I38-H38)/I38,"")
B39: Dimensions; 1465(w) x 838(d) x 458(h) mm Weight; 116Kg | G39: =IF(F39-F39*$G$16=0,"",F39-F39*$G$16) | H39: =IFERROR(G39*$H$16,"") | I39: =IFERROR(ROUND(H39*$I$16,0),"") | J39: =IFERROR((I39-H39)/I39,"")
G40: =IF(F40-F40*$G$16=0,"",F40-F40*$G$16) | H40: =IFERROR(G40*$H$16,"") | I40: =IFERROR(ROUND(H40*$I$16,0),"") | J40: =IFERROR((I40-H40)/I40,"")
A41: X-Q5-WS-OP | B41: DiGiCo Quantum 5 Surface - MADI / HMA optics | E41: =ROUND(F41/0.55,0) -> 107143 | F41: 58928.5 | G41: =IF(F41-F41*$G$16=0,"",F41-F41*$G$16) -> 58928.5 | H41: =IFERROR(G41*$H$16,"") -> 8662489.5 | I41: =IFERROR(ROUND(H41*$I$16,0),"") -> 12300735 | J41: =IFERROR((I41-H41)/I41,"") -> 0.29577464
B42: Quantum 5 surface - 36+1 faders, HMA optics, 2 DMI slots, USB Audio I/O, 8 BNC MADI, 2 PSU, 16 GPI/O | G42: =IF(F42-F42*$G$16=0,"",F42-F42*$G$16) | H42: =IFERROR(G42*$H$16,"") | I42: =IFERROR(ROUND(H42*$I$16,0),"") | J42: =IFERROR((I42-H42)/I42,"")
B43: 288 processing paths where up to 128 can be output busses | G43: =IF(F43-F43*$G$16=0,"",F43-F43*$G$16) | H43: =IFERROR(G43*$H$16,"") | I43: =IFERROR(ROUND(H43*$I$16,0),"") | J43: =IFERROR((I43-H43)/I43,"")
B44: 2 mono or stereo solo busses. LR, LCR. LCRS or 5.1 master buss | G44: =IF(F44-F44*$G$16=0,"",F44-F44*$G$16) | H44: =IFERROR(G44*$H$16,"") | I44: =IFERROR(ROUND(H44*$I$16,0),"") | J44: =IFERROR((I44-H44)/I44,"")
B45: 48ch USB audio I/O, 36 x 36 matrix, 36 CG/VCA, 36 FX, 32 x 32 band graphic eq’s | G45: =IF(F45-F45*$G$16=0,"",F45-F45*$G$16) | H45: =IFERROR(G45*$H$16,"") | I45: =IFERROR(ROUND(H45*$I$16,0),"") | J45: =IFERROR((I45-H45)/I45,"")
B46: 128 Nodal Processors, 64 Mustard Processors, 12 Spice FX | G46: =IF(F46-F46*$G$16=0,"",F46-F46*$G$16) | H46: =IFERROR(G46*$H$16,"") | I46: =IFERROR(ROUND(H46*$I$16,0),"") | J46: =IFERROR((I46-H46)/I46,"")
B47: Local I/O 8 x Mic/Line inputs, 8 x Line outputs, 8 x AES I/O mono stream, dust cover | G47: =IF(F47-F47*$G$16=0,"",F47-F47*$G$16) | H47: =IFERROR(G47*$H$16,"") | I47: =IFERROR(ROUND(H47*$I$16,0),"") | J47: =IFERROR((I47-H47)/I47,"")
B48: Dimensions; 1465(w) x 838(d) x 458(h) mm Weight; 116Kg | G48: =IF(F48-F48*$G$16=0,"",F48-F48*$G$16) | H48: =IFERROR(G48*$H$16,"") | I48: =IFERROR(ROUND(H48*$I$16,0),"") | J48: =IFERROR((I48-H48)/I48,"")
G49: =IF(F49-F49*$G$16=0,"",F49-F49*$G$16) | H49: =IFERROR(G49*$H$16,"") | I49: =IFERROR(ROUND(H49*$I$16,0),"") | J49: =IFERROR((I49-H49)/I49,"")
A50: X-Q5-WS-NC | B50: DiGiCo Quantum 5 Surface - MADI / NC optics | E50: =ROUND(F50/0.55,0) -> 106030 | F50: 58316.5 | G50: =IF(F50-F50*$G$16=0,"",F50-F50*$G$16) -> 58316.5 | H50: =IFERROR(G50*$H$16,"") -> 8572525.5 | I50: =IFERROR(ROUND(H50*$I$16,0),"") -> 12172986 | J50: =IFERROR((I50-H50)/I50,"") -> 0.29577464
B51: Quantum 5 surface - 36+1 faders, NC optics, 2 DMI slots, USB Audio I/O, 8 BNC MADI, 2 PSU, 16 GPI/O | G51: =IF(F51-F51*$G$16=0,"",F51-F51*$G$16) | H51: =IFERROR(G51*$H$16,"") | I51: =IFERROR(ROUND(H51*$I$16,0),"") | J51: =IFERROR((I51-H51)/I51,"")
B52: 288 processing paths where up to 128 can be output busses | G52: =IF(F52-F52*$G$16=0,"",F52-F52*$G$16) | H52: =IFERROR(G52*$H$16,"") | I52: =IFERROR(ROUND(H52*$I$16,0),"") | J52: =IFERROR((I52-H52)/I52,"")
B53: 2 mono or stereo solo busses. LR, LCR. LCRS or 5.1 master buss | G53: =IF(F53-F53*$G$16=0,"",F53-F53*$G$16) | H53: =IFERROR(G53*$H$16,"") | I53: =IFERROR(ROUND(H53*$I$16,0),"") | J53: =IFERROR((I53-H53)/I53,"")
B54: 48ch USB audio I/O, 36 x 36 matrix, 36 CG/VCA, 36 FX, 32 x 32 band graphic eq’s | G54: =IF(F54-F54*$G$16=0,"",F54-F54*$G$16) | H54: =IFERROR(G54*$H$16,"") | I54: =IFERROR(ROUND(H54*$I$16,0),"") | J54: =IFERROR((I54-H54)/I54,"")
B55: 128 Nodal Processors, 64 Mustard Processors, 12 Spice FX | G55: =IF(F55-F55*$G$16=0,"",F55-F55*$G$16) | H55: =IFERROR(G55*$H$16,"") | I55: =IFERROR(ROUND(H55*$I$16,0),"") | J55: =IFERROR((I55-H55)/I55,"")
B56: Local I/O 8 x Mic/Line inputs, 8 x Line outputs, 8 x AES I/O mono stream, dust cover | G56: =IF(F56-F56*$G$16=0,"",F56-F56*$G$16) | H56: =IFERROR(G56*$H$16,"") | I56: =IFERROR(ROUND(H56*$I$16,0),"") | J56: =IFERROR((I56-H56)/I56,"")
B57: Dimensions; 1465(w) x 838(d) x 458(h) mm Weight; 116Kg | G57: =IF(F57-F57*$G$16=0,"",F57-F57*$G$16) | H57: =IFERROR(G57*$H$16,"") | I57: =IFERROR(ROUND(H57*$I$16,0),"") | J57: =IFERROR((I57-H57)/I57,"")
G58: =IF(F58-F58*$G$16=0,"",F58-F58*$G$16) | H58: =IFERROR(G58*$H$16,"") | I58: =IFERROR(ROUND(H58*$I$16,0),"") | J58: =IFERROR((I58-H58)/I58,"")
A59: X-Q5-WS-ST | B59: DiGiCo Quantum 5 Surface - MADI / ST optics | E59: =ROUND(F59/0.55,0) -> 105817 | F59: 58199.5 | G59: =IF(F59-F59*$G$16=0,"",F59-F59*$G$16) -> 58199.5 | H59: =IFERROR(G59*$H$16,"") -> 8555326.5 | I59: =IFERROR(ROUND(H59*$I$16,0),"") -> 12148564 | J59: =IFERROR((I59-H59)/I59,"") -> 0.29577467
B60: Quantum 5 surface - 36+1 faders, ST optics, 2 DMI slots, USB Audio I/O, 8 BNC MADI, 2 PSU, 16 GPI/O | G60: =IF(F60-F60*$G$16=0,"",F60-F60*$G$16) | H60: =IFERROR(G60*$H$16,"") | I60: =IFERROR(ROUND(H60*$I$16,0),"") | J60: =IFERROR((I60-H60)/I60,"")
B61: 288 processing paths where up to 128 can be output busses | G61: =IF(F61-F61*$G$16=0,"",F61-F61*$G$16) | H61: =IFERROR(G61*$H$16,"") | I61: =IFERROR(ROUND(H61*$I$16,0),"") | J61: =IFERROR((I61-H61)/I61,"")
B62: 2 mono or stereo solo busses. LR, LCR. LCRS or 5.1 master buss | G62: =IF(F62-F62*$G$16=0,"",F62-F62*$G$16) | H62: =IFERROR(G62*$H$16,"") | I62: =IFERROR(ROUND(H62*$I$16,0),"") | J62: =IFERROR((I62-H62)/I62,"")
B63: 48ch USB audio I/O, 36 x 36 matrix, 36 CG/VCA, 36 FX, 32 x 32 band graphic eq’s | G63: =IF(F63-F63*$G$16=0,"",F63-F63*$G$16) | H63: =IFERROR(G63*$H$16,"") | I63: =IFERROR(ROUND(H63*$I$16,0),"") | J63: =IFERROR((I63-H63)/I63,"")
B64: 128 Nodal Processors, 64 Mustard Processors, 12 Spice FX | G64: =IF(F64-F64*$G$16=0,"",F64-F64*$G$16) | H64: =IFERROR(G64*$H$16,"") | I64: =IFERROR(ROUND(H64*$I$16,0),"") | J64: =IFERROR((I64-H64)/I64,"")
B65: Local I/O 8 x Mic/Line inputs, 8 x Line outputs, 8 x AES I/O mono stream, dust cover | G65: =IF(F65-F65*$G$16=0,"",F65-F65*$G$16) | H65: =IFERROR(G65*$H$16,"") | I65: =IFERROR(ROUND(H65*$I$16,0),"") | J65: =IFERROR((I65-H65)/I65,"")
B66: Dimensions; 1465(w) x 838(d) x 458(h) mm Weight; 116Kg | G66: =IF(F66-F66*$G$16=0,"",F66-F66*$G$16) | H66: =IFERROR(G66*$H$16,"") | I66: =IFERROR(ROUND(H66*$I$16,0),"") | J66: =IFERROR((I66-H66)/I66,"")
G67: =IF(F67-F67*$G$16=0,"",F67-F67*$G$16) | H67: =IFERROR(G67*$H$16,"") | I67: =IFERROR(ROUND(H67*$I$16,0),"") | J67: =IFERROR((I67-H67)/I67,"")
A68: DiGiCo SD5 Surface Upgrade to Quantum 5 pecification - Trade in Existing Engines | E68: =ROUND(F68/0.55,0) -> 0 | G68: =IF(F68-F68*$G$16=0,"",F68-F68*$G$16) | H68: =IFERROR(G68*$H$16,"") | I68: =IFERROR(ROUND(H68*$I$16,0),"") | J68: =IFERROR((I68-H68)/I68,"")
G69: =IF(F69-F69*$G$16=0,"",F69-F69*$G$16) | H69: =IFERROR(G69*$H$16,"") | I69: =IFERROR(ROUND(H69*$I$16,0),"") | J69: =IFERROR((I69-H69)/I69,"")
A70: X-Q5-UP-OP | B70: DiGiCo SD5 surface upgrade to Quantum 5 spec - MADI / HMA optics | E70: =ROUND(F70/0.55,0) -> 23705 | F70: 13037.5 | G70: =IF(F70-F70*$G$16=0,"",F70-F70*$G$16) -> 13037.5 | H70: =IFERROR(G70*$H$16,"") -> 1916512.5 | I70: =IFERROR(ROUND(H70*$I$16,0),"") -> 2721448 | J70: =IFERROR((I70-H70)/I70,"") -> 0.29577471
B71: Quantum 5 engine, HMA optics, 2 DMI slots, USB Audio I/O, 8 BNC MADI, 2 PSU, 16 GPI/O | G71: =IF(F71-F71*$G$16=0,"",F71-F71*$G$16) | H71: =IFERROR(G71*$H$16,"") | I71: =IFERROR(ROUND(H71*$I$16,0),"") | J71: =IFERROR((I71-H71)/I71,"")
B72: 288 processing paths where up to 128 can be output busses | G72: =IF(F72-F72*$G$16=0,"",F72-F72*$G$16) | H72: =IFERROR(G72*$H$16,"") | I72: =IFERROR(ROUND(H72*$I$16,0),"") | J72: =IFERROR((I72-H72)/I72,"")
B73: 2 mono or stereo solo busses. LR, LCR. LCRS or 5.1 master buss | G73: =IF(F73-F73*$G$16=0,"",F73-F73*$G$16) | H73: =IFERROR(G73*$H$16,"") | I73: =IFERROR(ROUND(H73*$I$16,0),"") | J73: =IFERROR((I73-H73)/I73,"")
B74: 48ch USB audio I/O, 36 x 36 matrix, 36 CG/VCA, 36 FX, 32 x 32 band graphic eq’s | G74: =IF(F74-F74*$G$16=0,"",F74-F74*$G$16) | H74: =IFERROR(G74*$H$16,"") | I74: =IFERROR(ROUND(H74*$I$16,0),"") | J74: =IFERROR((I74-H74)/I74,"")
B75: 128 Nodal Processors, 48 Mustard Processors, 12 Spice FX | G75: =IF(F75-F75*$G$16=0,"",F75-F75*$G$16) | H75: =IFERROR(G75*$H$16,"") | I75: =IFERROR(ROUND(H75*$I$16,0),"") | J75: =IFERROR((I75-H75)/I75,"")
B76: Upgrade also includes Gold Power Upgrade kit, comprising of upgraded power distribution board and power looms | G76: =IF(F76-F76*$G$16=0,"",F76-F76*$G$16) | H76: =IFERROR(G76*$H$16,"") | I76: =IFERROR(ROUND(H76*$I$16,0),"") | J76: =IFERROR((I76-H76)/I76,"")
G77: =IF(F77-F77*$G$16=0,"",F77-F77*$G$16) | H77: =IFERROR(G77*$H$16,"") | I77: =IFERROR(ROUND(H77*$I$16,0),"") | J77: =IFERROR((I77-H77)/I77,"")
A78: X-Q5-UP-NC | B78: DiGiCo SD5 surface upgrade to Quantum 5 spec - MADI / NC optics | E78: =ROUND(F78/0.55,0) -> 22592 | F78: 12425.5 | G78: =IF(F78-F78*$G$16=0,"",F78-F78*$G$16) -> 12425.5 | H78: =IFERROR(G78*$H$16,"") -> 1826548.5 | I78: =IFERROR(ROUND(H78*$I$16,0),"") -> 2593699 | J78: =IFERROR((I78-H78)/I78,"") -> 0.29577468
B79: Quantum 5 engine, NC optics, 2 DMI slots, USB Audio I/O, 8 BNC MADI, 2 PSU, 16 GPI/O | G79: =IF(F79-F79*$G$16=0,"",F79-F79*$G$16) | H79: =IFERROR(G79*$H$16,"") | I79: =IFERROR(ROUND(H79*$I$16,0),"") | J79: =IFERROR((I79-H79)/I79,"")
B80: 288 processing paths where up to 128 can be output busses | G80: =IF(F80-F80*$G$16=0,"",F80-F80*$G$16) | H80: =IFERROR(G80*$H$16,"") | I80: =IFERROR(ROUND(H80*$I$16,0),"") | J80: =IFERROR((I80-H80)/I80,"")
B81: 2 mono or stereo solo busses. LR, LCR. LCRS or 5.1 master buss | G81: =IF(F81-F81*$G$16=0,"",F81-F81*$G$16) | H81: =IFERROR(G81*$H$16,"") | I81: =IFERROR(ROUND(H81*$I$16,0),"") | J81: =IFERROR((I81-H81)/I81,"")
B82: 48ch USB audio I/O, 36 x 36 matrix, 36 CG/VCA, 36 FX, 32 x 32 band graphic eq’s | G82: =IF(F82-F82*$G$16=0,"",F82-F82*$G$16) | H82: =IFERROR(G82*$H$16,"") | I82: =IFERROR(ROUND(H82*$I$16,0),"") | J82: =IFERROR((I82-H82)/I82,"")
B83: 128 Nodal Processors, 48 Mustard Processors, 12 Spice FX | G83: =IF(F83-F83*$G$16=0,"",F83-F83*$G$16) | H83: =IFERROR(G83*$H$16,"") | I83: =IFERROR(ROUND(H83*$I$16,0),"") | J83: =IFERROR((I83-H83)/I83,"")
B84: Upgrade also includes Gold Power Upgrade kit, comprising of upgraded power distribution board and power looms | G84: =IF(F84-F84*$G$16=0,"",F84-F84*$G$16) | H84: =IFERROR(G84*$H$16,"") | I84: =IFERROR(ROUND(H84*$I$16,0),"") | J84: =IFERROR((I84-H84)/I84,"")
G85: =IF(F85-F85*$G$16=0,"",F85-F85*$G$16) | H85: =IFERROR(G85*$H$16,"") | I85: =IFERROR(ROUND(H85*$I$16,0),"") | J85: =IFERROR((I85-H85)/I85,"")
A86: X-Q5-UP-ST | B86: DiGiCo SD5 surface upgrade to Quantum 5 spec - MADI / ST optics | E86: =ROUND(F86/0.55,0) -> 22379 | F86: 12308.5 | G86: =IF(F86-F86*$G$16=0,"",F86-F86*$G$16) -> 12308.5 | H86: =IFERROR(G86*$H$16,"") -> 1809349.5 | I86: =IFERROR(ROUND(H86*$I$16,0),"") -> 2569276 | J86: =IFERROR((I86-H86)/I86,"") -> 0.29577457
B87: Quantum 5 engine, ST optics, 2 DMI slots, USB Audio I/O, 8 BNC MADI, 2 PSU, 16 GPI/O | G87: =IF(F87-F87*$G$16=0,"",F87-F87*$G$16) | H87: =IFERROR(G87*$H$16,"") | I87: =IFERROR(ROUND(H87*$I$16,0),"") | J87: =IFERROR((I87-H87)/I87,"")
B88: 288 processing paths where up to 128 can be output busses | G88: =IF(F88-F88*$G$16=0,"",F88-F88*$G$16) | H88: =IFERROR(G88*$H$16,"") | I88: =IFERROR(ROUND(H88*$I$16,0),"") | J88: =IFERROR((I88-H88)/I88,"")
B89: 2 mono or stereo solo busses. LR, LCR. LCRS or 5.1 master buss | G89: =IF(F89-F89*$G$16=0,"",F89-F89*$G$16) | H89: =IFERROR(G89*$H$16,"") | I89: =IFERROR(ROUND(H89*$I$16,0),"") | J89: =IFERROR((I89-H89)/I89,"")
B90: 48ch USB audio I/O, 36 x 36 matrix, 36 CG/VCA, 36 FX, 32 x 32 band graphic eq’s | G90: =IF(F90-F90*$G$16=0,"",F90-F90*$G$16) | H90: =IFERROR(G90*$H$16,"") | I90: =IFERROR(ROUND(H90*$I$16,0),"") | J90: =IFERROR((I90-H90)/I90,"")
B91: 128 Nodal Processors, 48 Mustard Processors, 12 Spice FX | G91: =IF(F91-F91*$G$16=0,"",F91-F91*$G$16) | H91: =IFERROR(G91*$H$16,"") | I91: =IFERROR(ROUND(H91*$I$16,0),"") | J91: =IFERROR((I91-H91)/I91,"")
B92: Upgrade also includes Gold Power Upgrade kit, comprising of upgraded power distribution board and power looms | G92: =IF(F92-F92*$G$16=0,"",F92-F92*$G$16) | H92: =IFERROR(G92*$H$16,"") | I92: =IFERROR(ROUND(H92*$I$16,0),"") | J92: =IFERROR((I92-H92)/I92,"")
G93: =IF(F93-F93*$G$16=0,"",F93-F93*$G$16) | H93: =IFERROR(G93*$H$16,"") | I93: =IFERROR(ROUND(H93*$I$16,0),"") | J93: =IFERROR((I93-H93)/I93,"")
A94: DiGiCo Quantum 5 / SD5 Surface Options | E94: =ROUND(F94/0.55,0) -> 0 | G94: =IF(F94-F94*$G$16=0,"",F94-F94*$G$16) | H94: =IFERROR(G94*$H$16,"") | I94: =IFERROR(ROUND(H94*$I$16,0),"") | J94: =IFERROR((I94-H94)/I94,"")
G95: =IF(F95-F95*$G$16=0,"",F95-F95*$G$16) | H95: =IFERROR(G95*$H$16,"") | I95: =IFERROR(ROUND(H95*$I$16,0),"") | J95: =IFERROR((I95-H95)/I95,"")
A96: MOD-Q5-OP-2 | B96: DiGiCo Quantum 5 second Optocore interface (HMA) | E96: =ROUND(F96/0.55,0) -> 7364 | F96: 4050 | G96: =IF(F96-F96*$G$16=0,"",F96-F96*$G$16) -> 4050 | H96: =IFERROR(G96*$H$16,"") -> 595350 | I96: =IFERROR(ROUND(H96*$I$16,0),"") -> 845397 | J96: =IFERROR((I96-H96)/I96,"") -> 0.29577465
B97: Factory fitted 2nd HMA Optocore Interface | G97: =IF(F97-F97*$G$16=0,"",F97-F97*$G$16) | H97: =IFERROR(G97*$H$16,"") | I97: =IFERROR(ROUND(H97*$I$16,0),"") | J97: =IFERROR((I97-H97)/I97,"")
G98: =IF(F98-F98*$G$16=0,"",F98-F98*$G$16) | H98: =IFERROR(G98*$H$16,"") | I98: =IFERROR(ROUND(H98*$I$16,0),"") | J98: =IFERROR((I98-H98)/I98,"")
A99: MOD-Q5-NC-2 | B99: DiGiCo Quantum 5 second Optocore interface (NC) | E99: =ROUND(F99/0.55,0) -> 6251 | F99: 3438 | G99: =IF(F99-F99*$G$16=0,"",F99-F99*$G$16) -> 3438 | H99: =IFERROR(G99*$H$16,"") -> 505386 | I99: =IFERROR(ROUND(H99*$I$16,0),"") -> 717648 | J99: =IFERROR((I99-H99)/I99,"") -> 0.29577453
B100: Factory fitted 2nd NC Optocore Interface | G100: =IF(F100-F100*$G$16=0,"",F100-F100*$G$16) | H100: =IFERROR(G100*$H$16,"") | I100: =IFERROR(ROUND(H100*$I$16,0),"") | J100: =IFERROR((I100-H100)/I100,"")
G101: =IF(F101-F101*$G$16=0,"",F101-F101*$G$16) | H101: =IFERROR(G101*$H$16,"") | I101: =IFERROR(ROUND(H101*$I$16,0),"") | J101: =IFERROR((I101-H101)/I101,"")
A102: MOD-Q5-ST-2 | B102: DiGiCo Quantum 5 second Optocore interface (ST) | E102: =ROUND(F102/0.55,0) -> 6038 | F102: 3321 | G102: =IF(F102-F102*$G$16=0,"",F102-F102*$G$16) -> 3321 | H102: =IFERROR(G102*$H$16,"") -> 488187 | I102: =IFERROR(ROUND(H102*$I$16,0),"") -> 693226 | J102: =IFERROR((I102-H102)/I102,"") -> 0.29577512
B103: Factory fitted 2nd ST Optocore Interface | G103: =IF(F103-F103*$G$16=0,"",F103-F103*$G$16) | H103: =IFERROR(G103*$H$16,"") | I103: =IFERROR(ROUND(H103*$I$16,0),"") | J103: =IFERROR((I103-H103)/I103,"")
G104: =IF(F104-F104*$G$16=0,"",F104-F104*$G$16) | H104: =IFERROR(G104*$H$16,"") | I104: =IFERROR(ROUND(H104*$I$16,0),"") | J104: =IFERROR((I104-H104)/I104,"")
A105: MOD-FOURIER-Q5 | B105: DiGiCo Quantum 5 Fourier Audio interface card | E105: =ROUND(F105/0.55,0) -> 1864 | F105: 1025 | G105: =IF(F105-F105*$G$16=0,"",F105-F105*$G$16) -> 1025 | H105: =IFERROR(G105*$H$16,"") -> 150675 | I105: =IFERROR(ROUND(H105*$I$16,0),"") -> 213959 | J105: =IFERROR((I105-H105)/I105,"") -> 0.29577629
...

Sheet Q7
B1: DiGiCo Quantum 7 Distributor Price List
B3: Sept 2024
B5: Unit 10 Silverglade Business Park, Leatherhead Road
B6: Chessington, Surrey, KT9 2QL
B7: Tel; +44 1372 845600
B8: Fax; +44 1372 845656
B9: email; sales@digiconsoles.com
B10: web; www.digiconsoles.com
B12: FCA Glenrothes KY7 4NX. E&OE. Prices, Products and Specification are subject to change without notice.
B13: This price list supercedes all previous price lists.
A15: Product Code | B15: Description | E15: List (£) | F15: Distributor (£) | G15: Disc. | H15: HT Buy (INR) | I15: Customer Price | J15: Hi-Tech
G16: 0 | H16: 147 | I16: 1.42 | J16: Margin
A17: DiGiCo Quantum 7 32bit System
B19: DiGiCo Quantum 7 32bit touring system | E19: =ROUND(F19/0.55,0) -> 180299 | F19: 99164.5 | G19: =IF(F19-F19*$G$16=0,"",F19-F19*$G$16) -> 99164.5 | H19: =IFERROR(G19*$H$16,"") -> 14577182 | I19: =IFERROR(ROUND(H19*$I$16,0),"") -> 20699598 | J19: =IFERROR((I19-H19)/I19,"") -> 0.29577466
B20: 1 x Quantum 7 surface - 36+2 100mm faders, 12+2 60mm faders, 2 quantum engines, HMA optics, 2 DMI slots, 8 BNC MADI, 2 PSU, 16 GPI/O | G20: =IF(F20-F20*$G$16=0,"",F20-F20*$G$16) | H20: =IFERROR(G20*$H$16,"") | I20: =IFERROR(ROUND(H20*$I$16,0),"") | J20: =IFERROR((I20-H20)/I20,"")
B21: 256 input channels, 128 output busses, 2 mono or stereo solo busses. LR, LCR, LCRS or 5.1 master buss | G21: =IF(F21-F21*$G$16=0,"",F21-F21*$G$16) | H21: =IFERROR(G21*$H$16,"") | I21: =IFERROR(ROUND(H21*$I$16,0),"") | J21: =IFERROR((I21-H21)/I21,"")
B22: 48ch USB audio IO, 64ch plugin I/O option (Fourier or Dante), 48 x 48 matrix, 36 CG/VCA, 48 FX, 48 x 32 band graphic eq’s, | G22: =IF(F22-F22*$G$16=0,"",F22-F22*$G$16) | H22: =IFERROR(G22*$H$16,"") | I22: =IFERROR(ROUND(H22*$I$16,0),"") | J22: =IFERROR((I22-H22)/I22,"")
B23: 256 Nodal Processors, 80 Mustard Processors, 16 Spice FX | G23: =IF(F23-F23*$G$16=0,"",F23-F23*$G$16) | H23: =IFERROR(G23*$H$16,"") | I23: =IFERROR(ROUND(H23*$I$16,0),"") | J23: =IFERROR((I23-H23)/I23,"")
B24: Local I/O 12 x Mic inputs, 12 x Line outputs, 12 x AES I/O mono stream, dust cover | G24: =IF(F24-F24*$G$16=0,"",F24-F24*$G$16) | H24: =IFERROR(G24*$H$16,"") | I24: =IFERROR(ROUND(H24*$I$16,0),"") | J24: =IFERROR((I24-H24)/I24,"")
B25: 1 x Stage SD-Rack, HMA optics, 2 BNC MADI, dual PSU - 56 32bit mic/line in / 40 32bit line out / 16 AES outputs | G25: =IF(F25-F25*$G$16=0,"",F25-F25*$G$16) | H25: =IFERROR(G25*$H$16,"") | I25: =IFERROR(ROUND(H25*$I$16,0),"") | J25: =IFERROR((I25-H25)/I25,"")
B26: 2 x 150m optical cable on drum | G26: =IF(F26-F26*$G$16=0,"",F26-F26*$G$16) | H26: =IFERROR(G26*$H$16,"") | I26: =IFERROR(ROUND(H26*$I$16,0),"") | J26: =IFERROR((I26-H26)/I26,"")
B27: 1 x Touring surface flight case | G27: =IF(F27-F27*$G$16=0,"",F27-F27*$G$16) | H27: =IFERROR(G27*$H$16,"") | I27: =IFERROR(ROUND(H27*$I$16,0),"") | J27: =IFERROR((I27-H27)/I27,"")
G28: =IF(F28-F28*$G$16=0,"",F28-F28*$G$16) | H28: =IFERROR(G28*$H$16,"") | I28: =IFERROR(ROUND(H28*$I$16,0),"") | J28: =IFERROR((I28-H28)/I28,"")
A29: DiGiCo Quantum 7 Surface | G29: =IF(F29-F29*$G$16=0,"",F29-F29*$G$16) | H29: =IFERROR(G29*$H$16,"") | I29: =IFERROR(ROUND(H29*$I$16,0),"") | J29: =IFERROR((I29-H29)/I29,"")
G30: =IF(F30-F30*$G$16=0,"",F30-F30*$G$16) | H30: =IFERROR(G30*$H$16,"") | I30: =IFERROR(ROUND(H30*$I$16,0),"") | J30: =IFERROR((I30-H30)/I30,"")
A31: X-SD7-Q7-OP | B31: DiGiCo Quantum 7 surface - MADI / HMA optics | E31: =ROUND(F31/0.55,0) -> 144497 | F31: 79473.125 | G31: =IF(F31-F31*$G$16=0,"",F31-F31*$G$16) -> 79473.125 | H31: =IFERROR(G31*$H$16,"") -> 11682549 | I31: =IFERROR(ROUND(H31*$I$16,0),"") -> 16589220 | J31: =IFERROR((I31-H31)/I31,"") -> 0.29577464
B32: Quantum 7 surface - 36+2 100mm faders, 12+2 60mm faders, 2 quantum engines, HMA optics, 2 DMI slots, 8 BNC MADI, 2 PSU, 16 GPI/O | G32: =IF(F32-F32*$G$16=0,"",F32-F32*$G$16) | H32: =IFERROR(G32*$H$16,"") | I32: =IFERROR(ROUND(H32*$I$16,0),"") | J32: =IFERROR((I32-H32)/I32,"")
B33: 256 input channels, 128 output busses, 2 mono or stereo solo busses. LR, LCR, LCRS or 5.1 master buss | G33: =IF(F33-F33*$G$16=0,"",F33-F33*$G$16) | H33: =IFERROR(G33*$H$16,"") | I33: =IFERROR(ROUND(H33*$I$16,0),"") | J33: =IFERROR((I33-H33)/I33,"")
B34: USB audio IO, 48 x 48 matrix, 36 CG/VCA, 48 FX, 48 x 32 band graphic eq’s | G34: =IF(F34-F34*$G$16=0,"",F34-F34*$G$16) | H34: =IFERROR(G34*$H$16,"") | I34: =IFERROR(ROUND(H34*$I$16,0),"") | J34: =IFERROR((I34-H34)/I34,"")
B35: 256 Nodal Processors, 80 Mustard Processors, 16 Spice FX | G35: =IF(F35-F35*$G$16=0,"",F35-F35*$G$16) | H35: =IFERROR(G35*$H$16,"") | I35: =IFERROR(ROUND(H35*$I$16,0),"") | J35: =IFERROR((I35-H35)/I35,"")
B36: Local I/O 12 x Mic inputs, 12 x Line outputs, 12 x AES I/O mono stream, dust cover | G36: =IF(F36-F36*$G$16=0,"",F36-F36*$G$16) | H36: =IFERROR(G36*$H$16,"") | I36: =IFERROR(ROUND(H36*$I$16,0),"") | J36: =IFERROR((I36-H36)/I36,"")
B37: Dimensions; 1496(w) x 875(d) x 503(h) mm Weight; 107Kg | G37: =IF(F37-F37*$G$16=0,"",F37-F37*$G$16) | H37: =IFERROR(G37*$H$16,"") | I37: =IFERROR(ROUND(H37*$I$16,0),"") | J37: =IFERROR((I37-H37)/I37,"")
G38: =IF(F38-F38*$G$16=0,"",F38-F38*$G$16) | H38: =IFERROR(G38*$H$16,"") | I38: =IFERROR(ROUND(H38*$I$16,0),"") | J38: =IFERROR((I38-H38)/I38,"")
A39: X-SD7-Q7-NC | B39: DiGiCo Quantum 7 surface - MADI / NC optics | E39: =ROUND(F39/0.55,0) -> 142271 | F39: 78249.125 | G39: =IF(F39-F39*$G$16=0,"",F39-F39*$G$16) -> 78249.125 | H39: =IFERROR(G39*$H$16,"") -> 11502621 | I39: =IFERROR(ROUND(H39*$I$16,0),"") -> 16333722 | J39: =IFERROR((I39-H39)/I39,"") -> 0.29577463
B40: Quantum 7 surface - 36+2 100mm faders, 12+2 60mm faders, 2 quantum engines, NC optics, 2 DMI slots, 8 BNC MADI, 2 PSU, 16 GPI/O | G40: =IF(F40-F40*$G$16=0,"",F40-F40*$G$16) | H40: =IFERROR(G40*$H$16,"") | I40: =IFERROR(ROUND(H40*$I$16,0),"") | J40: =IFERROR((I40-H40)/I40,"")
B41: 256 input channels, 128 output busses, 2 mono or stereo solo busses. LR, LCR, LCRS or 5.1 master buss | G41: =IF(F41-F41*$G$16=0,"",F41-F41*$G$16) | H41: =IFERROR(G41*$H$16,"") | I41: =IFERROR(ROUND(H41*$I$16,0),"") | J41: =IFERROR((I41-H41)/I41,"")
B42: USB audio IO, 48 x 48 matrix, 36 CG/VCA, 48 FX, 48 x 32 band graphic eq’s | G42: =IF(F42-F42*$G$16=0,"",F42-F42*$G$16) | H42: =IFERROR(G42*$H$16,"") | I42: =IFERROR(ROUND(H42*$I$16,0),"") | J42: =IFERROR((I42-H42)/I42,"")
B43: 256 Nodal Processors, 80 Mustard Processors, 16 Spice FX | G43: =IF(F43-F43*$G$16=0,"",F43-F43*$G$16) | H43: =IFERROR(G43*$H$16,"") | I43: =IFERROR(ROUND(H43*$I$16,0),"") | J43: =IFERROR((I43-H43)/I43,"")
B44: Local I/O 12 x Mic inputs, 12 x Line outputs, 12 x AES I/O mono stream, dust cover | G44: =IF(F44-F44*$G$16=0,"",F44-F44*$G$16) | H44: =IFERROR(G44*$H$16,"") | I44: =IFERROR(ROUND(H44*$I$16,0),"") | J44: =IFERROR((I44-H44)/I44,"")
B45: Dimensions; 1496(w) x 875(d) x 503(h) mm Weight; 107Kg | G45: =IF(F45-F45*$G$16=0,"",F45-F45*$G$16) | H45: =IFERROR(G45*$H$16,"") | I45: =IFERROR(ROUND(H45*$I$16,0),"") | J45: =IFERROR((I45-H45)/I45,"")
G46: =IF(F46-F46*$G$16=0,"",F46-F46*$G$16) | H46: =IFERROR(G46*$H$16,"") | I46: =IFERROR(ROUND(H46*$I$16,0),"") | J46: =IFERROR((I46-H46)/I46,"")
A47: X-SD7-Q7-ST | B47: DiGiCo Quantum 7 surface - MADI / ST optics | E47: =ROUND(F47/0.55,0) -> 141846 | F47: 78015.125 | G47: =IF(F47-F47*$G$16=0,"",F47-F47*$G$16) -> 78015.125 | H47: =IFERROR(G47*$H$16,"") -> 11468223 | I47: =IFERROR(ROUND(H47*$I$16,0),"") -> 16284877 | J47: =IFERROR((I47-H47)/I47,"") -> 0.29577464
B48: Quantum 7 surface - 36+2 100mm faders, 12+2 60mm faders, 2 quantum engines, ST optics, 2 DMI slots, 8 BNC MADI, 2 PSU, 16 GPI/O | G48: =IF(F48-F48*$G$16=0,"",F48-F48*$G$16) | H48: =IFERROR(G48*$H$16,"") | I48: =IFERROR(ROUND(H48*$I$16,0),"") | J48: =IFERROR((I48-H48)/I48,"")
B49: 256 input channels, 128 output busses, 2 mono or stereo solo busses. LR, LCR, LCRS or 5.1 master buss | G49: =IF(F49-F49*$G$16=0,"",F49-F49*$G$16) | H49: =IFERROR(G49*$H$16,"") | I49: =IFERROR(ROUND(H49*$I$16,0),"") | J49: =IFERROR((I49-H49)/I49,"")
B50: USB audio IO, 48 x 48 matrix, 36 CG/VCA, 48 FX, 48 x 32 band graphic eq’s | G50: =IF(F50-F50*$G$16=0,"",F50-F50*$G$16) | H50: =IFERROR(G50*$H$16,"") | I50: =IFERROR(ROUND(H50*$I$16,0),"") | J50: =IFERROR((I50-H50)/I50,"")
B51: 256 Nodal Processors, 80 Mustard Processors, 16 Spice FX | G51: =IF(F51-F51*$G$16=0,"",F51-F51*$G$16) | H51: =IFERROR(G51*$H$16,"") | I51: =IFERROR(ROUND(H51*$I$16,0),"") | J51: =IFERROR((I51-H51)/I51,"")
B52: Local I/O 12 x Mic inputs, 12 x Line outputs, 12 x AES I/O mono stream, dust cover | G52: =IF(F52-F52*$G$16=0,"",F52-F52*$G$16) | H52: =IFERROR(G52*$H$16,"") | I52: =IFERROR(ROUND(H52*$I$16,0),"") | J52: =IFERROR((I52-H52)/I52,"")
B53: Dimensions; 1496(w) x 875(d) x 503(h) mm Weight; 107Kg | G53: =IF(F53-F53*$G$16=0,"",F53-F53*$G$16) | H53: =IFERROR(G53*$H$16,"") | I53: =IFERROR(ROUND(H53*$I$16,0),"") | J53: =IFERROR((I53-H53)/I53,"")
G54: =IF(F54-F54*$G$16=0,"",F54-F54*$G$16) | H54: =IFERROR(G54*$H$16,"") | I54: =IFERROR(ROUND(H54*$I$16,0),"") | J54: =IFERROR((I54-H54)/I54,"")
A55: DiGiCo SD7 Surface Upgrade to Quantum 7 Specification - Trade in Existing Engines | G55: =IF(F55-F55*$G$16=0,"",F55-F55*$G$16) | H55: =IFERROR(G55*$H$16,"") | I55: =IFERROR(ROUND(H55*$I$16,0),"") | J55: =IFERROR((I55-H55)/I55,"")
G56: =IF(F56-F56*$G$16=0,"",F56-F56*$G$16) | H56: =IFERROR(G56*$H$16,"") | I56: =IFERROR(ROUND(H56*$I$16,0),"") | J56: =IFERROR((I56-H56)/I56,"")
A57: X-Q7-UP-OP | B57: DiGiCo SD7 surface upgrade to Quantum 7 Spec - MADI / HMA optics | E57: =ROUND(F57/0.55,0) -> 47409 | F57: 26075 | G57: =IF(F57-F57*$G$16=0,"",F57-F57*$G$16) -> 26075 | H57: =IFERROR(G57*$H$16,"") -> 3833025 | I57: =IFERROR(ROUND(H57*$I$16,0),"") -> 5442896 | J57: =IFERROR((I57-H57)/I57,"") -> 0.29577471
B58: Includes two Quantum 7 engines, HMA optics, 2 DMI slots, 8 BNC MADI | G58: =IF(F58-F58*$G$16=0,"",F58-F58*$G$16) | H58: =IFERROR(G58*$H$16,"") | I58: =IFERROR(ROUND(H58*$I$16,0),"") | J58: =IFERROR((I58-H58)/I58,"")
B59: 256 input channels, 128 output busses, 2 mono or stereo solo busses. LR, LCR, LCRS or 5.1 master buss | G59: =IF(F59-F59*$G$16=0,"",F59-F59*$G$16) | H59: =IFERROR(G59*$H$16,"") | I59: =IFERROR(ROUND(H59*$I$16,0),"") | J59: =IFERROR((I59-H59)/I59,"")
B60: USB audio IO, 48 x 48 matrix, 36 CG/VCA, 48 FX, 48 x 32 band graphic eq’s | G60: =IF(F60-F60*$G$16=0,"",F60-F60*$G$16) | H60: =IFERROR(G60*$H$16,"") | I60: =IFERROR(ROUND(H60*$I$16,0),"") | J60: =IFERROR((I60-H60)/I60,"")
B61: 256 Nodal Processors, 80 Mustard Processors, 16 Spice FX | G61: =IF(F61-F61*$G$16=0,"",F61-F61*$G$16) | H61: =IFERROR(G61*$H$16,"") | I61: =IFERROR(ROUND(H61*$I$16,0),"") | J61: =IFERROR((I61-H61)/I61,"")
B62: Upgrade also includes Gold Power Upgrade kit, comprising of upgraded power distribution board, power looms and USB cable. | G62: =IF(F62-F62*$G$16=0,"",F62-F62*$G$16) | H62: =IFERROR(G62*$H$16,"") | I62: =IFERROR(ROUND(H62*$I$16,0),"") | J62: =IFERROR((I62-H62)/I62,"")
G63: =IF(F63-F63*$G$16=0,"",F63-F63*$G$16) | H63: =IFERROR(G63*$H$16,"") | I63: =IFERROR(ROUND(H63*$I$16,0),"") | J63: =IFERROR((I63-H63)/I63,"")
A64: X-Q7-UP-NC | B64: DiGiCo SD7 surface upgrade to Quantum 7 Spec - MADI / NC optics | E64: =ROUND(F64/0.55,0) -> 45184 | F64: 24851 | G64: =IF(F64-F64*$G$16=0,"",F64-F64*$G$16) -> 24851 | H64: =IFERROR(G64*$H$16,"") -> 3653097 | I64: =IFERROR(ROUND(H64*$I$16,0),"") -> 5187398 | J64: =IFERROR((I64-H64)/I64,"") -> 0.29577468
B65: Includes two Quantum 7 engines, NC optics, 2 DMI slots, 8 BNC MADI | G65: =IF(F65-F65*$G$16=0,"",F65-F65*$G$16) | H65: =IFERROR(G65*$H$16,"") | I65: =IFERROR(ROUND(H65*$I$16,0),"") | J65: =IFERROR((I65-H65)/I65,"")
B66: 256 input channels, 128 output busses, 2 mono or stereo solo busses. LR, LCR, LCRS or 5.1 master buss | G66: =IF(F66-F66*$G$16=0,"",F66-F66*$G$16) | H66: =IFERROR(G66*$H$16,"") | I66: =IFERROR(ROUND(H66*$I$16,0),"") | J66: =IFERROR((I66-H66)/I66,"")
B67: USB audio IO, 48 x 48 matrix, 36 CG/VCA, 48 FX, 48 x 32 band graphic eq’s | G67: =IF(F67-F67*$G$16=0,"",F67-F67*$G$16) | H67: =IFERROR(G67*$H$16,"") | I67: =IFERROR(ROUND(H67*$I$16,0),"") | J67: =IFERROR((I67-H67)/I67,"")
B68: 256 Nodal Processors, 80 Mustard Processors, 16 Spice FX | G68: =IF(F68-F68*$G$16=0,"",F68-F68*$G$16) | H68: =IFERROR(G68*$H$16,"") | I68: =IFERROR(ROUND(H68*$I$16,0),"") | J68: =IFERROR((I68-H68)/I68,"")
B69: Upgrade also includes Gold Power Upgrade kit, comprising of upgraded power distribution board, power looms and USB cable. | G69: =IF(F69-F69*$G$16=0,"",F69-F69*$G$16) | H69: =IFERROR(G69*$H$16,"") | I69: =IFERROR(ROUND(H69*$I$16,0),"") | J69: =IFERROR((I69-H69)/I69,"")
G70: =IF(F70-F70*$G$16=0,"",F70-F70*$G$16) | H70: =IFERROR(G70*$H$16,"") | I70: =IFERROR(ROUND(H70*$I$16,0),"") | J70: =IFERROR((I70-H70)/I70,"")
A71: X-Q7-UP-ST | B71: DiGiCo SD7 surface upgrade to Quantum 7 Spec - MADI / ST optics | E71: =ROUND(F71/0.55,0) -> 44758 | F71: 24617 | G71: =IF(F71-F71*$G$16=0,"",F71-F71*$G$16) -> 24617 | H71: =IFERROR(G71*$H$16,"") -> 3618699 | I71: =IFERROR(ROUND(H71*$I$16,0),"") -> 5138553 | J71: =IFERROR((I71-H71)/I71,"") -> 0.29577471
B72: Includes two Quantum 7 engines, ST optics, 2 DMI slots, 8 BNC MADI | G72: =IF(F72-F72*$G$16=0,"",F72-F72*$G$16) | H72: =IFERROR(G72*$H$16,"") | I72: =IFERROR(ROUND(H72*$I$16,0),"") | J72: =IFERROR((I72-H72)/I72,"")
B73: 256 input channels, 128 output busses, 2 mono or stereo solo busses. LR, LCR, LCRS or 5.1 master buss | G73: =IF(F73-F73*$G$16=0,"",F73-F73*$G$16) | H73: =IFERROR(G73*$H$16,"") | I73: =IFERROR(ROUND(H73*$I$16,0),"") | J73: =IFERROR((I73-H73)/I73,"")
B74: USB audio IO, 48 x 48 matrix, 36 CG/VCA, 48 FX, 48 x 32 band graphic eq’s | G74: =IF(F74-F74*$G$16=0,"",F74-F74*$G$16) | H74: =IFERROR(G74*$H$16,"") | I74: =IFERROR(ROUND(H74*$I$16,0),"") | J74: =IFERROR((I74-H74)/I74,"")
B75: 256 Nodal Processors, 80 Mustard Processors, 16 Spice FX | G75: =IF(F75-F75*$G$16=0,"",F75-F75*$G$16) | H75: =IFERROR(G75*$H$16,"") | I75: =IFERROR(ROUND(H75*$I$16,0),"") | J75: =IFERROR((I75-H75)/I75,"")
B76: Upgrade also includes Gold Power Upgrade kit, comprising of upgraded power distribution board, power looms and USB cable. | G76: =IF(F76-F76*$G$16=0,"",F76-F76*$G$16) | H76: =IFERROR(G76*$H$16,"") | I76: =IFERROR(ROUND(H76*$I$16,0),"") | J76: =IFERROR((I76-H76)/I76,"")
G77: =IF(F77-F77*$G$16=0,"",F77-F77*$G$16) | H77: =IFERROR(G77*$H$16,"") | I77: =IFERROR(ROUND(H77*$I$16,0),"") | J77: =IFERROR((I77-H77)/I77,"")
A78: DiGiCo Quantum 7 / SD7 Surface Options | G78: =IF(F78-F78*$G$16=0,"",F78-F78*$G$16) | H78: =IFERROR(G78*$H$16,"") | I78: =IFERROR(ROUND(H78*$I$16,0),"") | J78: =IFERROR((I78-H78)/I78,"")
G79: =IF(F79-F79*$G$16=0,"",F79-F79*$G$16) | H79: =IFERROR(G79*$H$16,"") | I79: =IFERROR(ROUND(H79*$I$16,0),"") | J79: =IFERROR((I79-H79)/I79,"")
A80: MOD-Q7-OP-2 | B80: DiGiCo Quantum 7 second Optocore interface (HMA) | E80: =ROUND(F80/0.55,0) -> 7364 | F80: 4050 | G80: =IF(F80-F80*$G$16=0,"",F80-F80*$G$16) -> 4050 | H80: =IFERROR(G80*$H$16,"") -> 595350 | I80: =IFERROR(ROUND(H80*$I$16,0),"") -> 845397 | J80: =IFERROR((I80-H80)/I80,"") -> 0.29577465
B81: Factory fitted 2nd HMA Optocore Interface. Two required for dual engined surface. | G81: =IF(F81-F81*$G$16=0,"",F81-F81*$G$16) | H81: =IFERROR(G81*$H$16,"") | I81: =IFERROR(ROUND(H81*$I$16,0),"") | J81: =IFERROR((I81-H81)/I81,"")
G82: =IF(F82-F82*$G$16=0,"",F82-F82*$G$16) | H82: =IFERROR(G82*$H$16,"") | I82: =IFERROR(ROUND(H82*$I$16,0),"") | J82: =IFERROR((I82-H82)/I82,"")
A83: MOD-Q7-NC-2 | B83: DiGiCo Quantum 7 second Pptocore interface (NC) | E83: =ROUND(F83/0.55,0) -> 6251 | F83: 3438 | G83: =IF(F83-F83*$G$16=0,"",F83-F83*$G$16) -> 3438 | H83: =IFERROR(G83*$H$16,"") -> 505386 | I83: =IFERROR(ROUND(H83*$I$16,0),"") -> 717648 | J83: =IFERROR((I83-H83)/I83,"") -> 0.29577453
B84: Factory fitted 2nd NC Optocore Interface. Two required for dual engined surface. | G84: =IF(F84-F84*$G$16=0,"",F84-F84*$G$16) | H84: =IFERROR(G84*$H$16,"") | I84: =IFERROR(ROUND(H84*$I$16,0),"") | J84: =IFERROR((I84-H84)/I84,"")
G85: =IF(F85-F85*$G$16=0,"",F85-F85*$G$16) | H85: =IFERROR(G85*$H$16,"") | I85: =IFERROR(ROUND(H85*$I$16,0),"") | J85: =IFERROR((I85-H85)/I85,"")
A86: MOD-Q7-ST-2 | B86: DiGiCo Quantum 7 second Optocore interface (ST) | E86: =ROUND(F86/0.55,0) -> 6038 | F86: 3321 | G86: =IF(F86-F86*$G$16=0,"",F86-F86*$G$16) -> 3321 | H86: =IFERROR(G86*$H$16,"") -> 488187 | I86: =IFERROR(ROUND(H86*$I$16,0),"") -> 693226 | J86: =IFERROR((I86-H86)/I86,"") -> 0.29577512
B87: Factory fitted 2nd ST Optocore Interface. Two required for dual engined surface. | G87: =IF(F87-F87*$G$16=0,"",F87-F87*$G$16) | H87: =IFERROR(G87*$H$16,"") | I87: =IFERROR(ROUND(H87*$I$16,0),"") | J87: =IFERROR((I87-H87)/I87,"")
G88: =IF(F88-F88*$G$16=0,"",F88-F88*$G$16) | H88: =IFERROR(G88*$H$16,"") | I88: =IFERROR(ROUND(H88*$I$16,0),"") | J88: =IFERROR((I88-H88)/I88,"")
A89: X-SD7-SCRIPT | B89: DiGiCo Quantum 7 / SD7 script tray | E89: =ROUND(F89/0.55,0) -> 1113 | F89: 612 | G89: =IF(F89-F89*$G$16=0,"",F89-F89*$G$16) -> 612 | H89: =IFERROR(G89*$H$16,"") -> 89964 | I89: =IFERROR(ROUND(H89*$I$16,0),"") -> 127749 | J89: =IFERROR((I89-H89)/I89,"") -> 0.29577531
B90: Transparent Script tray for SD7 surface | G90: =IF(F90-F90*$G$16=0,"",F90-F90*$G$16) | H90: =IFERROR(G90*$H$16,"") | I90: =IFERROR(ROUND(H90*$I$16,0),"") | J90: =IFERROR((I90-H90)/I90,"")
G91: =IF(F91-F91*$G$16=0,"",F91-F91*$G$16) | H91: =IFERROR(G91*$H$16,"") | I91: =IFERROR(ROUND(H91*$I$16,0),"") | J91: =IFERROR((I91-H91)/I91,"")
A92: MOD-FOURIER-Q7 | B92: DiGiCo Quantum 7 Fourier Audio interface card | E92: =ROUND(F92/0.55,0) -> 1864 | F92: 1025 | G92: =IF(F92-F92*$G$16=0,"",F92-F92*$G$16) -> 1025 | H92: =IFERROR(G92*$H$16,"") -> 150675 | I92: =IFERROR(ROUND(H92*$I$16,0),"") -> 213959 | J92: =IFERROR((I92-H92)/I92,"") -> 0.29577629
B93: Fourier Audio interface card. 64ch Dante I/O. 3 x RJ45. Two required for dual engined surface | G93: =IF(F93-F93*$G$16=0,"",F93-F93*$G$16) | H93: =IFERROR(G93*$H$16,"") | I93: =IFERROR(ROUND(H93*$I$16,0),"") | J93: =IFERROR((I93-H93)/I93,"")
G94: =IF(F94-F94*$G$16=0,"",F94-F94*$G$16) | H94: =IFERROR(G94*$H$16,"") | I94: =IFERROR(ROUND(H94*$I$16,0),"") | J94: =IFERROR((I94-H94)/I94,"")
A95: MOD-WAVES-Q7 | B95: DiGiCo Quantum 7 Waves upgrade kit | E95: =ROUND(F95/0.55,0) -> 1864 | F95: 1025 | G95: =IF(F95-F95*$G$16=0,"",F95-F95*$G$16) -> 1025 | H95: =IFERROR(G95*$H$16,"") -> 150675 | I95: =IFERROR(ROUND(H95*$I$16,0),"") -> 213959 | J95: =IFERROR((I95-H95)/I95,"") -> 0.29577629
B96: Waves interface card. 64ch Soundgrid I/O. RJ45. Two required for dual engined surface | G96: =IF(F96-F96*$G$16=0,"",F96-F96*$G$16) | H96: =IFERROR(G96*$H$16,"") | I96: =IFERROR(ROUND(H96*$I$16,0),"") | J96: =IFERROR((I96-H96)/I96,"")
G97: =IF(F97-F97*$G$16=0,"",F97-F97*$G$16) | H97: =IFERROR(G97*$H$16,"") | I97: =IFERROR(ROUND(H97*$I$16,0),"") | J97: =IFERROR((I97-H97)/I97,"")
A98: X-SD7-TUPG | B98: DiGiCo Quantum 7 / SD7 T theatre-specific application software | E98: =ROUND(F98/0.55,0) -> 14545 | F98: 8000 | G98: =IF(F98-F98*$G$16=0,"",F98-F98*$G$16) -> 8000 | H98: =IFERROR(G98*$H$16,"") -> 1176000 | I98: =IFERROR(ROUND(H98*$I$16,0),"") -> 1669920 | J98: =IFERROR((I98-H98)/I98,"") -> 0.29577465
B99: Extensive Theatre specific software including - Auto Update, Cue Editor, Matrix nodal delay. | G99: =IF(F99-F99*$G$16=0,"",F99-F99*$G$16) | H99: =IFERROR(G99*$H$16,"") | I99: =IFERROR(ROUND(H99*$I$16,0),"") | J99: =IFERROR((I99-H99)/I99,"")
G100: =IF(F100-F100*$G$16=0,"",F100-F100*$G$16) | H100: =IFERROR(G100*$H$16,"") | I100: =IFERROR(ROUND(H100*$I$16,0),"") | J100: =IFERROR((I100-H100)/I100,"")
A101: X-SD7-BUPG | B101: DiGiCo Quantum 7 / SD7 B broadcast-specific application software | E101: =ROUND(F101/0.55,0) -> 7796 | F101: 4288 | G101: =IF(F101-F101*$G$16=0,"",F101-F101*$G$16) -> 4288 | H101: =IFERROR(G101*$H$16,"") -> 630336 | I101: =IFERROR(ROUND(H101*$I$16,0),"") -> 895077 | J101: =IFERROR((I101-H101)/I101,"") -> 0.29577455
B102: Adds Mix-minus output per channel, Buss Down/Up Mix, Talk to Buss, | G102: =IF(F102-F102*$G$16=0,"",F102-F102*$G$16) | H102: =IFERROR(G102*$H$16,"") | I102: =IFERROR(ROUND(H102*$I$16,0),"") | J102: =IFERROR((I102-H102)/I102,"")
B103: Backstop PFL and Auto PFL, 12 source Monitor matrix, 3 Speaker select | G103: =IF(F103-F103*$G$16=0,"",F103-F103*$G$16) | H103: =IFERROR(G103*$H$16,"") | I103: =IFERROR(ROUND(H103*$I$16,0),"") | J103: =IFERROR((I103-H103)/I103,"")
G104: =IF(F104-F104*$G$16=0,"",F104-F104*$G$16) | H104: =IFERROR(G104*$H$16,"") | I104: =IFERROR(ROUND(H104*$I$16,0),"") | J104: =IFERROR((I104-H104)/I104,"")
A105: X-SD7Q-EXP | B105: DiGiCo EX007 Quantum 7 fader expander | E105: =ROUND(F105/0.55,0) -> 40909 | F105: 22500 | G105: =IF(F105-F105*$G$16=0,"",F105-F105*$G$16) -> 22500 | H105: =IFERROR(G105*$H$16,"") -> 3307500 | I105: =IFERROR(ROUND(H105*$I$16,0),"") -> 4696650 | J105: =IFERROR((I105-H105)/I105,"") -> 0.29577465
...

Sheet SD 9
B1: DiGiCo SD9 Distributor Price List
B3: Sept 2024
B5: Unit 10 Silverglade Business Park, Leatherhead Road
B6: Chessington, Surrey, KT9 2QL
B7: Tel; +44 1372 845600
B8: Fax; +44 1372 845656
B9: email; sales@digiconsoles.com
B10: web; www.digiconsoles.com
B12: FCA Glenrothes KY7 4NX. E&OE. Prices, Products and Specification are subject to change without notice.
B13: This price list supercedes all previous price lists.
A15: Product Code | B15: Description | E15: List (£) | F15: Distributor (£) | G15: Disc. () | H15: HT Buy (INR) | I15: Customer Price | J15: Hi-Tech
G16: 0.2 | H16: 147 | I16: 1.42 | J16: Margin
A17: DiGiCo SD9 Systems
A19: X-SD9-1P | B19: DiGiCo SD9 system - single power supply | E19: =ROUND(F19/0.55,0) -> 19147 | F19: 10531 | G19: =IF(F19-F19*$G$16=0,"",F19-F19*$G$16) -> 8424.8 | H19: =IFERROR(G19*$H$16,"") -> 1238445.6 | I19: =IFERROR(ROUND(H19*$I$16,0),"") -> 1758593 | J19: =IFERROR((I19-H19)/I19,"") -> 0.29577475
B20: 1 x SD9 surface - 24 faders, 2 etherCON MADI, 1 BNC MADI, 1 PSU, 2 GPIO | G20: =IF(F20-F20*$G$16=0,"",F20-F20*$G$16) | H20: =IFERROR(G20*$H$16,"") | I20: =IFERROR(ROUND(H20*$I$16,0),"") | J20: =IFERROR((I20-H20)/I20,"")
B21: 96 mono input channels, 48 mono output busses | G21: =IF(F21-F21*$G$16=0,"",F21-F21*$G$16) | H21: =IFERROR(G21*$H$16,"") | I21: =IFERROR(ROUND(H21*$I$16,0),"") | J21: =IFERROR((I21-H21)/I21,"")
B22: 2 mono or stereo solo busses, 1 stereo or LCR master buss | G22: =IF(F22-F22*$G$16=0,"",F22-F22*$G$16) | H22: =IFERROR(G22*$H$16,"") | I22: =IFERROR(ROUND(H22*$I$16,0),"") | J22: =IFERROR((I22-H22)/I22,"")
B23: 12 x 8 matrix, 12 CG/VCA, 12 FX, 16 x 32 band graphic eq’s | G23: =IF(F23-F23*$G$16=0,"",F23-F23*$G$16) | H23: =IFERROR(G23*$H$16,"") | I23: =IFERROR(ROUND(H23*$I$16,0),"") | J23: =IFERROR((I23-H23)/I23,"")
B24: Local I/O 8x Mic/Line inputs, 8x Line outputs, 4x AES I/O mono stream | G24: =IF(F24-F24*$G$16=0,"",F24-F24*$G$16) | H24: =IFERROR(G24*$H$16,"") | I24: =IFERROR(ROUND(H24*$I$16,0),"") | J24: =IFERROR((I24-H24)/I24,"")
B25: Includes dust cover and packing carton | G25: =IF(F25-F25*$G$16=0,"",F25-F25*$G$16) | H25: =IFERROR(G25*$H$16,"") | I25: =IFERROR(ROUND(H25*$I$16,0),"") | J25: =IFERROR((I25-H25)/I25,"")
B26: 1 x Stage D-Rack, etherCON MADI, 1 PSU, iso transformer, rack kit (7U) - 32 mic/line in / 8 line out | G26: =IF(F26-F26*$G$16=0,"",F26-F26*$G$16) | H26: =IFERROR(G26*$H$16,"") | I26: =IFERROR(ROUND(H26*$I$16,0),"") | J26: =IFERROR((I26-H26)/I26,"")
B27: 1 x 75m CAT6 Cable | G27: =IF(F27-F27*$G$16=0,"",F27-F27*$G$16) | H27: =IFERROR(G27*$H$16,"") | I27: =IFERROR(ROUND(H27*$I$16,0),"") | J27: =IFERROR((I27-H27)/I27,"")
G28: =IF(F28-F28*$G$16=0,"",F28-F28*$G$16) | H28: =IFERROR(G28*$H$16,"") | I28: =IFERROR(ROUND(H28*$I$16,0),"") | J28: =IFERROR((I28-H28)/I28,"")
A29: X-SD9-2P | B29: DiGiCo SD9 system - dual power supplies | E29: =ROUND(F29/0.55,0) -> 20022 | F29: 11012 | G29: =IF(F29-F29*$G$16=0,"",F29-F29*$G$16) -> 8809.6 | H29: =IFERROR(G29*$H$16,"") -> 1295011.2 | I29: =IFERROR(ROUND(H29*$I$16,0),"") -> 1838916 | J29: =IFERROR((I29-H29)/I29,"") -> 0.29577468
B30: 1 x SD9 surface - 24 faders, 2 etherCON MADI, 1 BNC MADI, 2 PSU, 2 GPIO | G30: =IF(F30-F30*$G$16=0,"",F30-F30*$G$16) | H30: =IFERROR(G30*$H$16,"") | I30: =IFERROR(ROUND(H30*$I$16,0),"") | J30: =IFERROR((I30-H30)/I30,"")
B31: 96 mono input channels, 48 mono output busses | G31: =IF(F31-F31*$G$16=0,"",F31-F31*$G$16) | H31: =IFERROR(G31*$H$16,"") | I31: =IFERROR(ROUND(H31*$I$16,0),"") | J31: =IFERROR((I31-H31)/I31,"")
B32: 2 mono or stereo solo busses, 1 stereo or LCR master buss | G32: =IF(F32-F32*$G$16=0,"",F32-F32*$G$16) | H32: =IFERROR(G32*$H$16,"") | I32: =IFERROR(ROUND(H32*$I$16,0),"") | J32: =IFERROR((I32-H32)/I32,"")
B33: 12 x 8 matrix, 12 CG/VCA, 12 FX, 16 x 32 band graphic eq’s | G33: =IF(F33-F33*$G$16=0,"",F33-F33*$G$16) | H33: =IFERROR(G33*$H$16,"") | I33: =IFERROR(ROUND(H33*$I$16,0),"") | J33: =IFERROR((I33-H33)/I33,"")
B34: Local I/O 8x Mic/Line inputs, 8x Line outputs, 4x AES I/O mono stream | G34: =IF(F34-F34*$G$16=0,"",F34-F34*$G$16) | H34: =IFERROR(G34*$H$16,"") | I34: =IFERROR(ROUND(H34*$I$16,0),"") | J34: =IFERROR((I34-H34)/I34,"")
B35: Includes dust cover and packing carton | G35: =IF(F35-F35*$G$16=0,"",F35-F35*$G$16) | H35: =IFERROR(G35*$H$16,"") | I35: =IFERROR(ROUND(H35*$I$16,0),"") | J35: =IFERROR((I35-H35)/I35,"")
B36: 1 x Stage D-Rack, etherCON MADI, 2 PSU, iso transformer, rack kit (7U) - 32 mic/line in / 8 line out | G36: =IF(F36-F36*$G$16=0,"",F36-F36*$G$16) | H36: =IFERROR(G36*$H$16,"") | I36: =IFERROR(ROUND(H36*$I$16,0),"") | J36: =IFERROR((I36-H36)/I36,"")
B37: 1 x 75m CAT6 Cable | G37: =IF(F37-F37*$G$16=0,"",F37-F37*$G$16) | H37: =IFERROR(G37*$H$16,"") | I37: =IFERROR(ROUND(H37*$I$16,0),"") | J37: =IFERROR((I37-H37)/I37,"")
G38: =IF(F38-F38*$G$16=0,"",F38-F38*$G$16) | H38: =IFERROR(G38*$H$16,"") | I38: =IFERROR(ROUND(H38*$I$16,0),"") | J38: =IFERROR((I38-H38)/I38,"")
A39: X-SD9-2P-2R | B39: DiGiCo SD9 Rack Pack system | E39: =ROUND(F39/0.55,0) -> 23253 | F39: 12789 | G39: =IF(F39-F39*$G$16=0,"",F39-F39*$G$16) -> 10231.2 | H39: =IFERROR(G39*$H$16,"") -> 1503986.4 | I39: =IFERROR(ROUND(H39*$I$16,0),"") -> 2135661 | J39: =IFERROR((I39-H39)/I39,"") -> 0.29577475
B40: 1 x SD9 surface - 24 faders, 2 etherCON MADI, 1 BNC MADI, 2 PSU, 2 GPIO | G40: =IF(F40-F40*$G$16=0,"",F40-F40*$G$16) | H40: =IFERROR(G40*$H$16,"") | I40: =IFERROR(ROUND(H40*$I$16,0),"") | J40: =IFERROR((I40-H40)/I40,"")
B41: 96 mono input channels, 48 mono output busses | G41: =IF(F41-F41*$G$16=0,"",F41-F41*$G$16) | H41: =IFERROR(G41*$H$16,"") | I41: =IFERROR(ROUND(H41*$I$16,0),"") | J41: =IFERROR((I41-H41)/I41,"")
B42: 2 mono or stereo solo busses, 1 stereo or LCR master buss | G42: =IF(F42-F42*$G$16=0,"",F42-F42*$G$16) | H42: =IFERROR(G42*$H$16,"") | I42: =IFERROR(ROUND(H42*$I$16,0),"") | J42: =IFERROR((I42-H42)/I42,"")
B43: 12 x 8 matrix, 12 CG/VCA, 12 FX, 16 x 32 band graphic eq’s | G43: =IF(F43-F43*$G$16=0,"",F43-F43*$G$16) | H43: =IFERROR(G43*$H$16,"") | I43: =IFERROR(ROUND(H43*$I$16,0),"") | J43: =IFERROR((I43-H43)/I43,"")
B44: Local I/O 8x Mic/Line inputs, 8x Line outputs, 4x AES I/O mono stream | G44: =IF(F44-F44*$G$16=0,"",F44-F44*$G$16) | H44: =IFERROR(G44*$H$16,"") | I44: =IFERROR(ROUND(H44*$I$16,0),"") | J44: =IFERROR((I44-H44)/I44,"")
B45: Includes dust cover and packing carton | G45: =IF(F45-F45*$G$16=0,"",F45-F45*$G$16) | H45: =IFERROR(G45*$H$16,"") | I45: =IFERROR(ROUND(H45*$I$16,0),"") | J45: =IFERROR((I45-H45)/I45,"")
B46: 2 x Stage D-Rack, etherCON MADI, 2 PSU, iso transformer, rack kit (7U) - 32 mic/line in / 8 line out | G46: =IF(F46-F46*$G$16=0,"",F46-F46*$G$16) | H46: =IFERROR(G46*$H$16,"") | I46: =IFERROR(ROUND(H46*$I$16,0),"") | J46: =IFERROR((I46-H46)/I46,"")
B47: 2 x 75m CAT6 Cable | G47: =IF(F47-F47*$G$16=0,"",F47-F47*$G$16) | H47: =IFERROR(G47*$H$16,"") | I47: =IFERROR(ROUND(H47*$I$16,0),"") | J47: =IFERROR((I47-H47)/I47,"")
G48: =IF(F48-F48*$G$16=0,"",F48-F48*$G$16) | H48: =IFERROR(G48*$H$16,"") | I48: =IFERROR(ROUND(H48*$I$16,0),"") | J48: =IFERROR((I48-H48)/I48,"")
A49: X-SD9-D2-1 | B49: DiGiCo SD9 D2 system | E49: =ROUND(F49/0.55,0) -> 21282 | F49: 11705 | G49: =IF(F49-F49*$G$16=0,"",F49-F49*$G$16) -> 9364 | H49: =IFERROR(G49*$H$16,"") -> 1376508 | I49: =IFERROR(ROUND(H49*$I$16,0),"") -> 1954641 | J49: =IFERROR((I49-H49)/I49,"") -> 0.29577452
B50: 1 x SD9 surface - 24 faders, 2 etherCON MADI, 1 BNC MADI, 2 PSU, 2 GPIO | G50: =IF(F50-F50*$G$16=0,"",F50-F50*$G$16) | H50: =IFERROR(G50*$H$16,"") | I50: =IFERROR(ROUND(H50*$I$16,0),"") | J50: =IFERROR((I50-H50)/I50,"")
B51: 96 mono input channels, 48 mono output busses | G51: =IF(F51-F51*$G$16=0,"",F51-F51*$G$16) | H51: =IFERROR(G51*$H$16,"") | I51: =IFERROR(ROUND(H51*$I$16,0),"") | J51: =IFERROR((I51-H51)/I51,"")
B52: 2 mono or stereo solo busses, 1 stereo or LCR master buss | G52: =IF(F52-F52*$G$16=0,"",F52-F52*$G$16) | H52: =IFERROR(G52*$H$16,"") | I52: =IFERROR(ROUND(H52*$I$16,0),"") | J52: =IFERROR((I52-H52)/I52,"")
B53: 12 x 8 matrix, 12 CG/VCA, 12 FX, 16 x 32 band graphic eq’s | G53: =IF(F53-F53*$G$16=0,"",F53-F53*$G$16) | H53: =IFERROR(G53*$H$16,"") | I53: =IFERROR(ROUND(H53*$I$16,0),"") | J53: =IFERROR((I53-H53)/I53,"")
B54: Local I/O 8x Mic/Line inputs, 8x Line outputs, 4x AES I/O mono stream | G54: =IF(F54-F54*$G$16=0,"",F54-F54*$G$16) | H54: =IFERROR(G54*$H$16,"") | I54: =IFERROR(ROUND(H54*$I$16,0),"") | J54: =IFERROR((I54-H54)/I54,"")
B55: Includes dust cover and packing carton | G55: =IF(F55-F55*$G$16=0,"",F55-F55*$G$16) | H55: =IFERROR(G55*$H$16,"") | I55: =IFERROR(ROUND(H55*$I$16,0),"") | J55: =IFERROR((I55-H55)/I55,"")
B56: 1 x Stage D2 Rack, 2 etherCON MADI, 2 PSU - 48 mic/line in / 16 line out | G56: =IF(F56-F56*$G$16=0,"",F56-F56*$G$16) | H56: =IFERROR(G56*$H$16,"") | I56: =IFERROR(ROUND(H56*$I$16,0),"") | J56: =IFERROR((I56-H56)/I56,"")
B57: 2 x 75m CAT6 Cable | G57: =IF(F57-F57*$G$16=0,"",F57-F57*$G$16) | H57: =IFERROR(G57*$H$16,"") | I57: =IFERROR(ROUND(H57*$I$16,0),"") | J57: =IFERROR((I57-H57)/I57,"")
G58: =IF(F58-F58*$G$16=0,"",F58-F58*$G$16) | H58: =IFERROR(G58*$H$16,"") | I58: =IFERROR(ROUND(H58*$I$16,0),"") | J58: =IFERROR((I58-H58)/I58,"")
A59: DiGiCo SD9 Surface Only | G59: =IF(F59-F59*$G$16=0,"",F59-F59*$G$16) | H59: =IFERROR(G59*$H$16,"") | I59: =IFERROR(ROUND(H59*$I$16,0),"") | J59: =IFERROR((I59-H59)/I59,"")
G60: =IF(F60-F60*$G$16=0,"",F60-F60*$G$16) | H60: =IFERROR(G60*$H$16,"") | I60: =IFERROR(ROUND(H60*$I$16,0),"") | J60: =IFERROR((I60-H60)/I60,"")
A61: X-SD9-WS | B61: DiGiCo SD9 surface - single power supply | E61: =ROUND(F61/0.55,0) -> 15211 | F61: 8366 | G61: =IF(F61-F61*$G$16=0,"",F61-F61*$G$16) -> 6692.8 | H61: =IFERROR(G61*$H$16,"") -> 983841.6 | I61: =IFERROR(ROUND(H61*$I$16,0),"") -> 1397055 | J61: =IFERROR((I61-H61)/I61,"") -> 0.29577461
B62: SD9 surface - 24 faders, 2 etherCON MADI, 1 BNC MADI, 1 PSU, 2 GPIO | G62: =IF(F62-F62*$G$16=0,"",F62-F62*$G$16) | H62: =IFERROR(G62*$H$16,"") | I62: =IFERROR(ROUND(H62*$I$16,0),"") | J62: =IFERROR((I62-H62)/I62,"")
B63: 96 mono input channels, 48 mono output busses | G63: =IF(F63-F63*$G$16=0,"",F63-F63*$G$16) | H63: =IFERROR(G63*$H$16,"") | I63: =IFERROR(ROUND(H63*$I$16,0),"") | J63: =IFERROR((I63-H63)/I63,"")
B64: 2 mono or stereo solo busses, 1 stereo or LCR master buss | G64: =IF(F64-F64*$G$16=0,"",F64-F64*$G$16) | H64: =IFERROR(G64*$H$16,"") | I64: =IFERROR(ROUND(H64*$I$16,0),"") | J64: =IFERROR((I64-H64)/I64,"")
B65: 12 x 8 matrix, 12 CG/VCA, 12 FX, 16 x 32 band graphic eq’s | G65: =IF(F65-F65*$G$16=0,"",F65-F65*$G$16) | H65: =IFERROR(G65*$H$16,"") | I65: =IFERROR(ROUND(H65*$I$16,0),"") | J65: =IFERROR((I65-H65)/I65,"")
B66: Local I/O 8x Mic/Line inputs, 8x Line outputs, 4x AES I/O mono stream | G66: =IF(F66-F66*$G$16=0,"",F66-F66*$G$16) | H66: =IFERROR(G66*$H$16,"") | I66: =IFERROR(ROUND(H66*$I$16,0),"") | J66: =IFERROR((I66-H66)/I66,"")
B67: Includes dust cover and packing carton | G67: =IF(F67-F67*$G$16=0,"",F67-F67*$G$16) | H67: =IFERROR(G67*$H$16,"") | I67: =IFERROR(ROUND(H67*$I$16,0),"") | J67: =IFERROR((I67-H67)/I67,"")
B68: Dimensions; 878(w) x 785(d) x 258(h) mm Weight; 36Kg | G68: =IF(F68-F68*$G$16=0,"",F68-F68*$G$16) | H68: =IFERROR(G68*$H$16,"") | I68: =IFERROR(ROUND(H68*$I$16,0),"") | J68: =IFERROR((I68-H68)/I68,"")
G69: =IF(F69-F69*$G$16=0,"",F69-F69*$G$16) | H69: =IFERROR(G69*$H$16,"") | I69: =IFERROR(ROUND(H69*$I$16,0),"") | J69: =IFERROR((I69-H69)/I69,"")
A70: X-SD9-WS-2P | B70: DiGiCo SD9 surface - dual power supplies | E70: =ROUND(F70/0.55,0) -> 16738 | F70: 9206 | G70: =IF(F70-F70*$G$16=0,"",F70-F70*$G$16) -> 7364.8 | H70: =IFERROR(G70*$H$16,"") -> 1082625.6 | I70: =IFERROR(ROUND(H70*$I$16,0),"") -> 1537328 | J70: =IFERROR((I70-H70)/I70,"") -> 0.29577449
B71: SD9 surface - 24 faders, 2 etherCON MADI, 1 BNC MADI, 2 PSU, 2 GPIO | G71: =IF(F71-F71*$G$16=0,"",F71-F71*$G$16) | H71: =IFERROR(G71*$H$16,"") | I71: =IFERROR(ROUND(H71*$I$16,0),"") | J71: =IFERROR((I71-H71)/I71,"")
B72: 96 mono input channels, 48 mono output busses | G72: =IF(F72-F72*$G$16=0,"",F72-F72*$G$16) | H72: =IFERROR(G72*$H$16,"") | I72: =IFERROR(ROUND(H72*$I$16,0),"") | J72: =IFERROR((I72-H72)/I72,"")
B73: 2 mono or stereo solo busses, 1 stereo or LCR master buss | G73: =IF(F73-F73*$G$16=0,"",F73-F73*$G$16) | H73: =IFERROR(G73*$H$16,"") | I73: =IFERROR(ROUND(H73*$I$16,0),"") | J73: =IFERROR((I73-H73)/I73,"")
B74: 12 x 8 matrix, 12 CG/VCA, 12 FX, 16 x 32 band graphic eq’s | G74: =IF(F74-F74*$G$16=0,"",F74-F74*$G$16) | H74: =IFERROR(G74*$H$16,"") | I74: =IFERROR(ROUND(H74*$I$16,0),"") | J74: =IFERROR((I74-H74)/I74,"")
B75: Local I/O 8x Mic/Line inputs, 8x Line outputs, 4x AES I/O mono stream | G75: =IF(F75-F75*$G$16=0,"",F75-F75*$G$16) | H75: =IFERROR(G75*$H$16,"") | I75: =IFERROR(ROUND(H75*$I$16,0),"") | J75: =IFERROR((I75-H75)/I75,"")
B76: Includes dust cover and packing carton | G76: =IF(F76-F76*$G$16=0,"",F76-F76*$G$16) | H76: =IFERROR(G76*$H$16,"") | I76: =IFERROR(ROUND(H76*$I$16,0),"") | J76: =IFERROR((I76-H76)/I76,"")
B77: Dimensions; 878(w) x 785(d) x 258(h) mm Weight; 36Kg | G77: =IF(F77-F77*$G$16=0,"",F77-F77*$G$16) | H77: =IFERROR(G77*$H$16,"") | I77: =IFERROR(ROUND(H77*$I$16,0),"") | J77: =IFERROR((I77-H77)/I77,"")
G78: =IF(F78-F78*$G$16=0,"",F78-F78*$G$16) | H78: =IFERROR(G78*$H$16,"") | I78: =IFERROR(ROUND(H78*$I$16,0),"") | J78: =IFERROR((I78-H78)/I78,"")
A79: DiGiCo SD9 Surface Options | G79: =IF(F79-F79*$G$16=0,"",F79-F79*$G$16) | H79: =IFERROR(G79*$H$16,"") | I79: =IFERROR(ROUND(H79*$I$16,0),"") | J79: =IFERROR((I79-H79)/I79,"")
G80: =IF(F80-F80*$G$16=0,"",F80-F80*$G$16) | H80: =IFERROR(G80*$H$16,"") | I80: =IFERROR(ROUND(H80*$I$16,0),"") | J80: =IFERROR((I80-H80)/I80,"")
A81: X-SD9/11-OP-UP | B81: DiGiCo SD9/SD11 HMA optics upgrade | E81: =ROUND(F81/0.55,0) -> 7364 | F81: 4050 | G81: =IF(F81-F81*$G$16=0,"",F81-F81*$G$16) -> 3240 | H81: =IFERROR(G81*$H$16,"") -> 476280 | I81: =IFERROR(ROUND(H81*$I$16,0),"") -> 676318 | J81: =IFERROR((I81-H81)/I81,"") -> 0.29577506
B82: HMA expanded beam optics upgrade for SD9/SD11 surface. | G82: =IF(F82-F82*$G$16=0,"",F82-F82*$G$16) | H82: =IFERROR(G82*$H$16,"") | I82: =IFERROR(ROUND(H82*$I$16,0),"") | J82: =IFERROR((I82-H82)/I82,"")
G83: =IF(F83-F83*$G$16=0,"",F83-F83*$G$16) | H83: =IFERROR(G83*$H$16,"") | I83: =IFERROR(ROUND(H83*$I$16,0),"") | J83: =IFERROR((I83-H83)/I83,"")
A84: X-SD9/11-NC-UP | B84: DiGiCo SD9/SD11 OpticalCON optics upgrade | E84: =ROUND(F84/0.55,0) -> 6251 | F84: 3438 | G84: =IF(F84-F84*$G$16=0,"",F84-F84*$G$16) -> 2750.4 | H84: =IFERROR(G84*$H$16,"") -> 404308.8 | I84: =IFERROR(ROUND(H84*$I$16,0),"") -> 574118 | J84: =IFERROR((I84-H84)/I84,"") -> 0.29577404
B85: OpticalCON optics upgrade for SD9/SD11 surface. | G85: =IF(F85-F85*$G$16=0,"",F85-F85*$G$16) | H85: =IFERROR(G85*$H$16,"") | I85: =IFERROR(ROUND(H85*$I$16,0),"") | J85: =IFERROR((I85-H85)/I85,"")
G86: =IF(F86-F86*$G$16=0,"",F86-F86*$G$16) | H86: =IFERROR(G86*$H$16,"") | I86: =IFERROR(ROUND(H86*$I$16,0),"") | J86: =IFERROR((I86-H86)/I86,"")
A87: X-SD9/11-ST-UP | B87: DiGiCo SD9/SD11 ST optics upgrade | E87: =ROUND(F87/0.55,0) -> 6038 | F87: 3321 | G87: =IF(F87-F87*$G$16=0,"",F87-F87*$G$16) -> 2656.8 | H87: =IFERROR(G87*$H$16,"") -> 390549.6 | I87: =IFERROR(ROUND(H87*$I$16,0),"") -> 554580 | J87: =IFERROR((I87-H87)/I87,"") -> 0.2957741
B88: ST optics upgrade for SD9/SD11 surface. | G88: =IF(F88-F88*$G$16=0,"",F88-F88*$G$16) | H88: =IFERROR(G88*$H$16,"") | I88: =IFERROR(ROUND(H88*$I$16,0),"") | J88: =IFERROR((I88-H88)/I88,"")
G89: =IF(F89-F89*$G$16=0,"",F89-F89*$G$16) | H89: =IFERROR(G89*$H$16,"") | I89: =IFERROR(ROUND(H89*$I$16,0),"") | J89: =IFERROR((I89-H89)/I89,"")
A90: MOD-FOURIER-SD9 | B90: DiGiCo SD9 Fourier Audio interface card | E90: =ROUND(F90/0.55,0) -> 1864 | F90: 1025 | G90: =IF(F90-F90*$G$16=0,"",F90-F90*$G$16) -> 820 | H90: =IFERROR(G90*$H$16,"") -> 120540 | I90: =IFERROR(ROUND(H90*$I$16,0),"") -> 171167 | J90: =IFERROR((I90-H90)/I90,"") -> 0.29577547
B91: Fourier Audio interface card. 64ch Dante I/O. 3 x RJ45 | G91: =IF(F91-F91*$G$16=0,"",F91-F91*$G$16) | H91: =IFERROR(G91*$H$16,"") | I91: =IFERROR(ROUND(H91*$I$16,0),"") | J91: =IFERROR((I91-H91)/I91,"")
G92: =IF(F92-F92*$G$16=0,"",F92-F92*$G$16) | H92: =IFERROR(G92*$H$16,"") | I92: =IFERROR(ROUND(H92*$I$16,0),"") | J92: =IFERROR((I92-H92)/I92,"")
A93: MOD-WAVES-SD9 | B93: DiGiCo SD9 Waves interface card | E93: =ROUND(F93/0.55,0) -> 1864 | F93: 1025 | G93: =IF(F93-F93*$G$16=0,"",F93-F93*$G$16) -> 820 | H93: =IFERROR(G93*$H$16,"") -> 120540 | I93: =IFERROR(ROUND(H93*$I$16,0),"") -> 171167 | J93: =IFERROR((I93-H93)/I93,"") -> 0.29577547
B94: Waves interface card. 64ch Soundgrid I/O. RJ45. | G94: =IF(F94-F94*$G$16=0,"",F94-F94*$G$16) | H94: =IFERROR(G94*$H$16,"") | I94: =IFERROR(ROUND(H94*$I$16,0),"") | J94: =IFERROR((I94-H94)/I94,"")
G95: =IF(F95-F95*$G$16=0,"",F95-F95*$G$16) | H95: =IFERROR(G95*$H$16,"") | I95: =IFERROR(ROUND(H95*$I$16,0),"") | J95: =IFERROR((I95-H95)/I95,"")
A96: SOFTWARE-SD9T | B96: DiGiCo SD9 T theatre-specific application software | E96: =ROUND(F96/0.55,0) -> 5455 | F96: 3000 | G96: =IF(F96-F96*$G$16=0,"",F96-F96*$G$16) -> 2400 | H96: =IFERROR(G96*$H$16,"") -> 352800 | I96: =IFERROR(ROUND(H96*$I$16,0),"") -> 500976 | J96: =IFERROR((I96-H96)/I96,"") -> 0.29577465
B97: Extensive Theatre specific software including - Auto Update, Aliases, Cue Editor, Matrix nodal delay, Players. 12 CG/VCA. | G97: =IF(F97-F97*$G$16=0,"",F97-F97*$G$16) | H97: =IFERROR(G97*$H$16,"") | I97: =IFERROR(ROUND(H97*$I$16,0),"") | J97: =IFERROR((I97-H97)/I97,"")
G98: =IF(F98-F98*$G$16=0,"",F98-F98*$G$16) | H98: =IFERROR(G98*$H$16,"") | I98: =IFERROR(ROUND(H98*$I$16,0),"") | J98: =IFERROR((I98-H98)/I98,"")
A99: SOFTWARE-SD9B | B99: DiGiCo SD9 B broadcast-specific application software | E99: =ROUND(F99/0.55,0) -> 2924 | F99: 1608 | G99: =IF(F99-F99*$G$16=0,"",F99-F99*$G$16) -> 1286.4 | H99: =IFERROR(G99*$H$16,"") -> 189100.8 | I99: =IFERROR(ROUND(H99*$I$16,0),"") -> 268523 | J99: =IFERROR((I99-H99)/I99,"") -> 0.29577429
B100: Adds Mix-minus output per channel, Mono / LR / LCR / LCRS / 5.1 busses, Buss Down/Up Mix, Talk to Buss, | G100: =IF(F100-F100*$G$16=0,"",F100-F100*$G$16) | H100: =IFERROR(G100*$H$16,"") | I100: =IFERROR(ROUND(H100*$I$16,0),"") | J100: =IFERROR((I100-H100)/I100,"")
B101: Backstop PFL and Auto PFL, 8 source Monitor matrix, 3 Speaker select | G101: =IF(F101-F101*$G$16=0,"",F101-F101*$G$16) | H101: =IFERROR(G101*$H$16,"") | I101: =IFERROR(ROUND(H101*$I$16,0),"") | J101: =IFERROR((I101-H101)/I101,"")
G102: =IF(F102-F102*$G$16=0,"",F102-F102*$G$16) | H102: =IFERROR(G102*$H$16,"") | I102: =IFERROR(ROUND(H102*$I$16,0),"") | J102: =IFERROR((I102-H102)/I102,"")
A103: MOD-SDRR-PSU | B103: DiGiCo surface remote rack PSU | E103: =ROUND(F103/0.55,0) -> 1955 | F103: 1075.5 | G103: =IF(F103-F103*$G$16=0,"",F103-F103*$G$16) -> 860.4 | H103: =IFERROR(G103*$H$16,"") -> 126478.8 | I103: =IFERROR(ROUND(H103*$I$16,0),"") -> 179600 | J103: =IFERROR((I103-H103)/I103,"") -> 0.29577506
B104: Includes surface module, 3U rackmount module with two PSU sockets, 5m cable | G104: =IF(F104-F104*$G$16=0,"",F104-F104*$G$16) | H104: =IFERROR(G104*$H$16,"") | I104: =IFERROR(ROUND(H104*$I$16,0),"") | J104: =IFERROR((I104-H104)/I104,"")
G105: =IF(F105-F105*$G$16=0,"",F105-F105*$G$16) | H105: =IFERROR(G105*$H$16,"") | I105: =IFERROR(ROUND(H105*$I$16,0),"") | J105: =IFERROR((I105-H105)/I105,"")
...

Sheet SD 10
B1: DiGiCo SDTen Distributor Price List
B3: Sept 2024
B5: Unit 10 Silverglade Business Park, Leatherhead Road
B6: Chessington, Surrey, KT9 2QL
B7: Tel; +44 1372 845600
B8: Fax; +44 1372 845656
B9: email; sales@digiconsoles.com
B10: web; www.digiconsoles.com
B12: FCA Glenrothes KY7 4NX. E&OE. Prices, Products and Specification are subject to change without notice.
B13: This price list supercedes all previous price lists
A15: Product Code | B15: Description | E15: List (£) | F15: Distributor (£) | G15: Disc. () | H15: HT Buy (INR) | I15: Customer Price | J15: Hi-Tech
G16: 0.2 | H16: 147 | I16: 1.42 | J16: Margin
A17: DiGiCo SDTen 32Bit System
B19: DiGiCo SDTen 32bit system | E19: =ROUND(F19/0.55,0) -> 74422 | F19: 40932 | G19: =IF(F19-F19*$G$16=0,"",F19-F19*$G$16) -> 32745.6 | H19: =IFERROR(G19*$H$16,"") -> 4813603.2 | I19: =IFERROR(ROUND(H19*$I$16,0),"") -> 6835317 | J19: =IFERROR((I19-H19)/I19,"") -> 0.29577469
B20: 1 x SDTen surface - 36+1 faders, HMA optics, 2 BNC MADI, 2 PSU | G20: =IF(F20-F20*$G$16=0,"",F20-F20*$G$16) | H20: =IFERROR(G20*$H$16,"") | I20: =IFERROR(ROUND(H20*$I$16,0),"") | J20: =IFERROR((I20-H20)/I20,"")
B21: 144 mono input channels, 64 mono output busses | G21: =IF(F21-F21*$G$16=0,"",F21-F21*$G$16) | H21: =IFERROR(G21*$H$16,"") | I21: =IFERROR(ROUND(H21*$I$16,0),"") | J21: =IFERROR((I21-H21)/I21,"")
B22: 2 mono or stereo solo busses. LR, LCR. LCRS or 5.1 master buss | G22: =IF(F22-F22*$G$16=0,"",F22-F22*$G$16) | H22: =IFERROR(G22*$H$16,"") | I22: =IFERROR(ROUND(H22*$I$16,0),"") | J22: =IFERROR((I22-H22)/I22,"")
B23: 24 x 24 matrix, 24 CG/VCA, 24 FX, 24 x 32 band graphic eq’s | G23: =IF(F23-F23*$G$16=0,"",F23-F23*$G$16) | H23: =IFERROR(G23*$H$16,"") | I23: =IFERROR(ROUND(H23*$I$16,0),"") | J23: =IFERROR((I23-H23)/I23,"")
B24: Local I/O 8 x Mic/Line inputs, 8 x Line outputs, 8 x AES I/O mono stream | G24: =IF(F24-F24*$G$16=0,"",F24-F24*$G$16) | H24: =IFERROR(G24*$H$16,"") | I24: =IFERROR(ROUND(H24*$I$16,0),"") | J24: =IFERROR((I24-H24)/I24,"")
B25: Includes dust cover & packing carton | G25: =IF(F25-F25*$G$16=0,"",F25-F25*$G$16) | H25: =IFERROR(G25*$H$16,"") | I25: =IFERROR(ROUND(H25*$I$16,0),"") | J25: =IFERROR((I25-H25)/I25,"")
B26: 1 x Stage SD-Rack, HMA optics, 2 BNC MADI, 2 MADI splits, dual PSU - 56 32bit mic/line in / 24 32bit line out / 8 AES out, packing carton | G26: =IF(F26-F26*$G$16=0,"",F26-F26*$G$16) | H26: =IFERROR(G26*$H$16,"") | I26: =IFERROR(ROUND(H26*$I$16,0),"") | J26: =IFERROR((I26-H26)/I26,"")
B27: 2 x 150m HMA optical cable on drum | G27: =IF(F27-F27*$G$16=0,"",F27-F27*$G$16) | H27: =IFERROR(G27*$H$16,"") | I27: =IFERROR(ROUND(H27*$I$16,0),"") | J27: =IFERROR((I27-H27)/I27,"")
G28: =IF(F28-F28*$G$16=0,"",F28-F28*$G$16) | H28: =IFERROR(G28*$H$16,"") | I28: =IFERROR(ROUND(H28*$I$16,0),"") | J28: =IFERROR((I28-H28)/I28,"")
A29: DiGiCo SDTen Surface | E29: =ROUND(F29/0.55,0) -> 0 | G29: =IF(F29-F29*$G$16=0,"",F29-F29*$G$16) | H29: =IFERROR(G29*$H$16,"") | I29: =IFERROR(ROUND(H29*$I$16,0),"") | J29: =IFERROR((I29-H29)/I29,"")
G30: =IF(F30-F30*$G$16=0,"",F30-F30*$G$16) | H30: =IFERROR(G30*$H$16,"") | I30: =IFERROR(ROUND(H30*$I$16,0),"") | J30: =IFERROR((I30-H30)/I30,"")
A31: X-SD10-WS | B31: DiGiCo SDTen surface - MADI only | E31: =ROUND(F31/0.55,0) -> 40451 | F31: 22248 | G31: =IF(F31-F31*$G$16=0,"",F31-F31*$G$16) -> 17798.4 | H31: =IFERROR(G31*$H$16,"") -> 2616364.8 | I31: =IFERROR(ROUND(H31*$I$16,0),"") -> 3715238 | J31: =IFERROR((I31-H31)/I31,"") -> 0.29577464
B32: SDTen surface - 36+1 faders, 2 BNC MADI, 2 PSU | G32: =IF(F32-F32*$G$16=0,"",F32-F32*$G$16) | H32: =IFERROR(G32*$H$16,"") | I32: =IFERROR(ROUND(H32*$I$16,0),"") | J32: =IFERROR((I32-H32)/I32,"")
B33: 144 mono input channels, 64 mono output busses | G33: =IF(F33-F33*$G$16=0,"",F33-F33*$G$16) | H33: =IFERROR(G33*$H$16,"") | I33: =IFERROR(ROUND(H33*$I$16,0),"") | J33: =IFERROR((I33-H33)/I33,"")
B34: 2 mono or stereo solo busses. LR, LCR. LCRS or 5.1 master buss | G34: =IF(F34-F34*$G$16=0,"",F34-F34*$G$16) | H34: =IFERROR(G34*$H$16,"") | I34: =IFERROR(ROUND(H34*$I$16,0),"") | J34: =IFERROR((I34-H34)/I34,"")
B35: 24 x 24 matrix, 24 CG/VCA, 24 FX, 24 x 32 band graphic eq’s | G35: =IF(F35-F35*$G$16=0,"",F35-F35*$G$16) | H35: =IFERROR(G35*$H$16,"") | I35: =IFERROR(ROUND(H35*$I$16,0),"") | J35: =IFERROR((I35-H35)/I35,"")
B36: Local I/O 8 x Mic/Line inputs, 8 x Line outputs, 8 x AES I/O mono stream | G36: =IF(F36-F36*$G$16=0,"",F36-F36*$G$16) | H36: =IFERROR(G36*$H$16,"") | I36: =IFERROR(ROUND(H36*$I$16,0),"") | J36: =IFERROR((I36-H36)/I36,"")
